Workbook

Sheet Raw Sales Transaction
A1: Transaction ID | B1: Date | C1: Branch | D1: Sales Rep | E1: Customer Name | F1: Product Code | G1: Product Name | H1: Qty | I1: Unit Price | J1: Discount | K1: Total Sales | L1: Payment Method | M1: Payment Status | N1: Channel
A2: TRX-1086 | B2: 2026-07-14 | C2: Cibubur | D2: Taufik Hidayat | E2: Galih Ramadhan | F2: P001 | G2: NMAX | H2: 1 | I2: 33500000 | J2: 1675000 | K2: 31825000 | L2: Kredit - Mandiri Tunas | M2: Lunas | N2: Pameran
A3: TRX-1192 | B3: 2026-07-16 | C3: Sukabumi | D3: Vino Bastian G. | E3: Made Ramadhan | F3: P001 | G3: NMAX | H3: 1 | I3: 33500000 | J3: 1005000 | K3: 32495000 | L3: Debit/Transfer | M3: Lunas | N3: Online - Website
A4: TRX-1108 | B4: 15 Juli 2026 | C4: Depok | D4: Joko Widodo S. | E4: Putra Hidayat | F4: P010 | G4: Freego | H4: 1 | I4: 22300000 | J4: 669000 | K4: 21631000 | L4: Cash | M4: Lunas | N4: Referral
A5: TRX-1106 | B5: 15/07/2026 | C5: Depok | D5: Lina Marlina | E5: Hana Anggraini | F5: P008 | G5: MX King | H5: 1 | I5: 24600000 | J5: 0 | K5: 24600000 | L5: Kredit - Adira | M5: Lunas | N5: Online - Website
A6: TRX-1124 | B6: 15/07/2026 | C6: Jakarta Selatan | D6: Fajar Nugraha | E6: Putra Saputra | F6: P007 | G6: XSR 155 | H6: 1 | I6: 41000000 | J6: 0 | K6: 41000000 | L6: Debit/Transfer | M6: Lunas | N6: Online - Website
A7: TRX-1094 | B7: 2026-07-14 | C7: Sukabumi | D7: Hadi Santoso | E7: Galih Kusuma | F7: P001 | G7: NMAX | H7: 1 | I7: 33500000 | J7: 1005000 | K7: 32495000 | L7: Cash | M7: Lunas | N7: Pameran
A8: TRX-1236 | B8: 2026-07-17 | C8: Cibubur | D8: Umi Kalsum | E8: Putra Kusuma | F8: P005 | G8: Fazzio | H8: 1 | I8: 21500000 | J8: 645000 | K8: 20855000 | L8: Kredit - FIF | M8: Lunas | N8: Online - Website
A9: TRX-1012 | B9: 2026-07-13 | C9: Bandung | D9: Puji Lestari | E9: Oscar Wijaya | F9: P006 | G9: Gear | H9: 1 | I9: 17800000 | J9: 890000 | K9: 16910000 | L9: Debit/Transfer | M9: Lunas | N9: Online - Website
A10: TRX-1148 | B10: 2026-07-16 | C10: Bekasi | D10: Sari Dewi | E10: Made Wijaya | F10: P001 | G10: NMAX | H10: 1 | I10: 33500000 | J10: 670000 | K10: 32830000 | L10: Cash | M10: Lunas | N10: Referral
A11: TRX-1213 | B11: 2026-07-17 | C11: Depok | D11: Eka Putri | E11: Ahmad Hidayat | F11: P001 | G11: NMAX | H11: 1 | I11: 33500000 | J11: 335000 | K11: 33165000 | L11: Kredit - FIF | M11: Lunas | N11: Showroom
A12: TRX-1340 | B12: 19/07/2026 | C12: Cibubur | D12: Kiki Amelia | E12: Eko Kusuma | F12: P007 | G12: XSR 155 | H12: 1 | I12: 41000000 | J12: 0 | K12: 41000000 | L12: Debit/Transfer | M12: DP | N12: Pameran
A13: TRX-1132 | B13: 2026-07-15 | C13: Karawang | D13: Kiki Amelia | E13: Citra Ramadhan | F13: P001 | G13: NMAX | H13: 1 | I13: 33500000 | J13: 1005000 | K13: 32495000 | L13: Debit/Transfer | M13: Proses Kredit | N13: Referral
... A61: TRX-1269 | B61: 2026-07-18 | C61: Serang | D61: Taufik Hidayat | E61: Eko Pratama | F61: P001 | G61: NMAX | H61: 1 | I61: 33500000 | J61: 670000 | K61: 32830000 | L61: Kredit - Mandiri Tunas | M61: Lunas | N61: Showroom
A62: TRX-1202 | B62: 17/07/2026 | C62: TANGERANG | E62: Fitri Anggraini | F62: P007 | G62: XSR 155 | H62: 1 | I62: 41000000 | J62: 0 | K62: 41000000 | L62: Kredit - FIF | M62: Proses Kredit | N62: Online - Website
A63: TRX-1013 | B63: 13/07/2026 | C63: Bandung | D63: Indah Permata | E63: Budi Hidayat | F63: P005 | G63: Fazzio | H63: 1 | I63: 21500000 | J63: 1075000 | K63: 20425000 | L63: Kredit - Adira | M63: Lunas | N63: Online - Website
A64: TRX-1200 | B64: 2026-07-17 | C64: Tangerang | D64: Mira Anjani | E64: Putra Hidayat | F64: P003 | G64: Lexi | H64: 1 | I64: 27400000 | J64: 1370000 | K64: 26030000 | L64: Kredit - Mandiri Tunas | M64: DP | N64: Referral
A65: TRX-1028 | B65: 13/07/2026 | C65: Cibubur | D65: Joko Widodo S. | E65: Tono Ramadhan | F65: P001 | G65: NMAX | H65: 2 | I65: 33500000 | J65: 0 | K65: 67000000 | L65: Debit/Transfer | M65: Lunas | N65: Showroom
A66: TRX-1103 | B66: 2026-07-15 | C66: Bekasi | D66: Vino Bastian G. | E66: Kevin Wijaya | F66: P002 | G66: Aerox | H66: 1 | I66: 29800000 | J66: 596000 | K66: 29204000 | L66: Kredit - Mandiri Tunas | M66: Lunas | N66: Online - Website
A67: TRX-1339 | B67: 2026-07-19 | C67: Cibubur | D67: Hadi Santoso | E67: Rendi Kusuma | F67: P003 | G67: Lexi | H67: 1 | I67: 27400000 | J67: 1370000 | K67: 26030000 | L67: Debit/Transfer | M67: Lunas | N67: Pameran
A68: TRX-1093 | B68: 14 Juli 2026 | C68: Sukabumi | D68: Hadi Santoso | E68: Dewi Hidayat | F68: P005 | G68: Fazzio | H68: 1 | I68: 21500000 | J68: 430000 | K68: 21070000 | L68: Kredit - Mandiri Tunas | M68: Lunas | N68: Referral
A69: TRX-1030 | B69: 13/07/2026 | C69: Sukabumi | D69: Lukman Hakim | E69: Jihan Firmansyah | F69: P006 | G69: Gear | H69: 1 | I69: 17800000 | J69: 178000 | K69: 17622000 | L69: Kredit - Adira | M69: Lunas | N69: Referral
A70: TRX-1059 | B70: 2026-07-14 | C70: Bogor | D70: Rangga Saputra | E70: Putra Hidayat | F70: P009 | G70: Grand Filano | H70: 1 | I70: 26900000 | J70: 807000 | K70: 26093000 | L70: Kredit - Adira | M70: Lunas | N70: Referral
A71: TRX-1193 | B71: 16/07/2026 | C71: Sukabumi | D71: Vino Bastian G. | E71: Lala Saputra | F71: P004 | G71: Mio | H71: 1 | I71: 18900000 | J71: 189000 | K71: 18711000 | L71: Debit/Transfer | M71: Lunas | N71: Pameran
A72: TRX-1223 | B72: 2026-07-17 | C72: Cikarang | D72: Kiki Amelia | E72: Tono Saputra | F72: P003 | G72: Lexi | H72: 1 | I72: 27400000 | J72: 0 | K72: 27400000 | L72: Cash | M72: DP | N72: Online - Website
A73: TRX-1278 | B73: 18/07/2026 | C73: Jakarta Selatan | D73: Lukman Hakim | E73: Budi Firmansyah | F73: P008 | G73: MX King | H73: 1 | I73: 24600000 | J73: 492000 | K73: 24108000 | L73: Cash | M73: Lunas | N73: Pameran
A74: TRX-1295 | B74: 18/07/2026 | C74: Sukabumi | D74: Indah Permata | E74: Kevin Ramadhan | F74: P003 | G74: Lexi | H74: 1 | I74: 27400000 | J74: 822000 | K74: 26578000 | L74: Kredit - FIF | M74: DP | N74: Referral
... A87: TRX-1052 | B87: 2026-07-14 | C87: Bandung | D87: Rangga Saputra | E87: Citra Ramadhan | F87: P002 | G87: Aerox | H87: 2 | I87: 29800000 | J87: 596000 | K87: 59004000 | L87: Kredit - Adira | M87: Lunas | N87: Online - Website
A88: TRX-1010 | B88: 13 Juli 2026 | C88: Depok | E88: Lala Lestari | F88: P010 | G88: Freego | H88: 1 | I88: 22300000 | J88: 0 | K88: 22300000 | L88: Cash | M88: Lunas | N88: Showroom
A89: TRX-1276 | B89: 2026-07-18 | C89: Jakarta Selatan | D89: Sari Dewi | E89: Siska Maharani | F89: P001 | G89: NMAX | H89: 1 | I89: 33500000 | J89: 335000 | K89: 0 | L89: Debit/Transfer | M89: Proses Kredit | N89: Showroom
A90: TRX-1017 | B90: 2026-07-13 | C90: Jakarta Timur | D90: Taufik Hidayat | E90: Putra Kusuma | F90: P009 | G90: Grand Filano | H90: 1 | I90: 26900000 | J90: 269000 | K90: 26631000 | L90: Debit/Transfer | M90: Lunas | N90: Showroom
A91: TRX-1248 | B91: 2026-07-18 | C91: Bandung | D91: Oki Setiawan | E91: Putra Maharani | F91: P007 | G91: XSR 155 | H91: 1 | I91: 41000000 | J91: 1230000 | K91: 39770000 | L91: Kredit - Mandiri Tunas | M91: Lunas | N91: Online - Website
A92: TRX-1001 | B92: 13 Juli 2026 | C92: Tangerang | D92: Taufik Hidayat | E92: Nia Saputra | F92: P002 | G92: Aerox | H92: 1 | I92: 29800000 | J92: 1490000 | K92: 28310000 | L92: Debit/Transfer | M92: Lunas | N92: Online - Website
A93: TRX-1159 | B93: 16 Juli 2026 | C93: Bandung | D93: Vino Bastian G. | E93: Kevin Pratama | F93: P002 | G93: Aerox | H93: 1 | I93: 29800000 | J93: 894000 | K93: 28906000 | L93: Kredit - Adira | M93: Lunas | N93: Pameran
A94: TRX-1139 | B94: 15/07/2026 | C94: Sukabumi | D94: Lukman Hakim | E94: Nia Pratama | F94: P004 | G94: Mio | H94: 1 | I94: 18900000 | J94: 0 | K94: 18900000 | L94: Cash | M94: Lunas | N94: Online - Website
A95: TRX-1063 | B95: 2026-07-14 | C95: Cikarang | D95: Kiki Amelia | E95: Irfan Ramadhan | F95: P003 | G95: Lexi | H95: 1 | I95: 27400000 | J95: 0 | K95: 27400000 | L95: Kredit - Mandiri Tunas | M95: Proses Kredit | N95: Online - Website
A96: TRX-1329 | B96: 2026-07-19 | C96: Jakarta Selatan | D96: Rudi Hartono | E96: Irfan Wijaya | F96: P010 | G96: Freego | H96: 1 | I96: 22300000 | J96: 446000 | K96: 21854000 | L96: Kredit - Adira | M96: Lunas | N96: Referral
A97: TRX-1160 | B97: 16/07/2026 | C97: Bandung | D97: Gita Ayu | E97: Nia Firmansyah | F97: P002 | G97: Aerox | H97: 1 | I97: 29800000 | J97: 894000 | K97: 28906000 | L97: Debit/Transfer | M97: Proses Kredit | N97: Referral
A98: TRX-1198 | B98: 16 Juli 2026 | C98: Sukabumi | D98: Lukman Hakim | E98: Jihan Lestari | F98: P004 | G98: Mio | H98: 1 | I98: 18900000 | J98: 567000 | K98: 18333000 | L98: Cash | M98: Proses Kredit | N98: Online - Website
A99: TRX-1071 | B99: 14/07/2026 | C99: Jakarta Timur | D99: Rudi Hartono | E99: Oscar Lestari | F99: P002 | G99: Aerox | H99: 1 | I99: 29800000 | J99: 596000 | K99: 29204000 | L99: Debit/Transfer | M99: Lunas | N99: Referral
A100: TRX-1181 | B100: 16/07/2026 | C100: Jakarta Selatan | D100: Lukman Hakim | E100: Made Hidayat | F100: P002 | G100: Aerox | H100: 1 | I100: 29800000 | J100: 1490000 | K100: 28310000 | L100: Kredit - Adira | M100: Lunas | N100: Referral
... A103: TRX-1128 | B103: 2026-07-15 | C103: Jaksel | D103: Vino Bastian G. | E103: Tono Hidayat | F103: P004 | G103: Mio | H103: 1 | I103: 18900000 | J103: 567000 | K103: 18333000 | L103: Kredit - Adira | M103: Lunas | N103: Pameran
A104: TRX-1334 | B104: 19 Juli 2026 | C104: Karawang | E104: Galih Ramadhan | F104: P010 | G104: Freego | H104: 1 | I104: 22300000 | J104: 446000 | K104: 21854000 | L104: Kredit - FIF | M104: Lunas | N104: Online - Website
A105: TRX-1296 | B105: 18 Juli 2026 | C105: Sukabumi | D105: Sari Dewi | E105: Budi Lestari | F105: P001 | G105: NMAX | H105: 1 | I105: 33500000 | J105: 335000 | K105: 33165000 | L105: Cash | M105: Lunas | N105: Showroom
A106: TRX-1249 | B106: 2026-07-18 | C106: Bandung | D106: Lukman Hakim | E106: Budi Anggraini | F106: P005 | G106: Fazzio | H106: 1 | I106: 21500000 | J106: 430000 | K106: 21070000 | L106: Kredit - FIF | M106: DP | N106: Referral
A107: TRX-1164 | B107: 2026-07-16 | C107: Cikarang | D107: Indah Permata | E107: Jihan Ramadhan | F107: P009 | G107: Grand Filano | H107: 1 | I107: 26900000 | J107: 1345000 | K107: 25555000 | L107: Kredit - FIF | M107: Lunas | N107: Referral
A108: TRX-1040 | B108: 14/07/2026 | C108: Bekasi | D108: Lukman Hakim | E108: Kevin Hidayat | F108: P001 | G108: NMAX | H108: 1 | I108: 33500000 | J108: 0 | K108: 33500000 | L108: Cash | M108: Lunas | N108: Pameran
A109: TRX-1113 | B109: 2026-07-15 | C109: Bandung | E109: Lala Pratama | F109: P005 | G109: Fazzio | H109: 1 | I109: 21500000 | J109: 1075000 | K109: 20425000 | L109: Debit/Transfer | M109: Lunas | N109: Referral
A110: TRX-1079 | B110: 2026-07-14 | C110: Karawang | D110: Mira Anjani | E110: Oscar Pratama | F110: P008 | G110: MX King | H110: 1 | I110: 24600000 | J110: 246000 | K110: 24354000 | L110: Debit/Transfer | M110: Lunas | N110: Referral
A111: TRX-1338 | B111: 2026-07-19 | C111: Cibubur | D111: Eka Putri | E111: Kevin Lestari | F111: P001 | G111: NMAX | H111: 1 | I111: 33500000 | J111: 670000 | K111: 32830000 | L111: Kredit - FIF | M111: Lunas | N111: Showroom
A112: TRX-1190 | B112: 16/07/2026 | C112: Cibubur | D112: Puji Lestari | E112: Putra Firmansyah | F112: P007 | G112: XSR 155 | H112: 1 | I112: 41000000 | J112: 410000 | K112: 40590000 | L112: Debit/Transfer | M112: Lunas | N112: Pameran
A113: TRX-1330 | B113: 2026-07-19 | C113: Jakarta Selatan | D113: Joko Widodo S. | E113: Citra Ramadhan | F113: P003 | G113: Lexi | H113: 1 | I113: 27400000 | J113: 822000 | K113: 0 | L113: Kredit - Adira | M113: Lunas | N113: Pameran
A114: TRX-1018 | B114: 2026-07-13 | C114: Jakarta Selatan | D114: Sari Dewi | E114: Fitri Wijaya | F114: P004 | G114: Mio | H114: 1 | I114: 18900000 | J114: 0 | K114: 18900000 | L114: Debit/Transfer | M114: Lunas | N114: Online - Website
A115: TRX-1274 | B115: 18/07/2026 | C115: Jakarta Timur | D115: Nanda Pratama | E115: Oscar Lestari | F115: P008 | G115: MX King | H115: 1 | I115: 24600000 | J115: 246000 | K115: 24354000 | L115: Kredit - Adira | M115: Lunas | N115: Showroom
A116: TRX-1229 | B116: 2026-07-17 | C116: Jakarta Selatan | D116: Rudi Hartono | E116: Irfan Saputra | F116: P003 | G116: Lexi | H116: 1 | I116: 27400000 | J116: 274000 | K116: 27126000 | L116: Kredit - Adira | M116: Lunas | N116: Online - Website
A117: TRX-1089 | B117: 2026-07-14 | C117: Sukabumi | D117: Rangga Saputra | E117: Dewi Hidayat | F117: P002 | G117: Aerox | H117: 1 | I117: 29800000 | J117: 894000 | K117: 28906000 | L117: Debit/Transfer | M117: Lunas | N117: Online - Website
A118: TRX-1170 | B118: 16/07/2026 | C118: Serang | D118: Sari Dewi | E118: Lala Lestari | F118: P009 | G118: Grand Filano | H118: 1 | I118: 26900000 | J118: 0 | K118: 26900000 | L118: Kredit - Mandiri Tunas | M118: Lunas | N118: Online - Website
A119: TRX-1315 | B119: 19/07/2026 | C119: Bogor | D119: Kiki Amelia | E119: Galih Anggraini | F119: P004 | G119: Mio | H119: 1 | I119: 18900000 | J119: 567000 | K119: 18333000 | L119: Kredit - Adira | M119: Lunas | N119: Online - Website
A120: TRX-1043 | B120: 2026-07-14 | C120: BEKASI | D120: Nanda Pratama | E120: Galih Wijaya | F120: P001 | G120: NMAX | H120: 1 | I120: 33500000 | J120: 335000 | K120: 33165000 | L120: Debit/Transfer | M120: Lunas | N120: Showroom
A121: TRX-1162 | B121: 2026-07-16 | C121: Bogor | D121: Puji Lestari | E121: Citra Firmansyah | F121: P003 | G121: Lexi | H121: 1 | I121: 27400000 | J121: 274000 | K121: 27126000 | L121: Kredit - Mandiri Tunas | M121: Lunas | N121: Showroom
... A127: TRX-1230 | B127: 2026-07-17 | C127: Jakarta Selatan | D127: Lina Marlina | E127: Hana Maharani | F127: P001 | G127: NMAX | H127: 1 | I127: 33500000 | J127: 335000 | K127: 33165000 | L127: Kredit - Adira | M127: Lunas | N127: Online - Website
A128: TRX-1180 | B128: 2026-07-16 | C128: Jakarta Selatan | E128: Made Hidayat | F128: P004 | G128: Mio | H128: 1 | I128: 18900000 | J128: 378000 | K128: 18522000 | L128: Kredit - Mandiri Tunas | M128: Lunas | N128: Online - Website
A129: TRX-1039 | B129: 14 Juli 2026 | C129: Bekasi | D129: Puji Lestari | E129: Tono Firmansyah | F129: P002 | G129: Aerox | H129: 1 | I129: 29800000 | J129: 596000 | K129: 29204000 | L129: Cash | M129: Lunas | N129: Pameran
A130: TRX-1239 | B130: 2026-07-17 | C130: Sukabumi | D130: Lukman Hakim | E130: Dewi Wijaya | F130: P003 | G130: Lexi | H130: 1 | I130: 27400000 | J130: 0 | K130: 27400000 | L130: Cash | M130: DP | N130: Showroom
A131: TRX-1292 | B131: 18 Juli 2026 | C131: Sukabumi | E131: Oscar Kusuma | F131: P003 | G131: Lexi | H131: 1 | I131: 27400000 | J131: 0 | K131: 27400000 | L131: Cash | M131: DP | N131: Referral
A132: TRX-1243 | B132: 2026-07-18 | C132: BEKASI | D132: Joko Widodo S. | E132: Irfan Maharani | F132: P002 | G132: Aerox | H132: 1 | I132: 29800000 | J132: 298000 | K132: 29502000 | L132: Debit/Transfer | M132: Lunas | N132: Pameran
A133: TRX-1101 | B133: 2026-07-15 | C133: Bekasi | D133: Rangga Saputra | E133: Budi Anggraini | F133: P009 | G133: Grand Filano | H133: 1 | I133: 26900000 | J133: 0 | K133: 26900000 | L133: Cash | M133: DP | N133: Online - Website
A134: TRX-1035 | B134: 14/07/2026 | C134: Tangerang | D134: Sari Dewi | E134: Rendi Anggraini | F134: P010 | G134: Freego | H134: 1 | I134: 22300000 | J134: 669000 | K134: 21631000 | L134: Kredit - Adira | M134: Lunas | N134: Referral
A135: TRX-1111 | B135: 2026-07-15 | C135: Depok | D135: Rangga Saputra | E135: Ahmad Wijaya | F135: P002 | G135: Aerox | H135: 1 | I135: 29800000 | J135: 1490000 | K135: 28310000 | L135: Debit/Transfer | M135: Lunas | N135: Pameran
A136: TRX-1187 | B136: 2026-07-16 | C136: Karawang | D136: Mira Anjani | E136: Oscar Anggraini | F136: P002 | G136: Aerox | H136: 1 | I136: 29800000 | J136: 0 | K136: 29800000 | L136: Cash | M136: Lunas | N136: Referral
A137: TRX-1327 | B137: 2026-07-19 | C137: Jakarta Selatan | D137: Puji Lestari | E137: Siska Saputra | F137: P010 | G137: Freego | H137: 1 | I137: 22300000 | J137: 669000 | K137: 21631000 | L137: Debit/Transfer | M137: Lunas | N137: Referral
A138: TRX-1020 | B138: 2026-07-13 | C138: Jakarta Selatan | D138: Vino Bastian G. | E138: Dewi Wijaya | F138: P003 | G138: Lexi | H138: 1 | I138: 27400000 | J138: 0 | K138: 0 | L138: Cash | M138: Lunas | N138: Online - Website
A139: TRX-1218 | B139: 2026-07-17 | C139: Bandung | D139: Hadi Santoso | E139: Rendi Pratama | F139: P003 | G139: Lexi | H139: 1 | I139: 27400000 | J139: 548000 | K139: 26852000 | L139: Kredit - Adira | M139: DP | N139: Referral
A140: TRX-1045 | B140: 2026-07-14 | C140: Depok | D140: Taufik Hidayat | E140: Oscar Ramadhan | F140: P001 | G140: NMAX | H140: 1 | I140: 33500000 | J140: 1675000 | K140: 31825000 | L140: Kredit - Adira | M140: Lunas | N140: Showroom
A141: TRX-1214 | B141: 2026-07-17 | C141: Depok | D141: Umi Kalsum | E141: Fitri Lestari | F141: P004 | G141: Mio | H141: 1 | I141: 18900000 | J141: 0 | K141: 18900000 | L141: Kredit - Adira | M141: DP | N141: Showroom
A142: TRX-1115 | B142: 15/07/2026 | C142: Bogor | D142: Lukman Hakim | E142: Lala Firmansyah | F142: P006 | G142: Gear | H142: 1 | I142: 17800000 | J142: 534000 | K142: 17266000 | L142: Kredit - Mandiri Tunas | M142: Lunas | N142: Online - Website
A143: TRX-1189 | B143: 2026-07-16 | C143: Cibubur | D143: Oki Setiawan | E143: Galih Pratama | F143: P003 | G143: Lexi | H143: 1 | I143: 27400000 | J143: 0 | K143: 27400000 | L143: Debit/Transfer | M143: Lunas | N143: Showroom
... A154: TRX-1279 | B154: 18 Juli 2026 | C154: Jakarta Selatan | D154: Puji Lestari | E154: Putra Saputra | F154: P003 | G154: Lexi | H154: 1 | I154: 27400000 | J154: 0 | K154: 27400000 | L154: Cash | M154: Lunas | N154: Referral
A155: TRX-1029 | B155: 2026-07-13 | C155: Cibubur | E155: Rendi Pratama | F155: P003 | G155: Lexi | H155: 1 | I155: 27400000 | J155: 274000 | K155: 27126000 | L155: Debit/Transfer | M155: Lunas | N155: Referral
A156: TRX-1032 | B156: 2026-07-13 | C156: Sukabumi | D156: Doni Saputra | E156: Tono Hidayat | F156: P007 | G156: XSR 155 | H156: 2 | I156: 41000000 | J156: 4100000 | K156: 77900000 | L156: Kredit - FIF | M156: Proses Kredit | N156: Online - Website
A157: TRX-1056 | B157: 14 Juli 2026 | C157: Bogor | D157: Joko Widodo S. | E157: Citra Saputra | F157: P003 | G157: Lexi | H157: 1 | I157: 27400000 | J157: 1370000 | K157: 26030000 | L157: Kredit - FIF | M157: Lunas | N157: Pameran
A158: TRX-1173 | B158: 2026-07-16 | C158: Serang | D158: Umi Kalsum | E158: Fitri Hidayat | F158: P001 | G158: NMAX | H158: 1 | I158: 33500000 | J158: 335000 | K158: 33165000 | L158: Kredit - Mandiri Tunas | M158: Lunas | N158: Showroom
A159: TRX-1033 | B159: 2026-07-13 | C159: Sukabumi | D159: Rangga Saputra | E159: Citra Anggraini | F159: P008 | G159: MX King | H159: 1 | I159: 24600000 | J159: 0 | K159: 24600000 | L159: Kredit - Mandiri Tunas | M159: Lunas | N159: Pameran
A160: TRX-1219 | B160: 2026-07-17 | C160: Bogor | D160: Hadi Santoso | E160: Hana Ramadhan | F160: P005 | G160: Fazzio | H160: 1 | I160: 21500000 | J160: 1075000 | K160: 20425000 | L160: Kredit - FIF | M160: Lunas | N160: Showroom
A161: TRX-1049 | B161: 2026-07-14 | C161: Depok | D161: Eka Putri | E161: Kevin Wijaya | F161: P002 | G161: Aerox | H161: 1 | I161: 29800000 | J161: 298000 | K161: 29502000 | L161: Kredit - Adira | M161: Proses Kredit | N161: Online - Website
A162: TRX-1288 | B162: 2026-07-18 | C162: Cibubur | D162: Joko Widodo S. | E162: Budi Lestari | F162: P001 | G162: NMAX | H162: 1 | I162: 33500000 | J162: 0 | K162: 33500000 | L162: Kredit - Mandiri Tunas | M162: Lunas | N162: Showroom
A163: TRX-1232 | B163: 2026-07-17 | C163: Karawang | E163: Putra Saputra | F163: P001 | G163: NMAX | H163: 1 | I163: 33500000 | J163: 0 | K163: 33500000 | L163: Kredit - FIF | M163: Lunas | N163: Online - Website
A164: TRX-1034 | B164: 2026-07-14 | C164: Tangerang | D164: Indah Permata | E164: Qori Anggraini | F164: P001 | G164: NMAX | H164: 1 | I164: 33500000 | J164: 0 | K164: 33500000 | L164: Kredit - Mandiri Tunas | M164: Lunas | N164: Referral
A165: TRX-1036 | B165: 14 Juli 2026 | C165: TANGERANG | D165: Puji Lestari | E165: Jihan Pratama | F165: P007 | G165: XSR 155 | H165: 1 | I165: 41000000 | J165: 2050000 | K165: 38950000 | L165: Kredit - Adira | M165: Lunas | N165: Pameran
A166: TRX-1272 | B166: 18/07/2026 | C166: Jakarta Timur | D166: Eka Putri | E166: Hana Anggraini | F166: P001 | G166: NMAX | H166: 1 | I166: 33500000 | J166: 1005000 | K166: 32495000 | L166: Cash | M166: Lunas | N166: Referral
A167: TRX-1064 | B167: 2026-07-14 | C167: Serang | D167: Oki Setiawan | E167: Qori Lestari | F167: P006 | G167: Gear | H167: 1 | I167: 17800000 | J167: 0 | K167: 17800000 | L167: Debit/Transfer | M167: Lunas | N167: Pameran
A168: TRX-1158 | B168: 2026-07-16 | C168: Bandung | D168: Lina Marlina | E168: Budi Ramadhan | F168: P001 | G168: NMAX | H168: 1 | I168: 33500000 | J168: 670000 | K168: 32830000 | L168: Kredit - Adira | M168: Lunas | N168: Referral
A169: TRX-1129 | B169: 2026-07-15 | C169: Karawang | D169: Kiki Amelia | E169: Made Lestari | F169: P005 | G169: Fazzio | H169: 1 | I169: 21500000 | J169: 1075000 | K169: 20425000 | L169: Kredit - Mandiri Tunas | M169: Lunas | N169: Pameran
A170: TRX-1047 | B170: 2026-07-14 | C170: Depok | D170: Sari Dewi | E170: Citra Pratama | F170: P009 | G170: Grand Filano | H170: 1 | I170: 26900000 | J170: 269000 | K170: 26631000 | L170: Kredit - Mandiri Tunas | M170: Lunas | N170: Pameran
A171: TRX-1067 | B171: 2026-07-14 | C171: Serang | D171: Puji Lestari | E171: Oscar Saputra | F171: P001 | G171: NMAX | H171: 2 | I171: 33500000 | J171: 670000 | K171: 66330000 | L171: Cash | M171: Lunas | N171: Pameran
A172: TRX-1222 | B172: 2026-07-17 | C172: Cikarang | D172: Puji Lestari | E172: Nia Wijaya | F172: P007 | G172: XSR 155 | H172: 1 | I172: 41000000 | J172: 0 | K172: 41000000 | L172: Kredit - Mandiri Tunas | M172: Proses Kredit | N172: Referral
A173: TRX-1176 | B173: 2026-07-16 | C173: Jakarta Timur | D173: Nanda Pratama | E173: Tono Lestari | F173: P004 | G173: Mio | H173: 1 | I173: 18900000 | J173: 0 | K173: 18900000 | L173: Kredit - Mandiri Tunas | M173: Lunas | N173: Online - Website
A174: TRX-1332 | B174: 2026-07-19 | C174: Jakarta Selatan | D174: Rangga Saputra | E174: Rendi Saputra | F174: P001 | G174: NMAX | H174: 1 | I174: 33500000 | J174: 0 | K174: 33500000 | L174: Debit/Transfer | M174: Lunas | N174: Referral
A175: TRX-1341 | B175: 2026-07-19 | C175: Sukabumi | D175: Kiki Amelia | E175: Tono Ramadhan | F175: P001 | G175: NMAX | H175: 1 | I175: 33500000 | J175: 335000 | K175: 33165000 | L175: Debit/Transfer | M175: Lunas | N175: Pameran
... A177: TRX-1046 | B177: 2026-07-14 | C177: Depok | D177: Nanda Pratama | E177: Putra Hidayat | F177: P002 | G177: Aerox | H177: 1 | I177: 29800000 | J177: 596000 | K177: 29204000 | L177: Kredit - FIF | M177: Lunas | N177: Referral
...

Sheet Cleaning Sales Transaction
A1: Transaction ID | B1: Date | C1: Date Clean 1 | D1: Date Clean | E1: Branch | F1: Branch Clean | G1: Sales Rep | H1: Sales Rep Clean | I1: Customer Name | J1: Custumer Name Clean | K1: Product Code | L1: Product Name | M1: Qty | N1: Unit Price | O1: Discount | P1: Total Sales | Q1: Status Transaksi | R1: Payment Method | S1: Payment Status | T1: Channel | U1: Duplicate Check
A2: TRX-1086 | B2: 2026-07-14 | C2: =SUBSTITUTE(SUBSTITUTE(SUBSTITUTE(SUBSTITUTE(SUBSTITUTE(SUBSTITUTE(SUBSTITUTE(SUBSTITUTE(SUBSTITUTE(SUBSTITUTE(SUBSTITUTE(SUBSTITUTE(B2," Januari ","/01/")," Februari ","/02/")," Maret ","/03/")," April ","/04/")," Mei ","/05/")," Juni ","/06/")," Juli ","/07/")," Agustus ","/08/")," September ","/09/")," Oktober ","/10/")," November ","/11/")," Desember ","/12/") -> 2026-07-14 | D2: =IFERROR(DATE(VALUE(LEFT(C2,4)),VALUE(MID(C2,6,2)),VALUE(RIGHT(C2,2))),DATE(VALUE(RIGHT(C2,4)),VALUE(MID(C2,4,2)),VALUE(LEFT(C2,2)))) -> 46217 | E2: Cibubur | F2: =PROPER(TRIM(SUBSTITUTE(SUBSTITUTE(E2,"Jaksel","Jakarta Selatan"),"Tangerang Kota","Tangerang"))) -> Cibubur | G2: Taufik Hidayat | H2: =IF(G2="","Unknown",G2) -> Taufik Hidayat | I2: Galih Ramadhan | J2: =IF(I2="","Unknown",I2) -> Galih Ramadhan | K2: P001 | L2: NMAX | M2: 1 | N2: 33500000 | O2: 1675000 | P2: 31825000 | Q2: =IF(P2=0,"Batal/Refund","Normal") -> Normal | R2: Kredit - Mandiri Tunas | S2: Lunas | T2: Pameran | U2: =COUNTIF($A$2:$A$342,A2) -> 1
A3: TRX-1192 | B3: 2026-07-16 | C3: =SUBSTITUTE(SUBSTITUTE(SUBSTITUTE(SUBSTITUTE(SUBSTITUTE(SUBSTITUTE(SUBSTITUTE(SUBSTITUTE(SUBSTITUTE(SUBSTITUTE(SUBSTITUTE(SUBSTITUTE(B3," Januari ","/01/")," Februari ","/02/")," Maret ","/03/")," April ","/04/")," Mei ","/05/")," Juni ","/06/")," Juli ","/07/")," Agustus ","/08/")," September ","/09/")," Oktober ","/10/")," November ","/11/")," Desember ","/12/") -> 2026-07-16 | D3: =IFERROR(DATE(VALUE(LEFT(C3,4)),VALUE(MID(C3,6,2)),VALUE(RIGHT(C3,2))),DATE(VALUE(RIGHT(C3,4)),VALUE(MID(C3,4,2)),VALUE(LEFT(C3,2)))) -> 46219 | E3: Sukabumi | F3: =PROPER(TRIM(SUBSTITUTE(SUBSTITUTE(E3,"Jaksel","Jakarta Selatan"),"Tangerang Kota","Tangerang"))) -> Sukabumi | G3: Vino Bastian G. | H3: =IF(G3="","Unknown",G3) -> Vino Bastian G. | I3: Made Ramadhan | J3: =IF(I3="","Unknown",I3) -> Made Ramadhan | K3: P001 | L3: NMAX | M3: 1 | N3: 33500000 | O3: 1005000 | P3: 32495000 | Q3: =IF(P3=0,"Batal/Refund","Normal") -> Normal | R3: Debit/Transfer | S3: Lunas | T3: Online - Website | U3: =COUNTIF($A$2:$A$342,A3) -> 1
A4: TRX-1108 | B4: 15 Juli 2026 | C4: =SUBSTITUTE(SUBSTITUTE(SUBSTITUTE(SUBSTITUTE(SUBSTITUTE(SUBSTITUTE(SUBSTITUTE(SUBSTITUTE(SUBSTITUTE(SUBSTITUTE(SUBSTITUTE(SUBSTITUTE(B4," Januari ","/01/")," Februari ","/02/")," Maret ","/03/")," April ","/04/")," Mei ","/05/")," Juni ","/06/")," Juli ","/07/")," Agustus ","/08/")," September ","/09/")," Oktober ","/10/")," November ","/11/")," Desember ","/12/") -> 15/07/2026 | D4: =IFERROR(DATE(VALUE(LEFT(C4,4)),VALUE(MID(C4,6,2)),VALUE(RIGHT(C4,2))),DATE(VALUE(RIGHT(C4,4)),VALUE(MID(C4,4,2)),VALUE(LEFT(C4,2)))) -> 46218 | E4: Depok | F4: =PROPER(TRIM(SUBSTITUTE(SUBSTITUTE(E4,"Jaksel","Jakarta Selatan"),"Tangerang Kota","Tangerang"))) -> Depok | G4: Joko Widodo S. | H4: =IF(G4="","Unknown",G4) -> Joko Widodo S. | I4: Putra Hidayat | J4: =IF(I4="","Unknown",I4) -> Putra Hidayat | K4: P010 | L4: Freego | M4: 1 | N4: 22300000 | O4: 669000 | P4: 21631000 | Q4: =IF(P4=0,"Batal/Refund","Normal") -> Normal | R4: Cash | S4: Lunas | T4: Referral | U4: =COUNTIF($A$2:$A$342,A4) -> 1
A5: TRX-1106 | B5: 15/07/2026 | C5: =SUBSTITUTE(SUBSTITUTE(SUBSTITUTE(SUBSTITUTE(SUBSTITUTE(SUBSTITUTE(SUBSTITUTE(SUBSTITUTE(SUBSTITUTE(SUBSTITUTE(SUBSTITUTE(SUBSTITUTE(B5," Januari ","/01/")," Februari ","/02/")," Maret ","/03/")," April ","/04/")," Mei ","/05/")," Juni ","/06/")," Juli ","/07/")," Agustus ","/08/")," September ","/09/")," Oktober ","/10/")," November ","/11/")," Desember ","/12/") -> 15/07/2026 | D5: =IFERROR(DATE(VALUE(LEFT(C5,4)),VALUE(MID(C5,6,2)),VALUE(RIGHT(C5,2))),DATE(VALUE(RIGHT(C5,4)),VALUE(MID(C5,4,2)),VALUE(LEFT(C5,2)))) -> 46218 | E5: Depok | F5: =PROPER(TRIM(SUBSTITUTE(SUBSTITUTE(E5,"Jaksel","Jakarta Selatan"),"Tangerang Kota","Tangerang"))) -> Depok | G5: Lina Marlina | H5: =IF(G5="","Unknown",G5) -> Lina Marlina | I5: Hana Anggraini | J5: =IF(I5="","Unknown",I5) -> Hana Anggraini | K5: P008 | L5: MX King | M5: 1 | N5: 24600000 | O5: 0 | P5: 24600000 | Q5: =IF(P5=0,"Batal/Refund","Normal") -> Normal | R5: Kredit - Adira | S5: Lunas | T5: Online - Website | U5: =COUNTIF($A$2:$A$342,A5) -> 1
A6: TRX-1124 | B6: 15/07/2026 | C6: =SUBSTITUTE(SUBSTITUTE(SUBSTITUTE(SUBSTITUTE(SUBSTITUTE(SUBSTITUTE(SUBSTITUTE(SUBSTITUTE(SUBSTITUTE(SUBSTITUTE(SUBSTITUTE(SUBSTITUTE(B6," Januari ","/01/")," Februari ","/02/")," Maret ","/03/")," April ","/04/")," Mei ","/05/")," Juni ","/06/")," Juli ","/07/")," Agustus ","/08/")," September ","/09/")," Oktober ","/10/")," November ","/11/")," Desember ","/12/") -> 15/07/2026 | D6: =IFERROR(DATE(VALUE(LEFT(C6,4)),VALUE(MID(C6,6,2)),VALUE(RIGHT(C6,2))),DATE(VALUE(RIGHT(C6,4)),VALUE(MID(C6,4,2)),VALUE(LEFT(C6,2)))) -> 46218 | E6: Jakarta Selatan | F6: =PROPER(TRIM(SUBSTITUTE(SUBSTITUTE(E6,"Jaksel","Jakarta Selatan"),"Tangerang Kota","Tangerang"))) -> Jakarta Selatan | G6: Fajar Nugraha | H6: =IF(G6="","Unknown",G6) -> Fajar Nugraha | I6: Putra Saputra | J6: =IF(I6="","Unknown",I6) -> Putra Saputra | K6: P007 | L6: XSR 155 | M6: 1 | N6: 41000000 | O6: 0 | P6: 41000000 | Q6: =IF(P6=0,"Batal/Refund","Normal") -> Normal | R6: Debit/Transfer | S6: Lunas | T6: Online - Website | U6: =COUNTIF($A$2:$A$342,A6) -> 1
A7: TRX-1094 | B7: 2026-07-14 | C7: =SUBSTITUTE(SUBSTITUTE(SUBSTITUTE(SUBSTITUTE(SUBSTITUTE(SUBSTITUTE(SUBSTITUTE(SUBSTITUTE(SUBSTITUTE(SUBSTITUTE(SUBSTITUTE(SUBSTITUTE(B7," Januari ","/01/")," Februari ","/02/")," Maret ","/03/")," April ","/04/")," Mei ","/05/")," Juni ","/06/")," Juli ","/07/")," Agustus ","/08/")," September ","/09/")," Oktober ","/10/")," November ","/11/")," Desember ","/12/") -> 2026-07-14 | D7: =IFERROR(DATE(VALUE(LEFT(C7,4)),VALUE(MID(C7,6,2)),VALUE(RIGHT(C7,2))),DATE(VALUE(RIGHT(C7,4)),VALUE(MID(C7,4,2)),VALUE(LEFT(C7,2)))) -> 46217 | E7: Sukabumi | F7: =PROPER(TRIM(SUBSTITUTE(SUBSTITUTE(E7,"Jaksel","Jakarta Selatan"),"Tangerang Kota","Tangerang"))) -> Sukabumi | G7: Hadi Santoso | H7: =IF(G7="","Unknown",G7) -> Hadi Santoso | I7: Galih Kusuma | J7: =IF(I7="","Unknown",I7) -> Galih Kusuma | K7: P001 | L7: NMAX | M7: 1 | N7: 33500000 | O7: 1005000 | P7: 32495000 | Q7: =IF(P7=0,"Batal/Refund","Normal") -> Normal | R7: Cash | S7: Lunas | T7: Pameran | U7: =COUNTIF($A$2:$A$342,A7) -> 1
A8: TRX-1115 | B8: 15/07/2026 | C8: =SUBSTITUTE(SUBSTITUTE(SUBSTITUTE(SUBSTITUTE(SUBSTITUTE(SUBSTITUTE(SUBSTITUTE(SUBSTITUTE(SUBSTITUTE(SUBSTITUTE(SUBSTITUTE(SUBSTITUTE(B8," Januari ","/01/")," Februari ","/02/")," Maret ","/03/")," April ","/04/")," Mei ","/05/")," Juni ","/06/")," Juli ","/07/")," Agustus ","/08/")," September ","/09/")," Oktober ","/10/")," November ","/11/")," Desember ","/12/") -> 15/07/2026 | D8: =IFERROR(DATE(VALUE(LEFT(C8,4)),VALUE(MID(C8,6,2)),VALUE(RIGHT(C8,2))),DATE(VALUE(RIGHT(C8,4)),VALUE(MID(C8,4,2)),VALUE(LEFT(C8,2)))) -> 46218 | E8: Bogor | F8: =PROPER(TRIM(SUBSTITUTE(SUBSTITUTE(E8,"Jaksel","Jakarta Selatan"),"Tangerang Kota","Tangerang"))) -> Bogor | G8: Lukman Hakim | H8: =IF(G8="","Unknown",G8) -> Lukman Hakim | I8: Lala Firmansyah | J8: =IF(I8="","Unknown",I8) -> Lala Firmansyah | K8: P006 | L8: Gear | M8: 1 | N8: 17800000 | O8: 534000 | P8: 17266000 | Q8: =IF(P8=0,"Batal/Refund","Normal") -> Normal | R8: Kredit - Mandiri Tunas | S8: Lunas | T8: Online - Website | U8: =COUNTIF($A$2:$A$342,A8) -> 1
A9: TRX-1012 | B9: 2026-07-13 | C9: =SUBSTITUTE(SUBSTITUTE(SUBSTITUTE(SUBSTITUTE(SUBSTITUTE(SUBSTITUTE(SUBSTITUTE(SUBSTITUTE(SUBSTITUTE(SUBSTITUTE(SUBSTITUTE(SUBSTITUTE(B9," Januari ","/01/")," Februari ","/02/")," Maret ","/03/")," April ","/04/")," Mei ","/05/")," Juni ","/06/")," Juli ","/07/")," Agustus ","/08/")," September ","/09/")," Oktober ","/10/")," November ","/11/")," Desember ","/12/") -> 2026-07-13 | D9: =IFERROR(DATE(VALUE(LEFT(C9,4)),VALUE(MID(C9,6,2)),VALUE(RIGHT(C9,2))),DATE(VALUE(RIGHT(C9,4)),VALUE(MID(C9,4,2)),VALUE(LEFT(C9,2)))) -> 46216 | E9: Bandung | F9: =PROPER(TRIM(SUBSTITUTE(SUBSTITUTE(E9,"Jaksel","Jakarta Selatan"),"Tangerang Kota","Tangerang"))) -> Bandung | G9: Puji Lestari | H9: =IF(G9="","Unknown",G9) -> Puji Lestari | I9: Oscar Wijaya | J9: =IF(I9="","Unknown",I9) -> Oscar Wijaya | K9: P006 | L9: Gear | M9: 1 | N9: 17800000 | O9: 890000 | P9: 16910000 | Q9: =IF(P9=0,"Batal/Refund","Normal") -> Normal | R9: Debit/Transfer | S9: Lunas | T9: Online - Website | U9: =COUNTIF($A$2:$A$342,A9) -> 1
A10: TRX-1148 | B10: 2026-07-16 | C10: =SUBSTITUTE(SUBSTITUTE(SUBSTITUTE(SUBSTITUTE(SUBSTITUTE(SUBSTITUTE(SUBSTITUTE(SUBSTITUTE(SUBSTITUTE(SUBSTITUTE(SUBSTITUTE(SUBSTITUTE(B10," Januari ","/01/")," Februari ","/02/")," Maret ","/03/")," April ","/04/")," Mei ","/05/")," Juni ","/06/")," Juli ","/07/")," Agustus ","/08/")," September ","/09/")," Oktober ","/10/")," November ","/11/")," Desember ","/12/") -> 2026-07-16 | D10: =IFERROR(DATE(VALUE(LEFT(C10,4)),VALUE(MID(C10,6,2)),VALUE(RIGHT(C10,2))),DATE(VALUE(RIGHT(C10,4)),VALUE(MID(C10,4,2)),VALUE(LEFT(C10,2)))) -> 46219 | E10: Bekasi | F10: =PROPER(TRIM(SUBSTITUTE(SUBSTITUTE(E10,"Jaksel","Jakarta Selatan"),"Tangerang Kota","Tangerang"))) -> Bekasi | G10: Sari Dewi | H10: =IF(G10="","Unknown",G10) -> Sari Dewi | I10: Made Wijaya | J10: =IF(I10="","Unknown",I10) -> Made Wijaya | K10: P001 | L10: NMAX | M10: 1 | N10: 33500000 | O10: 670000 | P10: 32830000 | Q10: =IF(P10=0,"Batal/Refund","Normal") -> Normal | R10: Cash | S10: Lunas | T10: Referral | U10: =COUNTIF($A$2:$A$342,A10) -> 1
A11: TRX-1213 | B11: 2026-07-17 | C11: =SUBSTITUTE(SUBSTITUTE(SUBSTITUTE(SUBSTITUTE(SUBSTITUTE(SUBSTITUTE(SUBSTITUTE(SUBSTITUTE(SUBSTITUTE(SUBSTITUTE(SUBSTITUTE(SUBSTITUTE(B11," Januari ","/01/")," Februari ","/02/")," Maret ","/03/")," April ","/04/")," Mei ","/05/")," Juni ","/06/")," Juli ","/07/")," Agustus ","/08/")," September ","/09/")," Oktober ","/10/")," November ","/11/")," Desember ","/12/") -> 2026-07-17 | D11: =IFERROR(DATE(VALUE(LEFT(C11,4)),VALUE(MID(C11,6,2)),VALUE(RIGHT(C11,2))),DATE(VALUE(RIGHT(C11,4)),VALUE(MID(C11,4,2)),VALUE(LEFT(C11,2)))) -> 46220 | E11: Depok | F11: =PROPER(TRIM(SUBSTITUTE(SUBSTITUTE(E11,"Jaksel","Jakarta Selatan"),"Tangerang Kota","Tangerang"))) -> Depok | G11: Eka Putri | H11: =IF(G11="","Unknown",G11) -> Eka Putri | I11: Ahmad Hidayat | J11: =IF(I11="","Unknown",I11) -> Ahmad Hidayat | K11: P001 | L11: NMAX | M11: 1 | N11: 33500000 | O11: 335000 | P11: 33165000 | Q11: =IF(P11=0,"Batal/Refund","Normal") -> Normal | R11: Kredit - FIF | S11: Lunas | T11: Showroom | U11: =COUNTIF($A$2:$A$342,A11) -> 1
A12: TRX-1340 | B12: 19/07/2026 | C12: =SUBSTITUTE(SUBSTITUTE(SUBSTITUTE(SUBSTITUTE(SUBSTITUTE(SUBSTITUTE(SUBSTITUTE(SUBSTITUTE(SUBSTITUTE(SUBSTITUTE(SUBSTITUTE(SUBSTITUTE(B12," Januari ","/01/")," Februari ","/02/")," Maret ","/03/")," April ","/04/")," Mei ","/05/")," Juni ","/06/")," Juli ","/07/")," Agustus ","/08/")," September ","/09/")," Oktober ","/10/")," November ","/11/")," Desember ","/12/") -> 19/07/2026 | D12: =IFERROR(DATE(VALUE(LEFT(C12,4)),VALUE(MID(C12,6,2)),VALUE(RIGHT(C12,2))),DATE(VALUE(RIGHT(C12,4)),VALUE(MID(C12,4,2)),VALUE(LEFT(C12,2)))) -> 46222 | E12: Cibubur | F12: =PROPER(TRIM(SUBSTITUTE(SUBSTITUTE(E12,"Jaksel","Jakarta Selatan"),"Tangerang Kota","Tangerang"))) -> Cibubur | G12: Kiki Amelia | H12: =IF(G12="","Unknown",G12) -> Kiki Amelia | I12: Eko Kusuma | J12: =IF(I12="","Unknown",I12) -> Eko Kusuma | K12: P007 | L12: XSR 155 | M12: 1 | N12: 41000000 | O12: 0 | P12: 41000000 | Q12: =IF(P12=0,"Batal/Refund","Normal") -> Normal | R12: Debit/Transfer | S12: DP | T12: Pameran | U12: =COUNTIF($A$2:$A$342,A12) -> 1
A13: TRX-1132 | B13: 2026-07-15 | C13: =SUBSTITUTE(SUBSTITUTE(SUBSTITUTE(SUBSTITUTE(SUBSTITUTE(SUBSTITUTE(SUBSTITUTE(SUBSTITUTE(SUBSTITUTE(SUBSTITUTE(SUBSTITUTE(SUBSTITUTE(B13," Januari ","/01/")," Februari ","/02/")," Maret ","/03/")," April ","/04/")," Mei ","/05/")," Juni ","/06/")," Juli ","/07/")," Agustus ","/08/")," September ","/09/")," Oktober ","/10/")," November ","/11/")," Desember ","/12/") -> 2026-07-15 | D13: =IFERROR(DATE(VALUE(LEFT(C13,4)),VALUE(MID(C13,6,2)),VALUE(RIGHT(C13,2))),DATE(VALUE(RIGHT(C13,4)),VALUE(MID(C13,4,2)),VALUE(LEFT(C13,2)))) -> 46218 | E13: Karawang | F13: =PROPER(TRIM(SUBSTITUTE(SUBSTITUTE(E13,"Jaksel","Jakarta Selatan"),"Tangerang Kota","Tangerang"))) -> Karawang | G13: Kiki Amelia | H13: =IF(G13="","Unknown",G13) -> Kiki Amelia | I13: Citra Ramadhan | J13: =IF(I13="","Unknown",I13) -> Citra Ramadhan | K13: P001 | L13: NMAX | M13: 1 | N13: 33500000 | O13: 1005000 | P13: 32495000 | Q13: =IF(P13=0,"Batal/Refund","Normal") -> Normal | R13: Debit/Transfer | S13: Proses Kredit | T13: Referral | U13: =COUNTIF($A$2:$A$342,A13) -> 1
... A60: TRX-1269 | B60: 2026-07-18 | C60: =SUBSTITUTE(SUBSTITUTE(SUBSTITUTE(SUBSTITUTE(SUBSTITUTE(SUBSTITUTE(SUBSTITUTE(SUBSTITUTE(SUBSTITUTE(SUBSTITUTE(SUBSTITUTE(SUBSTITUTE(B60," Januari ","/01/")," Februari ","/02/")," Maret ","/03/")," April ","/04/")," Mei ","/05/")," Juni ","/06/")," Juli ","/07/")," Agustus ","/08/")," September ","/09/")," Oktober ","/10/")," November ","/11/")," Desember ","/12/") -> 2026-07-18 | D60: =IFERROR(DATE(VALUE(LEFT(C60,4)),VALUE(MID(C60,6,2)),VALUE(RIGHT(C60,2))),DATE(VALUE(RIGHT(C60,4)),VALUE(MID(C60,4,2)),VALUE(LEFT(C60,2)))) -> 46221 | E60: Serang | F60: =PROPER(TRIM(SUBSTITUTE(SUBSTITUTE(E60,"Jaksel","Jakarta Selatan"),"Tangerang Kota","Tangerang"))) -> Serang | G60: Taufik Hidayat | H60: =IF(G60="","Unknown",G60) -> Taufik Hidayat | I60: Eko Pratama | J60: =IF(I60="","Unknown",I60) -> Eko Pratama | K60: P001 | L60: NMAX | M60: 1 | N60: 33500000 | O60: 670000 | P60: 32830000 | Q60: =IF(P60=0,"Batal/Refund","Normal") -> Normal | R60: Kredit - Mandiri Tunas | S60: Lunas | T60: Showroom | U60: =COUNTIF($A$2:$A$342,A60) -> 1
A61: TRX-1202 | B61: 17/07/2026 | C61: =SUBSTITUTE(SUBSTITUTE(SUBSTITUTE(SUBSTITUTE(SUBSTITUTE(SUBSTITUTE(SUBSTITUTE(SUBSTITUTE(SUBSTITUTE(SUBSTITUTE(SUBSTITUTE(SUBSTITUTE(B61," Januari ","/01/")," Februari ","/02/")," Maret ","/03/")," April ","/04/")," Mei ","/05/")," Juni ","/06/")," Juli ","/07/")," Agustus ","/08/")," September ","/09/")," Oktober ","/10/")," November ","/11/")," Desember ","/12/") -> 17/07/2026 | D61: =IFERROR(DATE(VALUE(LEFT(C61,4)),VALUE(MID(C61,6,2)),VALUE(RIGHT(C61,2))),DATE(VALUE(RIGHT(C61,4)),VALUE(MID(C61,4,2)),VALUE(LEFT(C61,2)))) -> 46220 | E61: TANGERANG | F61: =PROPER(TRIM(SUBSTITUTE(SUBSTITUTE(E61,"Jaksel","Jakarta Selatan"),"Tangerang Kota","Tangerang"))) -> Tangerang | H61: =IF(G61="","Unknown",G61) -> Unknown | I61: Fitri Anggraini | J61: =IF(I61="","Unknown",I61) -> Fitri Anggraini | K61: P007 | L61: XSR 155 | M61: 1 | N61: 41000000 | O61: 0 | P61: 41000000 | Q61: =IF(P61=0,"Batal/Refund","Normal") -> Normal | R61: Kredit - FIF | S61: Proses Kredit | T61: Online - Website | U61: =COUNTIF($A$2:$A$342,A61) -> 1
A62: TRX-1013 | B62: 13/07/2026 | C62: =SUBSTITUTE(SUBSTITUTE(SUBSTITUTE(SUBSTITUTE(SUBSTITUTE(SUBSTITUTE(SUBSTITUTE(SUBSTITUTE(SUBSTITUTE(SUBSTITUTE(SUBSTITUTE(SUBSTITUTE(B62," Januari ","/01/")," Februari ","/02/")," Maret ","/03/")," April ","/04/")," Mei ","/05/")," Juni ","/06/")," Juli ","/07/")," Agustus ","/08/")," September ","/09/")," Oktober ","/10/")," November ","/11/")," Desember ","/12/") -> 13/07/2026 | D62: =IFERROR(DATE(VALUE(LEFT(C62,4)),VALUE(MID(C62,6,2)),VALUE(RIGHT(C62,2))),DATE(VALUE(RIGHT(C62,4)),VALUE(MID(C62,4,2)),VALUE(LEFT(C62,2)))) -> 46216 | E62: Bandung | F62: =PROPER(TRIM(SUBSTITUTE(SUBSTITUTE(E62,"Jaksel","Jakarta Selatan"),"Tangerang Kota","Tangerang"))) -> Bandung | G62: Indah Permata | H62: =IF(G62="","Unknown",G62) -> Indah Permata | I62: Budi Hidayat | J62: =IF(I62="","Unknown",I62) -> Budi Hidayat | K62: P005 | L62: Fazzio | M62: 1 | N62: 21500000 | O62: 1075000 | P62: 20425000 | Q62: =IF(P62=0,"Batal/Refund","Normal") -> Normal | R62: Kredit - Adira | S62: Lunas | T62: Online - Website | U62: =COUNTIF($A$2:$A$342,A62) -> 1
A63: TRX-1200 | B63: 2026-07-17 | C63: =SUBSTITUTE(SUBSTITUTE(SUBSTITUTE(SUBSTITUTE(SUBSTITUTE(SUBSTITUTE(SUBSTITUTE(SUBSTITUTE(SUBSTITUTE(SUBSTITUTE(SUBSTITUTE(SUBSTITUTE(B63," Januari ","/01/")," Februari ","/02/")," Maret ","/03/")," April ","/04/")," Mei ","/05/")," Juni ","/06/")," Juli ","/07/")," Agustus ","/08/")," September ","/09/")," Oktober ","/10/")," November ","/11/")," Desember ","/12/") -> 2026-07-17 | D63: =IFERROR(DATE(VALUE(LEFT(C63,4)),VALUE(MID(C63,6,2)),VALUE(RIGHT(C63,2))),DATE(VALUE(RIGHT(C63,4)),VALUE(MID(C63,4,2)),VALUE(LEFT(C63,2)))) -> 46220 | E63: Tangerang | F63: =PROPER(TRIM(SUBSTITUTE(SUBSTITUTE(E63,"Jaksel","Jakarta Selatan"),"Tangerang Kota","Tangerang"))) -> Tangerang | G63: Mira Anjani | H63: =IF(G63="","Unknown",G63) -> Mira Anjani | I63: Putra Hidayat | J63: =IF(I63="","Unknown",I63) -> Putra Hidayat | K63: P003 | L63: Lexi | M63: 1 | N63: 27400000 | O63: 1370000 | P63: 26030000 | Q63: =IF(P63=0,"Batal/Refund","Normal") -> Normal | R63: Kredit - Mandiri Tunas | S63: DP | T63: Referral | U63: =COUNTIF($A$2:$A$342,A63) -> 1
A64: TRX-1028 | B64: 13/07/2026 | C64: =SUBSTITUTE(SUBSTITUTE(SUBSTITUTE(SUBSTITUTE(SUBSTITUTE(SUBSTITUTE(SUBSTITUTE(SUBSTITUTE(SUBSTITUTE(SUBSTITUTE(SUBSTITUTE(SUBSTITUTE(B64," Januari ","/01/")," Februari ","/02/")," Maret ","/03/")," April ","/04/")," Mei ","/05/")," Juni ","/06/")," Juli ","/07/")," Agustus ","/08/")," September ","/09/")," Oktober ","/10/")," November ","/11/")," Desember ","/12/") -> 13/07/2026 | D64: =IFERROR(DATE(VALUE(LEFT(C64,4)),VALUE(MID(C64,6,2)),VALUE(RIGHT(C64,2))),DATE(VALUE(RIGHT(C64,4)),VALUE(MID(C64,4,2)),VALUE(LEFT(C64,2)))) -> 46216 | E64: Cibubur | F64: =PROPER(TRIM(SUBSTITUTE(SUBSTITUTE(E64,"Jaksel","Jakarta Selatan"),"Tangerang Kota","Tangerang"))) -> Cibubur | G64: Joko Widodo S. | H64: =IF(G64="","Unknown",G64) -> Joko Widodo S. | I64: Tono Ramadhan | J64: =IF(I64="","Unknown",I64) -> Tono Ramadhan | K64: P001 | L64: NMAX | M64: 2 | N64: 33500000 | O64: 0 | P64: 67000000 | Q64: =IF(P64=0,"Batal/Refund","Normal") -> Normal | R64: Debit/Transfer | S64: Lunas | T64: Showroom | U64: =COUNTIF($A$2:$A$342,A64) -> 1
A65: TRX-1103 | B65: 2026-07-15 | C65: =SUBSTITUTE(SUBSTITUTE(SUBSTITUTE(SUBSTITUTE(SUBSTITUTE(SUBSTITUTE(SUBSTITUTE(SUBSTITUTE(SUBSTITUTE(SUBSTITUTE(SUBSTITUTE(SUBSTITUTE(B65," Januari ","/01/")," Februari ","/02/")," Maret ","/03/")," April ","/04/")," Mei ","/05/")," Juni ","/06/")," Juli ","/07/")," Agustus ","/08/")," September ","/09/")," Oktober ","/10/")," November ","/11/")," Desember ","/12/") -> 2026-07-15 | D65: =IFERROR(DATE(VALUE(LEFT(C65,4)),VALUE(MID(C65,6,2)),VALUE(RIGHT(C65,2))),DATE(VALUE(RIGHT(C65,4)),VALUE(MID(C65,4,2)),VALUE(LEFT(C65,2)))) -> 46218 | E65: Bekasi | F65: =PROPER(TRIM(SUBSTITUTE(SUBSTITUTE(E65,"Jaksel","Jakarta Selatan"),"Tangerang Kota","Tangerang"))) -> Bekasi | G65: Vino Bastian G. | H65: =IF(G65="","Unknown",G65) -> Vino Bastian G. | I65: Kevin Wijaya | J65: =IF(I65="","Unknown",I65) -> Kevin Wijaya | K65: P002 | L65: Aerox | M65: 1 | N65: 29800000 | O65: 596000 | P65: 29204000 | Q65: =IF(P65=0,"Batal/Refund","Normal") -> Normal | R65: Kredit - Mandiri Tunas | S65: Lunas | T65: Online - Website | U65: =COUNTIF($A$2:$A$342,A65) -> 1
A66: TRX-1130 | B66: 15 Juli 2026 | C66: =SUBSTITUTE(SUBSTITUTE(SUBSTITUTE(SUBSTITUTE(SUBSTITUTE(SUBSTITUTE(SUBSTITUTE(SUBSTITUTE(SUBSTITUTE(SUBSTITUTE(SUBSTITUTE(SUBSTITUTE(B66," Januari ","/01/")," Februari ","/02/")," Maret ","/03/")," April ","/04/")," Mei ","/05/")," Juni ","/06/")," Juli ","/07/")," Agustus ","/08/")," September ","/09/")," Oktober ","/10/")," November ","/11/")," Desember ","/12/") -> 15/07/2026 | D66: =IFERROR(DATE(VALUE(LEFT(C66,4)),VALUE(MID(C66,6,2)),VALUE(RIGHT(C66,2))),DATE(VALUE(RIGHT(C66,4)),VALUE(MID(C66,4,2)),VALUE(LEFT(C66,2)))) -> 46218 | E66: Karawang | F66: =PROPER(TRIM(SUBSTITUTE(SUBSTITUTE(E66,"Jaksel","Jakarta Selatan"),"Tangerang Kota","Tangerang"))) -> Karawang | G66: Lukman Hakim | H66: =IF(G66="","Unknown",G66) -> Lukman Hakim | I66: Lala Ramadhan | J66: =IF(I66="","Unknown",I66) -> Lala Ramadhan | K66: P004 | L66: Mio | M66: 1 | N66: 18900000 | O66: 567000 | P66: 18333000 | Q66: =IF(P66=0,"Batal/Refund","Normal") -> Normal | R66: Cash | S66: Lunas | T66: Referral | U66: =COUNTIF($A$2:$A$342,A66) -> 1
A67: TRX-1093 | B67: 14 Juli 2026 | C67: =SUBSTITUTE(SUBSTITUTE(SUBSTITUTE(SUBSTITUTE(SUBSTITUTE(SUBSTITUTE(SUBSTITUTE(SUBSTITUTE(SUBSTITUTE(SUBSTITUTE(SUBSTITUTE(SUBSTITUTE(B67," Januari ","/01/")," Februari ","/02/")," Maret ","/03/")," April ","/04/")," Mei ","/05/")," Juni ","/06/")," Juli ","/07/")," Agustus ","/08/")," September ","/09/")," Oktober ","/10/")," November ","/11/")," Desember ","/12/") -> 14/07/2026 | D67: =IFERROR(DATE(VALUE(LEFT(C67,4)),VALUE(MID(C67,6,2)),VALUE(RIGHT(C67,2))),DATE(VALUE(RIGHT(C67,4)),VALUE(MID(C67,4,2)),VALUE(LEFT(C67,2)))) -> 46217 | E67: Sukabumi | F67: =PROPER(TRIM(SUBSTITUTE(SUBSTITUTE(E67,"Jaksel","Jakarta Selatan"),"Tangerang Kota","Tangerang"))) -> Sukabumi | G67: Hadi Santoso | H67: =IF(G67="","Unknown",G67) -> Hadi Santoso | I67: Dewi Hidayat | J67: =IF(I67="","Unknown",I67) -> Dewi Hidayat | K67: P005 | L67: Fazzio | M67: 1 | N67: 21500000 | O67: 430000 | P67: 21070000 | Q67: =IF(P67=0,"Batal/Refund","Normal") -> Normal | R67: Kredit - Mandiri Tunas | S67: Lunas | T67: Referral | U67: =COUNTIF($A$2:$A$342,A67) -> 1
A68: TRX-1030 | B68: 13/07/2026 | C68: =SUBSTITUTE(SUBSTITUTE(SUBSTITUTE(SUBSTITUTE(SUBSTITUTE(SUBSTITUTE(SUBSTITUTE(SUBSTITUTE(SUBSTITUTE(SUBSTITUTE(SUBSTITUTE(SUBSTITUTE(B68," Januari ","/01/")," Februari ","/02/")," Maret ","/03/")," April ","/04/")," Mei ","/05/")," Juni ","/06/")," Juli ","/07/")," Agustus ","/08/")," September ","/09/")," Oktober ","/10/")," November ","/11/")," Desember ","/12/") -> 13/07/2026 | D68: =IFERROR(DATE(VALUE(LEFT(C68,4)),VALUE(MID(C68,6,2)),VALUE(RIGHT(C68,2))),DATE(VALUE(RIGHT(C68,4)),VALUE(MID(C68,4,2)),VALUE(LEFT(C68,2)))) -> 46216 | E68: Sukabumi | F68: =PROPER(TRIM(SUBSTITUTE(SUBSTITUTE(E68,"Jaksel","Jakarta Selatan"),"Tangerang Kota","Tangerang"))) -> Sukabumi | G68: Lukman Hakim | H68: =IF(G68="","Unknown",G68) -> Lukman Hakim | I68: Jihan Firmansyah | J68: =IF(I68="","Unknown",I68) -> Jihan Firmansyah | K68: P006 | L68: Gear | M68: 1 | N68: 17800000 | O68: 178000 | P68: 17622000 | Q68: =IF(P68=0,"Batal/Refund","Normal") -> Normal | R68: Kredit - Adira | S68: Lunas | T68: Referral | U68: =COUNTIF($A$2:$A$342,A68) -> 1
A69: TRX-1059 | B69: 2026-07-14 | C69: =SUBSTITUTE(SUBSTITUTE(SUBSTITUTE(SUBSTITUTE(SUBSTITUTE(SUBSTITUTE(SUBSTITUTE(SUBSTITUTE(SUBSTITUTE(SUBSTITUTE(SUBSTITUTE(SUBSTITUTE(B69," Januari ","/01/")," Februari ","/02/")," Maret ","/03/")," April ","/04/")," Mei ","/05/")," Juni ","/06/")," Juli ","/07/")," Agustus ","/08/")," September ","/09/")," Oktober ","/10/")," November ","/11/")," Desember ","/12/") -> 2026-07-14 | D69: =IFERROR(DATE(VALUE(LEFT(C69,4)),VALUE(MID(C69,6,2)),VALUE(RIGHT(C69,2))),DATE(VALUE(RIGHT(C69,4)),VALUE(MID(C69,4,2)),VALUE(LEFT(C69,2)))) -> 46217 | E69: Bogor | F69: =PROPER(TRIM(SUBSTITUTE(SUBSTITUTE(E69,"Jaksel","Jakarta Selatan"),"Tangerang Kota","Tangerang"))) -> Bogor | G69: Rangga Saputra | H69: =IF(G69="","Unknown",G69) -> Rangga Saputra | I69: Putra Hidayat | J69: =IF(I69="","Unknown",I69) -> Putra Hidayat | K69: P009 | L69: Grand Filano | M69: 1 | N69: 26900000 | O69: 807000 | P69: 26093000 | Q69: =IF(P69=0,"Batal/Refund","Normal") -> Normal | R69: Kredit - Adira | S69: Lunas | T69: Referral | U69: =COUNTIF($A$2:$A$342,A69) -> 1
A70: TRX-1193 | B70: 16/07/2026 | C70: =SUBSTITUTE(SUBSTITUTE(SUBSTITUTE(SUBSTITUTE(SUBSTITUTE(SUBSTITUTE(SUBSTITUTE(SUBSTITUTE(SUBSTITUTE(SUBSTITUTE(SUBSTITUTE(SUBSTITUTE(B70," Januari ","/01/")," Februari ","/02/")," Maret ","/03/")," April ","/04/")," Mei ","/05/")," Juni ","/06/")," Juli ","/07/")," Agustus ","/08/")," September ","/09/")," Oktober ","/10/")," November ","/11/")," Desember ","/12/") -> 16/07/2026 | D70: =IFERROR(DATE(VALUE(LEFT(C70,4)),VALUE(MID(C70,6,2)),VALUE(RIGHT(C70,2))),DATE(VALUE(RIGHT(C70,4)),VALUE(MID(C70,4,2)),VALUE(LEFT(C70,2)))) -> 46219 | E70: Sukabumi | F70: =PROPER(TRIM(SUBSTITUTE(SUBSTITUTE(E70,"Jaksel","Jakarta Selatan"),"Tangerang Kota","Tangerang"))) -> Sukabumi | G70: Vino Bastian G. | H70: =IF(G70="","Unknown",G70) -> Vino Bastian G. | I70: Lala Saputra | J70: =IF(I70="","Unknown",I70) -> Lala Saputra | K70: P004 | L70: Mio | M70: 1 | N70: 18900000 | O70: 189000 | P70: 18711000 | Q70: =IF(P70=0,"Batal/Refund","Normal") -> Normal | R70: Debit/Transfer | S70: Lunas | T70: Pameran | U70: =COUNTIF($A$2:$A$342,A70) -> 1
A71: TRX-1223 | B71: 2026-07-17 | C71: =SUBSTITUTE(SUBSTITUTE(SUBSTITUTE(SUBSTITUTE(SUBSTITUTE(SUBSTITUTE(SUBSTITUTE(SUBSTITUTE(SUBSTITUTE(SUBSTITUTE(SUBSTITUTE(SUBSTITUTE(B71," Januari ","/01/")," Februari ","/02/")," Maret ","/03/")," April ","/04/")," Mei ","/05/")," Juni ","/06/")," Juli ","/07/")," Agustus ","/08/")," September ","/09/")," Oktober ","/10/")," November ","/11/")," Desember ","/12/") -> 2026-07-17 | D71: =IFERROR(DATE(VALUE(LEFT(C71,4)),VALUE(MID(C71,6,2)),VALUE(RIGHT(C71,2))),DATE(VALUE(RIGHT(C71,4)),VALUE(MID(C71,4,2)),VALUE(LEFT(C71,2)))) -> 46220 | E71: Cikarang | F71: =PROPER(TRIM(SUBSTITUTE(SUBSTITUTE(E71,"Jaksel","Jakarta Selatan"),"Tangerang Kota","Tangerang"))) -> Cikarang | G71: Kiki Amelia | H71: =IF(G71="","Unknown",G71) -> Kiki Amelia | I71: Tono Saputra | J71: =IF(I71="","Unknown",I71) -> Tono Saputra | K71: P003 | L71: Lexi | M71: 1 | N71: 27400000 | O71: 0 | P71: 27400000 | Q71: =IF(P71=0,"Batal/Refund","Normal") -> Normal | R71: Cash | S71: DP | T71: Online - Website | U71: =COUNTIF($A$2:$A$342,A71) -> 1
A72: TRX-1278 | B72: 18/07/2026 | C72: =SUBSTITUTE(SUBSTITUTE(SUBSTITUTE(SUBSTITUTE(SUBSTITUTE(SUBSTITUTE(SUBSTITUTE(SUBSTITUTE(SUBSTITUTE(SUBSTITUTE(SUBSTITUTE(SUBSTITUTE(B72," Januari ","/01/")," Februari ","/02/")," Maret ","/03/")," April ","/04/")," Mei ","/05/")," Juni ","/06/")," Juli ","/07/")," Agustus ","/08/")," September ","/09/")," Oktober ","/10/")," November ","/11/")," Desember ","/12/") -> 18/07/2026 | D72: =IFERROR(DATE(VALUE(LEFT(C72,4)),VALUE(MID(C72,6,2)),VALUE(RIGHT(C72,2))),DATE(VALUE(RIGHT(C72,4)),VALUE(MID(C72,4,2)),VALUE(LEFT(C72,2)))) -> 46221 | E72: Jakarta Selatan | F72: =PROPER(TRIM(SUBSTITUTE(SUBSTITUTE(E72,"Jaksel","Jakarta Selatan"),"Tangerang Kota","Tangerang"))) -> Jakarta Selatan | G72: Lukman Hakim | H72: =IF(G72="","Unknown",G72) -> Lukman Hakim | I72: Budi Firmansyah | J72: =IF(I72="","Unknown",I72) -> Budi Firmansyah | K72: P008 | L72: MX King | M72: 1 | N72: 24600000 | O72: 492000 | P72: 24108000 | Q72: =IF(P72=0,"Batal/Refund","Normal") -> Normal | R72: Cash | S72: Lunas | T72: Pameran | U72: =COUNTIF($A$2:$A$342,A72) -> 1
A73: TRX-1295 | B73: 18/07/2026 | C73: =SUBSTITUTE(SUBSTITUTE(SUBSTITUTE(SUBSTITUTE(SUBSTITUTE(SUBSTITUTE(SUBSTITUTE(SUBSTITUTE(SUBSTITUTE(SUBSTITUTE(SUBSTITUTE(SUBSTITUTE(B73," Januari ","/01/")," Februari ","/02/")," Maret ","/03/")," April ","/04/")," Mei ","/05/")," Juni ","/06/")," Juli ","/07/")," Agustus ","/08/")," September ","/09/")," Oktober ","/10/")," November ","/11/")," Desember ","/12/") -> 18/07/2026 | D73: =IFERROR(DATE(VALUE(LEFT(C73,4)),VALUE(MID(C73,6,2)),VALUE(RIGHT(C73,2))),DATE(VALUE(RIGHT(C73,4)),VALUE(MID(C73,4,2)),VALUE(LEFT(C73,2)))) -> 46221 | E73: Sukabumi | F73: =PROPER(TRIM(SUBSTITUTE(SUBSTITUTE(E73,"Jaksel","Jakarta Selatan"),"Tangerang Kota","Tangerang"))) -> Sukabumi | G73: Indah Permata | H73: =IF(G73="","Unknown",G73) -> Indah Permata | I73: Kevin Ramadhan | J73: =IF(I73="","Unknown",I73) -> Kevin Ramadhan | K73: P003 | L73: Lexi | M73: 1 | N73: 27400000 | O73: 822000 | P73: 26578000 | Q73: =IF(P73=0,"Batal/Refund","Normal") -> Normal | R73: Kredit - FIF | S73: DP | T73: Referral | U73: =COUNTIF($A$2:$A$342,A73) -> 1
... A86: TRX-1052 | B86: 2026-07-14 | C86: =SUBSTITUTE(SUBSTITUTE(SUBSTITUTE(SUBSTITUTE(SUBSTITUTE(SUBSTITUTE(SUBSTITUTE(SUBSTITUTE(SUBSTITUTE(SUBSTITUTE(SUBSTITUTE(SUBSTITUTE(B86," Januari ","/01/")," Februari ","/02/")," Maret ","/03/")," April ","/04/")," Mei ","/05/")," Juni ","/06/")," Juli ","/07/")," Agustus ","/08/")," September ","/09/")," Oktober ","/10/")," November ","/11/")," Desember ","/12/") -> 2026-07-14 | D86: =IFERROR(DATE(VALUE(LEFT(C86,4)),VALUE(MID(C86,6,2)),VALUE(RIGHT(C86,2))),DATE(VALUE(RIGHT(C86,4)),VALUE(MID(C86,4,2)),VALUE(LEFT(C86,2)))) -> 46217 | E86: Bandung | F86: =PROPER(TRIM(SUBSTITUTE(SUBSTITUTE(E86,"Jaksel","Jakarta Selatan"),"Tangerang Kota","Tangerang"))) -> Bandung | G86: Rangga Saputra | H86: =IF(G86="","Unknown",G86) -> Rangga Saputra | I86: Citra Ramadhan | J86: =IF(I86="","Unknown",I86) -> Citra Ramadhan | K86: P002 | L86: Aerox | M86: 2 | N86: 29800000 | O86: 596000 | P86: 59004000 | Q86: =IF(P86=0,"Batal/Refund","Normal") -> Normal | R86: Kredit - Adira | S86: Lunas | T86: Online - Website | U86: =COUNTIF($A$2:$A$342,A86) -> 1
A87: TRX-1010 | B87: 13 Juli 2026 | C87: =SUBSTITUTE(SUBSTITUTE(SUBSTITUTE(SUBSTITUTE(SUBSTITUTE(SUBSTITUTE(SUBSTITUTE(SUBSTITUTE(SUBSTITUTE(SUBSTITUTE(SUBSTITUTE(SUBSTITUTE(B87," Januari ","/01/")," Februari ","/02/")," Maret ","/03/")," April ","/04/")," Mei ","/05/")," Juni ","/06/")," Juli ","/07/")," Agustus ","/08/")," September ","/09/")," Oktober ","/10/")," November ","/11/")," Desember ","/12/") -> 13/07/2026 | D87: =IFERROR(DATE(VALUE(LEFT(C87,4)),VALUE(MID(C87,6,2)),VALUE(RIGHT(C87,2))),DATE(VALUE(RIGHT(C87,4)),VALUE(MID(C87,4,2)),VALUE(LEFT(C87,2)))) -> 46216 | E87: Depok | F87: =PROPER(TRIM(SUBSTITUTE(SUBSTITUTE(E87,"Jaksel","Jakarta Selatan"),"Tangerang Kota","Tangerang"))) -> Depok | H87: =IF(G87="","Unknown",G87) -> Unknown | I87: Lala Lestari | J87: =IF(I87="","Unknown",I87) -> Lala Lestari | K87: P010 | L87: Freego | M87: 1 | N87: 22300000 | O87: 0 | P87: 22300000 | Q87: =IF(P87=0,"Batal/Refund","Normal") -> Normal | R87: Cash | S87: Lunas | T87: Showroom | U87: =COUNTIF($A$2:$A$342,A87) -> 1
A88: TRX-1276 | B88: 2026-07-18 | C88: =SUBSTITUTE(SUBSTITUTE(SUBSTITUTE(SUBSTITUTE(SUBSTITUTE(SUBSTITUTE(SUBSTITUTE(SUBSTITUTE(SUBSTITUTE(SUBSTITUTE(SUBSTITUTE(SUBSTITUTE(B88," Januari ","/01/")," Februari ","/02/")," Maret ","/03/")," April ","/04/")," Mei ","/05/")," Juni ","/06/")," Juli ","/07/")," Agustus ","/08/")," September ","/09/")," Oktober ","/10/")," November ","/11/")," Desember ","/12/") -> 2026-07-18 | D88: =IFERROR(DATE(VALUE(LEFT(C88,4)),VALUE(MID(C88,6,2)),VALUE(RIGHT(C88,2))),DATE(VALUE(RIGHT(C88,4)),VALUE(MID(C88,4,2)),VALUE(LEFT(C88,2)))) -> 46221 | E88: Jakarta Selatan | F88: =PROPER(TRIM(SUBSTITUTE(SUBSTITUTE(E88,"Jaksel","Jakarta Selatan"),"Tangerang Kota","Tangerang"))) -> Jakarta Selatan | G88: Sari Dewi | H88: =IF(G88="","Unknown",G88) -> Sari Dewi | I88: Siska Maharani | J88: =IF(I88="","Unknown",I88) -> Siska Maharani | K88: P001 | L88: NMAX | M88: 1 | N88: 33500000 | O88: 335000 | P88: 0 | Q88: =IF(P88=0,"Batal/Refund","Normal") -> Batal/Refund | R88: Debit/Transfer | S88: Proses Kredit | T88: Showroom | U88: =COUNTIF($A$2:$A$342,A88) -> 1
A89: TRX-1017 | B89: 2026-07-13 | C89: =SUBSTITUTE(SUBSTITUTE(SUBSTITUTE(SUBSTITUTE(SUBSTITUTE(SUBSTITUTE(SUBSTITUTE(SUBSTITUTE(SUBSTITUTE(SUBSTITUTE(SUBSTITUTE(SUBSTITUTE(B89," Januari ","/01/")," Februari ","/02/")," Maret ","/03/")," April ","/04/")," Mei ","/05/")," Juni ","/06/")," Juli ","/07/")," Agustus ","/08/")," September ","/09/")," Oktober ","/10/")," November ","/11/")," Desember ","/12/") -> 2026-07-13 | D89: =IFERROR(DATE(VALUE(LEFT(C89,4)),VALUE(MID(C89,6,2)),VALUE(RIGHT(C89,2))),DATE(VALUE(RIGHT(C89,4)),VALUE(MID(C89,4,2)),VALUE(LEFT(C89,2)))) -> 46216 | E89: Jakarta Timur | F89: =PROPER(TRIM(SUBSTITUTE(SUBSTITUTE(E89,"Jaksel","Jakarta Selatan"),"Tangerang Kota","Tangerang"))) -> Jakarta Timur | G89: Taufik Hidayat | H89: =IF(G89="","Unknown",G89) -> Taufik Hidayat | I89: Putra Kusuma | J89: =IF(I89="","Unknown",I89) -> Putra Kusuma | K89: P009 | L89: Grand Filano | M89: 1 | N89: 26900000 | O89: 269000 | P89: 26631000 | Q89: =IF(P89=0,"Batal/Refund","Normal") -> Normal | R89: Debit/Transfer | S89: Lunas | T89: Showroom | U89: =COUNTIF($A$2:$A$342,A89) -> 1
A90: TRX-1248 | B90: 2026-07-18 | C90: =SUBSTITUTE(SUBSTITUTE(SUBSTITUTE(SUBSTITUTE(SUBSTITUTE(SUBSTITUTE(SUBSTITUTE(SUBSTITUTE(SUBSTITUTE(SUBSTITUTE(SUBSTITUTE(SUBSTITUTE(B90," Januari ","/01/")," Februari ","/02/")," Maret ","/03/")," April ","/04/")," Mei ","/05/")," Juni ","/06/")," Juli ","/07/")," Agustus ","/08/")," September ","/09/")," Oktober ","/10/")," November ","/11/")," Desember ","/12/") -> 2026-07-18 | D90: =IFERROR(DATE(VALUE(LEFT(C90,4)),VALUE(MID(C90,6,2)),VALUE(RIGHT(C90,2))),DATE(VALUE(RIGHT(C90,4)),VALUE(MID(C90,4,2)),VALUE(LEFT(C90,2)))) -> 46221 | E90: Bandung | F90: =PROPER(TRIM(SUBSTITUTE(SUBSTITUTE(E90,"Jaksel","Jakarta Selatan"),"Tangerang Kota","Tangerang"))) -> Bandung | G90: Oki Setiawan | H90: =IF(G90="","Unknown",G90) -> Oki Setiawan | I90: Putra Maharani | J90: =IF(I90="","Unknown",I90) -> Putra Maharani | K90: P007 | L90: XSR 155 | M90: 1 | N90: 41000000 | O90: 1230000 | P90: 39770000 | Q90: =IF(P90=0,"Batal/Refund","Normal") -> Normal | R90: Kredit - Mandiri Tunas | S90: Lunas | T90: Online - Website | U90: =COUNTIF($A$2:$A$342,A90) -> 1
A91: TRX-1001 | B91: 13 Juli 2026 | C91: =SUBSTITUTE(SUBSTITUTE(SUBSTITUTE(SUBSTITUTE(SUBSTITUTE(SUBSTITUTE(SUBSTITUTE(SUBSTITUTE(SUBSTITUTE(SUBSTITUTE(SUBSTITUTE(SUBSTITUTE(B91," Januari ","/01/")," Februari ","/02/")," Maret ","/03/")," April ","/04/")," Mei ","/05/")," Juni ","/06/")," Juli ","/07/")," Agustus ","/08/")," September ","/09/")," Oktober ","/10/")," November ","/11/")," Desember ","/12/") -> 13/07/2026 | D91: =IFERROR(DATE(VALUE(LEFT(C91,4)),VALUE(MID(C91,6,2)),VALUE(RIGHT(C91,2))),DATE(VALUE(RIGHT(C91,4)),VALUE(MID(C91,4,2)),VALUE(LEFT(C91,2)))) -> 46216 | E91: Tangerang | F91: =PROPER(TRIM(SUBSTITUTE(SUBSTITUTE(E91,"Jaksel","Jakarta Selatan"),"Tangerang Kota","Tangerang"))) -> Tangerang | G91: Taufik Hidayat | H91: =IF(G91="","Unknown",G91) -> Taufik Hidayat | I91: Nia Saputra | J91: =IF(I91="","Unknown",I91) -> Nia Saputra | K91: P002 | L91: Aerox | M91: 1 | N91: 29800000 | O91: 1490000 | P91: 28310000 | Q91: =IF(P91=0,"Batal/Refund","Normal") -> Normal | R91: Debit/Transfer | S91: Lunas | T91: Online - Website | U91: =COUNTIF($A$2:$A$342,A91) -> 1
A92: TRX-1159 | B92: 16 Juli 2026 | C92: =SUBSTITUTE(SUBSTITUTE(SUBSTITUTE(SUBSTITUTE(SUBSTITUTE(SUBSTITUTE(SUBSTITUTE(SUBSTITUTE(SUBSTITUTE(SUBSTITUTE(SUBSTITUTE(SUBSTITUTE(B92," Januari ","/01/")," Februari ","/02/")," Maret ","/03/")," April ","/04/")," Mei ","/05/")," Juni ","/06/")," Juli ","/07/")," Agustus ","/08/")," September ","/09/")," Oktober ","/10/")," November ","/11/")," Desember ","/12/") -> 16/07/2026 | D92: =IFERROR(DATE(VALUE(LEFT(C92,4)),VALUE(MID(C92,6,2)),VALUE(RIGHT(C92,2))),DATE(VALUE(RIGHT(C92,4)),VALUE(MID(C92,4,2)),VALUE(LEFT(C92,2)))) -> 46219 | E92: Bandung | F92: =PROPER(TRIM(SUBSTITUTE(SUBSTITUTE(E92,"Jaksel","Jakarta Selatan"),"Tangerang Kota","Tangerang"))) -> Bandung | G92: Vino Bastian G. | H92: =IF(G92="","Unknown",G92) -> Vino Bastian G. | I92: Kevin Pratama | J92: =IF(I92="","Unknown",I92) -> Kevin Pratama | K92: P002 | L92: Aerox | M92: 1 | N92: 29800000 | O92: 894000 | P92: 28906000 | Q92: =IF(P92=0,"Batal/Refund","Normal") -> Normal | R92: Kredit - Adira | S92: Lunas | T92: Pameran | U92: =COUNTIF($A$2:$A$342,A92) -> 1
A93: TRX-1139 | B93: 15/07/2026 | C93: =SUBSTITUTE(SUBSTITUTE(SUBSTITUTE(SUBSTITUTE(SUBSTITUTE(SUBSTITUTE(SUBSTITUTE(SUBSTITUTE(SUBSTITUTE(SUBSTITUTE(SUBSTITUTE(SUBSTITUTE(B93," Januari ","/01/")," Februari ","/02/")," Maret ","/03/")," April ","/04/")," Mei ","/05/")," Juni ","/06/")," Juli ","/07/")," Agustus ","/08/")," September ","/09/")," Oktober ","/10/")," November ","/11/")," Desember ","/12/") -> 15/07/2026 | D93: =IFERROR(DATE(VALUE(LEFT(C93,4)),VALUE(MID(C93,6,2)),VALUE(RIGHT(C93,2))),DATE(VALUE(RIGHT(C93,4)),VALUE(MID(C93,4,2)),VALUE(LEFT(C93,2)))) -> 46218 | E93: Sukabumi | F93: =PROPER(TRIM(SUBSTITUTE(SUBSTITUTE(E93,"Jaksel","Jakarta Selatan"),"Tangerang Kota","Tangerang"))) -> Sukabumi | G93: Lukman Hakim | H93: =IF(G93="","Unknown",G93) -> Lukman Hakim | I93: Nia Pratama | J93: =IF(I93="","Unknown",I93) -> Nia Pratama | K93: P004 | L93: Mio | M93: 1 | N93: 18900000 | O93: 0 | P93: 18900000 | Q93: =IF(P93=0,"Batal/Refund","Normal") -> Normal | R93: Cash | S93: Lunas | T93: Online - Website | U93: =COUNTIF($A$2:$A$342,A93) -> 1
A94: TRX-1063 | B94: 2026-07-14 | C94: =SUBSTITUTE(SUBSTITUTE(SUBSTITUTE(SUBSTITUTE(SUBSTITUTE(SUBSTITUTE(SUBSTITUTE(SUBSTITUTE(SUBSTITUTE(SUBSTITUTE(SUBSTITUTE(SUBSTITUTE(B94," Januari ","/01/")," Februari ","/02/")," Maret ","/03/")," April ","/04/")," Mei ","/05/")," Juni ","/06/")," Juli ","/07/")," Agustus ","/08/")," September ","/09/")," Oktober ","/10/")," November ","/11/")," Desember ","/12/") -> 2026-07-14 | D94: =IFERROR(DATE(VALUE(LEFT(C94,4)),VALUE(MID(C94,6,2)),VALUE(RIGHT(C94,2))),DATE(VALUE(RIGHT(C94,4)),VALUE(MID(C94,4,2)),VALUE(LEFT(C94,2)))) -> 46217 | E94: Cikarang | F94: =PROPER(TRIM(SUBSTITUTE(SUBSTITUTE(E94,"Jaksel","Jakarta Selatan"),"Tangerang Kota","Tangerang"))) -> Cikarang | G94: Kiki Amelia | H94: =IF(G94="","Unknown",G94) -> Kiki Amelia | I94: Irfan Ramadhan | J94: =IF(I94="","Unknown",I94) -> Irfan Ramadhan | K94: P003 | L94: Lexi | M94: 1 | N94: 27400000 | O94: 0 | P94: 27400000 | Q94: =IF(P94=0,"Batal/Refund","Normal") -> Normal | R94: Kredit - Mandiri Tunas | S94: Proses Kredit | T94: Online - Website | U94: =COUNTIF($A$2:$A$342,A94) -> 1
A95: TRX-1329 | B95: 2026-07-19 | C95: =SUBSTITUTE(SUBSTITUTE(SUBSTITUTE(SUBSTITUTE(SUBSTITUTE(SUBSTITUTE(SUBSTITUTE(SUBSTITUTE(SUBSTITUTE(SUBSTITUTE(SUBSTITUTE(SUBSTITUTE(B95," Januari ","/01/")," Februari ","/02/")," Maret ","/03/")," April ","/04/")," Mei ","/05/")," Juni ","/06/")," Juli ","/07/")," Agustus ","/08/")," September ","/09/")," Oktober ","/10/")," November ","/11/")," Desember ","/12/") -> 2026-07-19 | D95: =IFERROR(DATE(VALUE(LEFT(C95,4)),VALUE(MID(C95,6,2)),VALUE(RIGHT(C95,2))),DATE(VALUE(RIGHT(C95,4)),VALUE(MID(C95,4,2)),VALUE(LEFT(C95,2)))) -> 46222 | E95: Jakarta Selatan | F95: =PROPER(TRIM(SUBSTITUTE(SUBSTITUTE(E95,"Jaksel","Jakarta Selatan"),"Tangerang Kota","Tangerang"))) -> Jakarta Selatan | G95: Rudi Hartono | H95: =IF(G95="","Unknown",G95) -> Rudi Hartono | I95: Irfan Wijaya | J95: =IF(I95="","Unknown",I95) -> Irfan Wijaya | K95: P010 | L95: Freego | M95: 1 | N95: 22300000 | O95: 446000 | P95: 21854000 | Q95: =IF(P95=0,"Batal/Refund","Normal") -> Normal | R95: Kredit - Adira | S95: Lunas | T95: Referral | U95: =COUNTIF($A$2:$A$342,A95) -> 1
A96: TRX-1160 | B96: 16/07/2026 | C96: =SUBSTITUTE(SUBSTITUTE(SUBSTITUTE(SUBSTITUTE(SUBSTITUTE(SUBSTITUTE(SUBSTITUTE(SUBSTITUTE(SUBSTITUTE(SUBSTITUTE(SUBSTITUTE(SUBSTITUTE(B96," Januari ","/01/")," Februari ","/02/")," Maret ","/03/")," April ","/04/")," Mei ","/05/")," Juni ","/06/")," Juli ","/07/")," Agustus ","/08/")," September ","/09/")," Oktober ","/10/")," November ","/11/")," Desember ","/12/") -> 16/07/2026 | D96: =IFERROR(DATE(VALUE(LEFT(C96,4)),VALUE(MID(C96,6,2)),VALUE(RIGHT(C96,2))),DATE(VALUE(RIGHT(C96,4)),VALUE(MID(C96,4,2)),VALUE(LEFT(C96,2)))) -> 46219 | E96: Bandung | F96: =PROPER(TRIM(SUBSTITUTE(SUBSTITUTE(E96,"Jaksel","Jakarta Selatan"),"Tangerang Kota","Tangerang"))) -> Bandung | G96: Gita Ayu | H96: =IF(G96="","Unknown",G96) -> Gita Ayu | I96: Nia Firmansyah | J96: =IF(I96="","Unknown",I96) -> Nia Firmansyah | K96: P002 | L96: Aerox | M96: 1 | N96: 29800000 | O96: 894000 | P96: 28906000 | Q96: =IF(P96=0,"Batal/Refund","Normal") -> Normal | R96: Debit/Transfer | S96: Proses Kredit | T96: Referral | U96: =COUNTIF($A$2:$A$342,A96) -> 1
A97: TRX-1198 | B97: 16 Juli 2026 | C97: =SUBSTITUTE(SUBSTITUTE(SUBSTITUTE(SUBSTITUTE(SUBSTITUTE(SUBSTITUTE(SUBSTITUTE(SUBSTITUTE(SUBSTITUTE(SUBSTITUTE(SUBSTITUTE(SUBSTITUTE(B97," Januari ","/01/")," Februari ","/02/")," Maret ","/03/")," April ","/04/")," Mei ","/05/")," Juni ","/06/")," Juli ","/07/")," Agustus ","/08/")," September ","/09/")," Oktober ","/10/")," November ","/11/")," Desember ","/12/") -> 16/07/2026 | D97: =IFERROR(DATE(VALUE(LEFT(C97,4)),VALUE(MID(C97,6,2)),VALUE(RIGHT(C97,2))),DATE(VALUE(RIGHT(C97,4)),VALUE(MID(C97,4,2)),VALUE(LEFT(C97,2)))) -> 46219 | E97: Sukabumi | F97: =PROPER(TRIM(SUBSTITUTE(SUBSTITUTE(E97,"Jaksel","Jakarta Selatan"),"Tangerang Kota","Tangerang"))) -> Sukabumi | G97: Lukman Hakim | H97: =IF(G97="","Unknown",G97) -> Lukman Hakim | I97: Jihan Lestari | J97: =IF(I97="","Unknown",I97) -> Jihan Lestari | K97: P004 | L97: Mio | M97: 1 | N97: 18900000 | O97: 567000 | P97: 18333000 | Q97: =IF(P97=0,"Batal/Refund","Normal") -> Normal | R97: Cash | S97: Proses Kredit | T97: Online - Website | U97: =COUNTIF($A$2:$A$342,A97) -> 1
A98: TRX-1071 | B98: 14/07/2026 | C98: =SUBSTITUTE(SUBSTITUTE(SUBSTITUTE(SUBSTITUTE(SUBSTITUTE(SUBSTITUTE(SUBSTITUTE(SUBSTITUTE(SUBSTITUTE(SUBSTITUTE(SUBSTITUTE(SUBSTITUTE(B98," Januari ","/01/")," Februari ","/02/")," Maret ","/03/")," April ","/04/")," Mei ","/05/")," Juni ","/06/")," Juli ","/07/")," Agustus ","/08/")," September ","/09/")," Oktober ","/10/")," November ","/11/")," Desember ","/12/") -> 14/07/2026 | D98: =IFERROR(DATE(VALUE(LEFT(C98,4)),VALUE(MID(C98,6,2)),VALUE(RIGHT(C98,2))),DATE(VALUE(RIGHT(C98,4)),VALUE(MID(C98,4,2)),VALUE(LEFT(C98,2)))) -> 46217 | E98: Jakarta Timur | F98: =PROPER(TRIM(SUBSTITUTE(SUBSTITUTE(E98,"Jaksel","Jakarta Selatan"),"Tangerang Kota","Tangerang"))) -> Jakarta Timur | G98: Rudi Hartono | H98: =IF(G98="","Unknown",G98) -> Rudi Hartono | I98: Oscar Lestari | J98: =IF(I98="","Unknown",I98) -> Oscar Lestari | K98: P002 | L98: Aerox | M98: 1 | N98: 29800000 | O98: 596000 | P98: 29204000 | Q98: =IF(P98=0,"Batal/Refund","Normal") -> Normal | R98: Debit/Transfer | S98: Lunas | T98: Referral | U98: =COUNTIF($A$2:$A$342,A98) -> 1
A99: TRX-1181 | B99: 16/07/2026 | C99: =SUBSTITUTE(SUBSTITUTE(SUBSTITUTE(SUBSTITUTE(SUBSTITUTE(SUBSTITUTE(SUBSTITUTE(SUBSTITUTE(SUBSTITUTE(SUBSTITUTE(SUBSTITUTE(SUBSTITUTE(B99," Januari ","/01/")," Februari ","/02/")," Maret ","/03/")," April ","/04/")," Mei ","/05/")," Juni ","/06/")," Juli ","/07/")," Agustus ","/08/")," September ","/09/")," Oktober ","/10/")," November ","/11/")," Desember ","/12/") -> 16/07/2026 | D99: =IFERROR(DATE(VALUE(LEFT(C99,4)),VALUE(MID(C99,6,2)),VALUE(RIGHT(C99,2))),DATE(VALUE(RIGHT(C99,4)),VALUE(MID(C99,4,2)),VALUE(LEFT(C99,2)))) -> 46219 | E99: Jakarta Selatan | F99: =PROPER(TRIM(SUBSTITUTE(SUBSTITUTE(E99,"Jaksel","Jakarta Selatan"),"Tangerang Kota","Tangerang"))) -> Jakarta Selatan | G99: Lukman Hakim | H99: =IF(G99="","Unknown",G99) -> Lukman Hakim | I99: Made Hidayat | J99: =IF(I99="","Unknown",I99) -> Made Hidayat | K99: P002 | L99: Aerox | M99: 1 | N99: 29800000 | O99: 1490000 | P99: 28310000 | Q99: =IF(P99=0,"Batal/Refund","Normal") -> Normal | R99: Kredit - Adira | S99: Lunas | T99: Referral | U99: =COUNTIF($A$2:$A$342,A99) -> 1
... A102: TRX-1128 | B102: 2026-07-15 | C102: =SUBSTITUTE(SUBSTITUTE(SUBSTITUTE(SUBSTITUTE(SUBSTITUTE(SUBSTITUTE(SUBSTITUTE(SUBSTITUTE(SUBSTITUTE(SUBSTITUTE(SUBSTITUTE(SUBSTITUTE(B102," Januari ","/01/")," Februari ","/02/")," Maret ","/03/")," April ","/04/")," Mei ","/05/")," Juni ","/06/")," Juli ","/07/")," Agustus ","/08/")," September ","/09/")," Oktober ","/10/")," November ","/11/")," Desember ","/12/") -> 2026-07-15 | D102: =IFERROR(DATE(VALUE(LEFT(C102,4)),VALUE(MID(C102,6,2)),VALUE(RIGHT(C102,2))),DATE(VALUE(RIGHT(C102,4)),VALUE(MID(C102,4,2)),VALUE(LEFT(C102,2)))) -> 46218 | E102: Jaksel | F102: =PROPER(TRIM(SUBSTITUTE(SUBSTITUTE(E102,"Jaksel","Jakarta Selatan"),"Tangerang Kota","Tangerang"))) -> Jakarta Selatan | G102: Vino Bastian G. | H102: =IF(G102="","Unknown",G102) -> Vino Bastian G. | I102: Tono Hidayat | J102: =IF(I102="","Unknown",I102) -> Tono Hidayat | K102: P004 | L102: Mio | M102: 1 | N102: 18900000 | O102: 567000 | P102: 18333000 | Q102: =IF(P102=0,"Batal/Refund","Normal") -> Normal | R102: Kredit - Adira | S102: Lunas | T102: Pameran | U102: =COUNTIF($A$2:$A$342,A102) -> 1
A103: TRX-1334 | B103: 19 Juli 2026 | C103: =SUBSTITUTE(SUBSTITUTE(SUBSTITUTE(SUBSTITUTE(SUBSTITUTE(SUBSTITUTE(SUBSTITUTE(SUBSTITUTE(SUBSTITUTE(SUBSTITUTE(SUBSTITUTE(SUBSTITUTE(B103," Januari ","/01/")," Februari ","/02/")," Maret ","/03/")," April ","/04/")," Mei ","/05/")," Juni ","/06/")," Juli ","/07/")," Agustus ","/08/")," September ","/09/")," Oktober ","/10/")," November ","/11/")," Desember ","/12/") -> 19/07/2026 | D103: =IFERROR(DATE(VALUE(LEFT(C103,4)),VALUE(MID(C103,6,2)),VALUE(RIGHT(C103,2))),DATE(VALUE(RIGHT(C103,4)),VALUE(MID(C103,4,2)),VALUE(LEFT(C103,2)))) -> 46222 | E103: Karawang | F103: =PROPER(TRIM(SUBSTITUTE(SUBSTITUTE(E103,"Jaksel","Jakarta Selatan"),"Tangerang Kota","Tangerang"))) -> Karawang | H103: =IF(G103="","Unknown",G103) -> Unknown | I103: Galih Ramadhan | J103: =IF(I103="","Unknown",I103) -> Galih Ramadhan | K103: P010 | L103: Freego | M103: 1 | N103: 22300000 | O103: 446000 | P103: 21854000 | Q103: =IF(P103=0,"Batal/Refund","Normal") -> Normal | R103: Kredit - FIF | S103: Lunas | T103: Online - Website | U103: =COUNTIF($A$2:$A$342,A103) -> 1
A104: TRX-1296 | B104: 18 Juli 2026 | C104: =SUBSTITUTE(SUBSTITUTE(SUBSTITUTE(SUBSTITUTE(SUBSTITUTE(SUBSTITUTE(SUBSTITUTE(SUBSTITUTE(SUBSTITUTE(SUBSTITUTE(SUBSTITUTE(SUBSTITUTE(B104," Januari ","/01/")," Februari ","/02/")," Maret ","/03/")," April ","/04/")," Mei ","/05/")," Juni ","/06/")," Juli ","/07/")," Agustus ","/08/")," September ","/09/")," Oktober ","/10/")," November ","/11/")," Desember ","/12/") -> 18/07/2026 | D104: =IFERROR(DATE(VALUE(LEFT(C104,4)),VALUE(MID(C104,6,2)),VALUE(RIGHT(C104,2))),DATE(VALUE(RIGHT(C104,4)),VALUE(MID(C104,4,2)),VALUE(LEFT(C104,2)))) -> 46221 | E104: Sukabumi | F104: =PROPER(TRIM(SUBSTITUTE(SUBSTITUTE(E104,"Jaksel","Jakarta Selatan"),"Tangerang Kota","Tangerang"))) -> Sukabumi | G104: Sari Dewi | H104: =IF(G104="","Unknown",G104) -> Sari Dewi | I104: Budi Lestari | J104: =IF(I104="","Unknown",I104) -> Budi Lestari | K104: P001 | L104: NMAX | M104: 1 | N104: 33500000 | O104: 335000 | P104: 33165000 | Q104: =IF(P104=0,"Batal/Refund","Normal") -> Normal | R104: Cash | S104: Lunas | T104: Showroom | U104: =COUNTIF($A$2:$A$342,A104) -> 1
A105: TRX-1249 | B105: 2026-07-18 | C105: =SUBSTITUTE(SUBSTITUTE(SUBSTITUTE(SUBSTITUTE(SUBSTITUTE(SUBSTITUTE(SUBSTITUTE(SUBSTITUTE(SUBSTITUTE(SUBSTITUTE(SUBSTITUTE(SUBSTITUTE(B105," Januari ","/01/")," Februari ","/02/")," Maret ","/03/")," April ","/04/")," Mei ","/05/")," Juni ","/06/")," Juli ","/07/")," Agustus ","/08/")," September ","/09/")," Oktober ","/10/")," November ","/11/")," Desember ","/12/") -> 2026-07-18 | D105: =IFERROR(DATE(VALUE(LEFT(C105,4)),VALUE(MID(C105,6,2)),VALUE(RIGHT(C105,2))),DATE(VALUE(RIGHT(C105,4)),VALUE(MID(C105,4,2)),VALUE(LEFT(C105,2)))) -> 46221 | E105: Bandung | F105: =PROPER(TRIM(SUBSTITUTE(SUBSTITUTE(E105,"Jaksel","Jakarta Selatan"),"Tangerang Kota","Tangerang"))) -> Bandung | G105: Lukman Hakim | H105: =IF(G105="","Unknown",G105) -> Lukman Hakim | I105: Budi Anggraini | J105: =IF(I105="","Unknown",I105) -> Budi Anggraini | K105: P005 | L105: Fazzio | M105: 1 | N105: 21500000 | O105: 430000 | P105: 21070000 | Q105: =IF(P105=0,"Batal/Refund","Normal") -> Normal | R105: Kredit - FIF | S105: DP | T105: Referral | U105: =COUNTIF($A$2:$A$342,A105) -> 1
A106: TRX-1164 | B106: 2026-07-16 | C106: =SUBSTITUTE(SUBSTITUTE(SUBSTITUTE(SUBSTITUTE(SUBSTITUTE(SUBSTITUTE(SUBSTITUTE(SUBSTITUTE(SUBSTITUTE(SUBSTITUTE(SUBSTITUTE(SUBSTITUTE(B106," Januari ","/01/")," Februari ","/02/")," Maret ","/03/")," April ","/04/")," Mei ","/05/")," Juni ","/06/")," Juli ","/07/")," Agustus ","/08/")," September ","/09/")," Oktober ","/10/")," November ","/11/")," Desember ","/12/") -> 2026-07-16 | D106: =IFERROR(DATE(VALUE(LEFT(C106,4)),VALUE(MID(C106,6,2)),VALUE(RIGHT(C106,2))),DATE(VALUE(RIGHT(C106,4)),VALUE(MID(C106,4,2)),VALUE(LEFT(C106,2)))) -> 46219 | E106: Cikarang | F106: =PROPER(TRIM(SUBSTITUTE(SUBSTITUTE(E106,"Jaksel","Jakarta Selatan"),"Tangerang Kota","Tangerang"))) -> Cikarang | G106: Indah Permata | H106: =IF(G106="","Unknown",G106) -> Indah Permata | I106: Jihan Ramadhan | J106: =IF(I106="","Unknown",I106) -> Jihan Ramadhan | K106: P009 | L106: Grand Filano | M106: 1 | N106: 26900000 | O106: 1345000 | P106: 25555000 | Q106: =IF(P106=0,"Batal/Refund","Normal") -> Normal | R106: Kredit - FIF | S106: Lunas | T106: Referral | U106: =COUNTIF($A$2:$A$342,A106) -> 1
A107: TRX-1040 | B107: 14/07/2026 | C107: =SUBSTITUTE(SUBSTITUTE(SUBSTITUTE(SUBSTITUTE(SUBSTITUTE(SUBSTITUTE(SUBSTITUTE(SUBSTITUTE(SUBSTITUTE(SUBSTITUTE(SUBSTITUTE(SUBSTITUTE(B107," Januari ","/01/")," Februari ","/02/")," Maret ","/03/")," April ","/04/")," Mei ","/05/")," Juni ","/06/")," Juli ","/07/")," Agustus ","/08/")," September ","/09/")," Oktober ","/10/")," November ","/11/")," Desember ","/12/") -> 14/07/2026 | D107: =IFERROR(DATE(VALUE(LEFT(C107,4)),VALUE(MID(C107,6,2)),VALUE(RIGHT(C107,2))),DATE(VALUE(RIGHT(C107,4)),VALUE(MID(C107,4,2)),VALUE(LEFT(C107,2)))) -> 46217 | E107: Bekasi | F107: =PROPER(TRIM(SUBSTITUTE(SUBSTITUTE(E107,"Jaksel","Jakarta Selatan"),"Tangerang Kota","Tangerang"))) -> Bekasi | G107: Lukman Hakim | H107: =IF(G107="","Unknown",G107) -> Lukman Hakim | I107: Kevin Hidayat | J107: =IF(I107="","Unknown",I107) -> Kevin Hidayat | K107: P001 | L107: NMAX | M107: 1 | N107: 33500000 | O107: 0 | P107: 33500000 | Q107: =IF(P107=0,"Batal/Refund","Normal") -> Normal | R107: Cash | S107: Lunas | T107: Pameran | U107: =COUNTIF($A$2:$A$342,A107) -> 1
A108: TRX-1113 | B108: 2026-07-15 | C108: =SUBSTITUTE(SUBSTITUTE(SUBSTITUTE(SUBSTITUTE(SUBSTITUTE(SUBSTITUTE(SUBSTITUTE(SUBSTITUTE(SUBSTITUTE(SUBSTITUTE(SUBSTITUTE(SUBSTITUTE(B108," Januari ","/01/")," Februari ","/02/")," Maret ","/03/")," April ","/04/")," Mei ","/05/")," Juni ","/06/")," Juli ","/07/")," Agustus ","/08/")," September ","/09/")," Oktober ","/10/")," November ","/11/")," Desember ","/12/") -> 2026-07-15 | D108: =IFERROR(DATE(VALUE(LEFT(C108,4)),VALUE(MID(C108,6,2)),VALUE(RIGHT(C108,2))),DATE(VALUE(RIGHT(C108,4)),VALUE(MID(C108,4,2)),VALUE(LEFT(C108,2)))) -> 46218 | E108: Bandung | F108: =PROPER(TRIM(SUBSTITUTE(SUBSTITUTE(E108,"Jaksel","Jakarta Selatan"),"Tangerang Kota","Tangerang"))) -> Bandung | H108: =IF(G108="","Unknown",G108) -> Unknown | I108: Lala Pratama | J108: =IF(I108="","Unknown",I108) -> Lala Pratama | K108: P005 | L108: Fazzio | M108: 1 | N108: 21500000 | O108: 1075000 | P108: 20425000 | Q108: =IF(P108=0,"Batal/Refund","Normal") -> Normal | R108: Debit/Transfer | S108: Lunas | T108: Referral | U108: =COUNTIF($A$2:$A$342,A108) -> 1
A109: TRX-1079 | B109: 2026-07-14 | C109: =SUBSTITUTE(SUBSTITUTE(SUBSTITUTE(SUBSTITUTE(SUBSTITUTE(SUBSTITUTE(SUBSTITUTE(SUBSTITUTE(SUBSTITUTE(SUBSTITUTE(SUBSTITUTE(SUBSTITUTE(B109," Januari ","/01/")," Februari ","/02/")," Maret ","/03/")," April ","/04/")," Mei ","/05/")," Juni ","/06/")," Juli ","/07/")," Agustus ","/08/")," September ","/09/")," Oktober ","/10/")," November ","/11/")," Desember ","/12/") -> 2026-07-14 | D109: =IFERROR(DATE(VALUE(LEFT(C109,4)),VALUE(MID(C109,6,2)),VALUE(RIGHT(C109,2))),DATE(VALUE(RIGHT(C109,4)),VALUE(MID(C109,4,2)),VALUE(LEFT(C109,2)))) -> 46217 | E109: Karawang | F109: =PROPER(TRIM(SUBSTITUTE(SUBSTITUTE(E109,"Jaksel","Jakarta Selatan"),"Tangerang Kota","Tangerang"))) -> Karawang | G109: Mira Anjani | H109: =IF(G109="","Unknown",G109) -> Mira Anjani | I109: Oscar Pratama | J109: =IF(I109="","Unknown",I109) -> Oscar Pratama | K109: P008 | L109: MX King | M109: 1 | N109: 24600000 | O109: 246000 | P109: 24354000 | Q109: =IF(P109=0,"Batal/Refund","Normal") -> Normal | R109: Debit/Transfer | S109: Lunas | T109: Referral | U109: =COUNTIF($A$2:$A$342,A109) -> 1
A110: TRX-1338 | B110: 2026-07-19 | C110: =SUBSTITUTE(SUBSTITUTE(SUBSTITUTE(SUBSTITUTE(SUBSTITUTE(SUBSTITUTE(SUBSTITUTE(SUBSTITUTE(SUBSTITUTE(SUBSTITUTE(SUBSTITUTE(SUBSTITUTE(B110," Januari ","/01/")," Februari ","/02/")," Maret ","/03/")," April ","/04/")," Mei ","/05/")," Juni ","/06/")," Juli ","/07/")," Agustus ","/08/")," September ","/09/")," Oktober ","/10/")," November ","/11/")," Desember ","/12/") -> 2026-07-19 | D110: =IFERROR(DATE(VALUE(LEFT(C110,4)),VALUE(MID(C110,6,2)),VALUE(RIGHT(C110,2))),DATE(VALUE(RIGHT(C110,4)),VALUE(MID(C110,4,2)),VALUE(LEFT(C110,2)))) -> 46222 | E110: Cibubur | F110: =PROPER(TRIM(SUBSTITUTE(SUBSTITUTE(E110,"Jaksel","Jakarta Selatan"),"Tangerang Kota","Tangerang"))) -> Cibubur | G110: Eka Putri | H110: =IF(G110="","Unknown",G110) -> Eka Putri | I110: Kevin Lestari | J110: =IF(I110="","Unknown",I110) -> Kevin Lestari | K110: P001 | L110: NMAX | M110: 1 | N110: 33500000 | O110: 670000 | P110: 32830000 | Q110: =IF(P110=0,"Batal/Refund","Normal") -> Normal | R110: Kredit - FIF | S110: Lunas | T110: Showroom | U110: =COUNTIF($A$2:$A$342,A110) -> 1
A111: TRX-1190 | B111: 16/07/2026 | C111: =SUBSTITUTE(SUBSTITUTE(SUBSTITUTE(SUBSTITUTE(SUBSTITUTE(SUBSTITUTE(SUBSTITUTE(SUBSTITUTE(SUBSTITUTE(SUBSTITUTE(SUBSTITUTE(SUBSTITUTE(B111," Januari ","/01/")," Februari ","/02/")," Maret ","/03/")," April ","/04/")," Mei ","/05/")," Juni ","/06/")," Juli ","/07/")," Agustus ","/08/")," September ","/09/")," Oktober ","/10/")," November ","/11/")," Desember ","/12/") -> 16/07/2026 | D111: =IFERROR(DATE(VALUE(LEFT(C111,4)),VALUE(MID(C111,6,2)),VALUE(RIGHT(C111,2))),DATE(VALUE(RIGHT(C111,4)),VALUE(MID(C111,4,2)),VALUE(LEFT(C111,2)))) -> 46219 | E111: Cibubur | F111: =PROPER(TRIM(SUBSTITUTE(SUBSTITUTE(E111,"Jaksel","Jakarta Selatan"),"Tangerang Kota","Tangerang"))) -> Cibubur | G111: Puji Lestari | H111: =IF(G111="","Unknown",G111) -> Puji Lestari | I111: Putra Firmansyah | J111: =IF(I111="","Unknown",I111) -> Putra Firmansyah | K111: P007 | L111: XSR 155 | M111: 1 | N111: 41000000 | O111: 410000 | P111: 40590000 | Q111: =IF(P111=0,"Batal/Refund","Normal") -> Normal | R111: Debit/Transfer | S111: Lunas | T111: Pameran | U111: =COUNTIF($A$2:$A$342,A111) -> 1
A112: TRX-1330 | B112: 2026-07-19 | C112: =SUBSTITUTE(SUBSTITUTE(SUBSTITUTE(SUBSTITUTE(SUBSTITUTE(SUBSTITUTE(SUBSTITUTE(SUBSTITUTE(SUBSTITUTE(SUBSTITUTE(SUBSTITUTE(SUBSTITUTE(B112," Januari ","/01/")," Februari ","/02/")," Maret ","/03/")," April ","/04/")," Mei ","/05/")," Juni ","/06/")," Juli ","/07/")," Agustus ","/08/")," September ","/09/")," Oktober ","/10/")," November ","/11/")," Desember ","/12/") -> 2026-07-19 | D112: =IFERROR(DATE(VALUE(LEFT(C112,4)),VALUE(MID(C112,6,2)),VALUE(RIGHT(C112,2))),DATE(VALUE(RIGHT(C112,4)),VALUE(MID(C112,4,2)),VALUE(LEFT(C112,2)))) -> 46222 | E112: Jakarta Selatan | F112: =PROPER(TRIM(SUBSTITUTE(SUBSTITUTE(E112,"Jaksel","Jakarta Selatan"),"Tangerang Kota","Tangerang"))) -> Jakarta Selatan | G112: Joko Widodo S. | H112: =IF(G112="","Unknown",G112) -> Joko Widodo S. | I112: Citra Ramadhan | J112: =IF(I112="","Unknown",I112) -> Citra Ramadhan | K112: P003 | L112: Lexi | M112: 1 | N112: 27400000 | O112: 822000 | P112: 0 | Q112: =IF(P112=0,"Batal/Refund","Normal") -> Batal/Refund | R112: Kredit - Adira | S112: Lunas | T112: Pameran | U112: =COUNTIF($A$2:$A$342,A112) -> 1
A113: TRX-1018 | B113: 2026-07-13 | C113: =SUBSTITUTE(SUBSTITUTE(SUBSTITUTE(SUBSTITUTE(SUBSTITUTE(SUBSTITUTE(SUBSTITUTE(SUBSTITUTE(SUBSTITUTE(SUBSTITUTE(SUBSTITUTE(SUBSTITUTE(B113," Januari ","/01/")," Februari ","/02/")," Maret ","/03/")," April ","/04/")," Mei ","/05/")," Juni ","/06/")," Juli ","/07/")," Agustus ","/08/")," September ","/09/")," Oktober ","/10/")," November ","/11/")," Desember ","/12/") -> 2026-07-13 | D113: =IFERROR(DATE(VALUE(LEFT(C113,4)),VALUE(MID(C113,6,2)),VALUE(RIGHT(C113,2))),DATE(VALUE(RIGHT(C113,4)),VALUE(MID(C113,4,2)),VALUE(LEFT(C113,2)))) -> 46216 | E113: Jakarta Selatan | F113: =PROPER(TRIM(SUBSTITUTE(SUBSTITUTE(E113,"Jaksel","Jakarta Selatan"),"Tangerang Kota","Tangerang"))) -> Jakarta Selatan | G113: Sari Dewi | H113: =IF(G113="","Unknown",G113) -> Sari Dewi | I113: Fitri Wijaya | J113: =IF(I113="","Unknown",I113) -> Fitri Wijaya | K113: P004 | L113: Mio | M113: 1 | N113: 18900000 | O113: 0 | P113: 18900000 | Q113: =IF(P113=0,"Batal/Refund","Normal") -> Normal | R113: Debit/Transfer | S113: Lunas | T113: Online - Website | U113: =COUNTIF($A$2:$A$342,A113) -> 1
A114: TRX-1274 | B114: 18/07/2026 | C114: =SUBSTITUTE(SUBSTITUTE(SUBSTITUTE(SUBSTITUTE(SUBSTITUTE(SUBSTITUTE(SUBSTITUTE(SUBSTITUTE(SUBSTITUTE(SUBSTITUTE(SUBSTITUTE(SUBSTITUTE(B114," Januari ","/01/")," Februari ","/02/")," Maret ","/03/")," April ","/04/")," Mei ","/05/")," Juni ","/06/")," Juli ","/07/")," Agustus ","/08/")," September ","/09/")," Oktober ","/10/")," November ","/11/")," Desember ","/12/") -> 18/07/2026 | D114: =IFERROR(DATE(VALUE(LEFT(C114,4)),VALUE(MID(C114,6,2)),VALUE(RIGHT(C114,2))),DATE(VALUE(RIGHT(C114,4)),VALUE(MID(C114,4,2)),VALUE(LEFT(C114,2)))) -> 46221 | E114: Jakarta Timur | F114: =PROPER(TRIM(SUBSTITUTE(SUBSTITUTE(E114,"Jaksel","Jakarta Selatan"),"Tangerang Kota","Tangerang"))) -> Jakarta Timur | G114: Nanda Pratama | H114: =IF(G114="","Unknown",G114) -> Nanda Pratama | I114: Oscar Lestari | J114: =IF(I114="","Unknown",I114) -> Oscar Lestari | K114: P008 | L114: MX King | M114: 1 | N114: 24600000 | O114: 246000 | P114: 24354000 | Q114: =IF(P114=0,"Batal/Refund","Normal") -> Normal | R114: Kredit - Adira | S114: Lunas | T114: Showroom | U114: =COUNTIF($A$2:$A$342,A114) -> 1
A115: TRX-1229 | B115: 2026-07-17 | C115: =SUBSTITUTE(SUBSTITUTE(SUBSTITUTE(SUBSTITUTE(SUBSTITUTE(SUBSTITUTE(SUBSTITUTE(SUBSTITUTE(SUBSTITUTE(SUBSTITUTE(SUBSTITUTE(SUBSTITUTE(B115," Januari ","/01/")," Februari ","/02/")," Maret ","/03/")," April ","/04/")," Mei ","/05/")," Juni ","/06/")," Juli ","/07/")," Agustus ","/08/")," September ","/09/")," Oktober ","/10/")," November ","/11/")," Desember ","/12/") -> 2026-07-17 | D115: =IFERROR(DATE(VALUE(LEFT(C115,4)),VALUE(MID(C115,6,2)),VALUE(RIGHT(C115,2))),DATE(VALUE(RIGHT(C115,4)),VALUE(MID(C115,4,2)),VALUE(LEFT(C115,2)))) -> 46220 | E115: Jakarta Selatan | F115: =PROPER(TRIM(SUBSTITUTE(SUBSTITUTE(E115,"Jaksel","Jakarta Selatan"),"Tangerang Kota","Tangerang"))) -> Jakarta Selatan | G115: Rudi Hartono | H115: =IF(G115="","Unknown",G115) -> Rudi Hartono | I115: Irfan Saputra | J115: =IF(I115="","Unknown",I115) -> Irfan Saputra | K115: P003 | L115: Lexi | M115: 1 | N115: 27400000 | O115: 274000 | P115: 27126000 | Q115: =IF(P115=0,"Batal/Refund","Normal") -> Normal | R115: Kredit - Adira | S115: Lunas | T115: Online - Website | U115: =COUNTIF($A$2:$A$342,A115) -> 1
A116: TRX-1089 | B116: 2026-07-14 | C116: =SUBSTITUTE(SUBSTITUTE(SUBSTITUTE(SUBSTITUTE(SUBSTITUTE(SUBSTITUTE(SUBSTITUTE(SUBSTITUTE(SUBSTITUTE(SUBSTITUTE(SUBSTITUTE(SUBSTITUTE(B116," Januari ","/01/")," Februari ","/02/")," Maret ","/03/")," April ","/04/")," Mei ","/05/")," Juni ","/06/")," Juli ","/07/")," Agustus ","/08/")," September ","/09/")," Oktober ","/10/")," November ","/11/")," Desember ","/12/") -> 2026-07-14 | D116: =IFERROR(DATE(VALUE(LEFT(C116,4)),VALUE(MID(C116,6,2)),VALUE(RIGHT(C116,2))),DATE(VALUE(RIGHT(C116,4)),VALUE(MID(C116,4,2)),VALUE(LEFT(C116,2)))) -> 46217 | E116: Sukabumi | F116: =PROPER(TRIM(SUBSTITUTE(SUBSTITUTE(E116,"Jaksel","Jakarta Selatan"),"Tangerang Kota","Tangerang"))) -> Sukabumi | G116: Rangga Saputra | H116: =IF(G116="","Unknown",G116) -> Rangga Saputra | I116: Dewi Hidayat | J116: =IF(I116="","Unknown",I116) -> Dewi Hidayat | K116: P002 | L116: Aerox | M116: 1 | N116: 29800000 | O116: 894000 | P116: 28906000 | Q116: =IF(P116=0,"Batal/Refund","Normal") -> Normal | R116: Debit/Transfer | S116: Lunas | T116: Online - Website | U116: =COUNTIF($A$2:$A$342,A116) -> 1
A117: TRX-1170 | B117: 16/07/2026 | C117: =SUBSTITUTE(SUBSTITUTE(SUBSTITUTE(SUBSTITUTE(SUBSTITUTE(SUBSTITUTE(SUBSTITUTE(SUBSTITUTE(SUBSTITUTE(SUBSTITUTE(SUBSTITUTE(SUBSTITUTE(B117," Januari ","/01/")," Februari ","/02/")," Maret ","/03/")," April ","/04/")," Mei ","/05/")," Juni ","/06/")," Juli ","/07/")," Agustus ","/08/")," September ","/09/")," Oktober ","/10/")," November ","/11/")," Desember ","/12/") -> 16/07/2026 | D117: =IFERROR(DATE(VALUE(LEFT(C117,4)),VALUE(MID(C117,6,2)),VALUE(RIGHT(C117,2))),DATE(VALUE(RIGHT(C117,4)),VALUE(MID(C117,4,2)),VALUE(LEFT(C117,2)))) -> 46219 | E117: Serang | F117: =PROPER(TRIM(SUBSTITUTE(SUBSTITUTE(E117,"Jaksel","Jakarta Selatan"),"Tangerang Kota","Tangerang"))) -> Serang | G117: Sari Dewi | H117: =IF(G117="","Unknown",G117) -> Sari Dewi | I117: Lala Lestari | J117: =IF(I117="","Unknown",I117) -> Lala Lestari | K117: P009 | L117: Grand Filano | M117: 1 | N117: 26900000 | O117: 0 | P117: 26900000 | Q117: =IF(P117=0,"Batal/Refund","Normal") -> Normal | R117: Kredit - Mandiri Tunas | S117: Lunas | T117: Online - Website | U117: =COUNTIF($A$2:$A$342,A117) -> 1
A118: TRX-1043 | B118: 2026-07-14 | C118: =SUBSTITUTE(SUBSTITUTE(SUBSTITUTE(SUBSTITUTE(SUBSTITUTE(SUBSTITUTE(SUBSTITUTE(SUBSTITUTE(SUBSTITUTE(SUBSTITUTE(SUBSTITUTE(SUBSTITUTE(B118," Januari ","/01/")," Februari ","/02/")," Maret ","/03/")," April ","/04/")," Mei ","/05/")," Juni ","/06/")," Juli ","/07/")," Agustus ","/08/")," September ","/09/")," Oktober ","/10/")," November ","/11/")," Desember ","/12/") -> 2026-07-14 | D118: =IFERROR(DATE(VALUE(LEFT(C118,4)),VALUE(MID(C118,6,2)),VALUE(RIGHT(C118,2))),DATE(VALUE(RIGHT(C118,4)),VALUE(MID(C118,4,2)),VALUE(LEFT(C118,2)))) -> 46217 | E118: BEKASI | F118: =PROPER(TRIM(SUBSTITUTE(SUBSTITUTE(E118,"Jaksel","Jakarta Selatan"),"Tangerang Kota","Tangerang"))) -> Bekasi | G118: Nanda Pratama | H118: =IF(G118="","Unknown",G118) -> Nanda Pratama | I118: Galih Wijaya | J118: =IF(I118="","Unknown",I118) -> Galih Wijaya | K118: P001 | L118: NMAX | M118: 1 | N118: 33500000 | O118: 335000 | P118: 33165000 | Q118: =IF(P118=0,"Batal/Refund","Normal") -> Normal | R118: Debit/Transfer | S118: Lunas | T118: Showroom | U118: =COUNTIF($A$2:$A$342,A118) -> 1
A119: TRX-1162 | B119: 2026-07-16 | C119: =SUBSTITUTE(SUBSTITUTE(SUBSTITUTE(SUBSTITUTE(SUBSTITUTE(SUBSTITUTE(SUBSTITUTE(SUBSTITUTE(SUBSTITUTE(SUBSTITUTE(SUBSTITUTE(SUBSTITUTE(B119," Januari ","/01/")," Februari ","/02/")," Maret ","/03/")," April ","/04/")," Mei ","/05/")," Juni ","/06/")," Juli ","/07/")," Agustus ","/08/")," September ","/09/")," Oktober ","/10/")," November ","/11/")," Desember ","/12/") -> 2026-07-16 | D119: =IFERROR(DATE(VALUE(LEFT(C119,4)),VALUE(MID(C119,6,2)),VALUE(RIGHT(C119,2))),DATE(VALUE(RIGHT(C119,4)),VALUE(MID(C119,4,2)),VALUE(LEFT(C119,2)))) -> 46219 | E119: Bogor | F119: =PROPER(TRIM(SUBSTITUTE(SUBSTITUTE(E119,"Jaksel","Jakarta Selatan"),"Tangerang Kota","Tangerang"))) -> Bogor | G119: Puji Lestari | H119: =IF(G119="","Unknown",G119) -> Puji Lestari | I119: Citra Firmansyah | J119: =IF(I119="","Unknown",I119) -> Citra Firmansyah | K119: P003 | L119: Lexi | M119: 1 | N119: 27400000 | O119: 274000 | P119: 27126000 | Q119: =IF(P119=0,"Batal/Refund","Normal") -> Normal | R119: Kredit - Mandiri Tunas | S119: Lunas | T119: Showroom | U119: =COUNTIF($A$2:$A$342,A119) -> 1
A120: TRX-1175 | B120: 16/07/2026 | C120: =SUBSTITUTE(SUBSTITUTE(SUBSTITUTE(SUBSTITUTE(SUBSTITUTE(SUBSTITUTE(SUBSTITUTE(SUBSTITUTE(SUBSTITUTE(SUBSTITUTE(SUBSTITUTE(SUBSTITUTE(B120," Januari ","/01/")," Februari ","/02/")," Maret ","/03/")," April ","/04/")," Mei ","/05/")," Juni ","/06/")," Juli ","/07/")," Agustus ","/08/")," September ","/09/")," Oktober ","/10/")," November ","/11/")," Desember ","/12/") -> 16/07/2026 | D120: =IFERROR(DATE(VALUE(LEFT(C120,4)),VALUE(MID(C120,6,2)),VALUE(RIGHT(C120,2))),DATE(VALUE(RIGHT(C120,4)),VALUE(MID(C120,4,2)),VALUE(LEFT(C120,2)))) -> 46219 | E120: Serang | F120: =PROPER(TRIM(SUBSTITUTE(SUBSTITUTE(E120,"Jaksel","Jakarta Selatan"),"Tangerang Kota","Tangerang"))) -> Serang | G120: Vino Bastian G. | H120: =IF(G120="","Unknown",G120) -> Vino Bastian G. | I120: Made Hidayat | J120: =IF(I120="","Unknown",I120) -> Made Hidayat | K120: P001 | L120: NMAX | M120: 1 | N120: 33500000 | O120: 0 | P120: 33500000 | Q120: =IF(P120=0,"Batal/Refund","Normal") -> Normal | R120: Kredit - Mandiri Tunas | S120: Lunas | T120: Online - Website | U120: =COUNTIF($A$2:$A$342,A120) -> 1
... A125: TRX-1230 | B125: 2026-07-17 | C125: =SUBSTITUTE(SUBSTITUTE(SUBSTITUTE(SUBSTITUTE(SUBSTITUTE(SUBSTITUTE(SUBSTITUTE(SUBSTITUTE(SUBSTITUTE(SUBSTITUTE(SUBSTITUTE(SUBSTITUTE(B125," Januari ","/01/")," Februari ","/02/")," Maret ","/03/")," April ","/04/")," Mei ","/05/")," Juni ","/06/")," Juli ","/07/")," Agustus ","/08/")," September ","/09/")," Oktober ","/10/")," November ","/11/")," Desember ","/12/") -> 2026-07-17 | D125: =IFERROR(DATE(VALUE(LEFT(C125,4)),VALUE(MID(C125,6,2)),VALUE(RIGHT(C125,2))),DATE(VALUE(RIGHT(C125,4)),VALUE(MID(C125,4,2)),VALUE(LEFT(C125,2)))) -> 46220 | E125: Jakarta Selatan | F125: =PROPER(TRIM(SUBSTITUTE(SUBSTITUTE(E125,"Jaksel","Jakarta Selatan"),"Tangerang Kota","Tangerang"))) -> Jakarta Selatan | G125: Lina Marlina | H125: =IF(G125="","Unknown",G125) -> Lina Marlina | I125: Hana Maharani | J125: =IF(I125="","Unknown",I125) -> Hana Maharani | K125: P001 | L125: NMAX | M125: 1 | N125: 33500000 | O125: 335000 | P125: 33165000 | Q125: =IF(P125=0,"Batal/Refund","Normal") -> Normal | R125: Kredit - Adira | S125: Lunas | T125: Online - Website | U125: =COUNTIF($A$2:$A$342,A125) -> 1
A126: TRX-1180 | B126: 2026-07-16 | C126: =SUBSTITUTE(SUBSTITUTE(SUBSTITUTE(SUBSTITUTE(SUBSTITUTE(SUBSTITUTE(SUBSTITUTE(SUBSTITUTE(SUBSTITUTE(SUBSTITUTE(SUBSTITUTE(SUBSTITUTE(B126," Januari ","/01/")," Februari ","/02/")," Maret ","/03/")," April ","/04/")," Mei ","/05/")," Juni ","/06/")," Juli ","/07/")," Agustus ","/08/")," September ","/09/")," Oktober ","/10/")," November ","/11/")," Desember ","/12/") -> 2026-07-16 | D126: =IFERROR(DATE(VALUE(LEFT(C126,4)),VALUE(MID(C126,6,2)),VALUE(RIGHT(C126,2))),DATE(VALUE(RIGHT(C126,4)),VALUE(MID(C126,4,2)),VALUE(LEFT(C126,2)))) -> 46219 | E126: Jakarta Selatan | F126: =PROPER(TRIM(SUBSTITUTE(SUBSTITUTE(E126,"Jaksel","Jakarta Selatan"),"Tangerang Kota","Tangerang"))) -> Jakarta Selatan | H126: =IF(G126="","Unknown",G126) -> Unknown | I126: Made Hidayat | J126: =IF(I126="","Unknown",I126) -> Made Hidayat | K126: P004 | L126: Mio | M126: 1 | N126: 18900000 | O126: 378000 | P126: 18522000 | Q126: =IF(P126=0,"Batal/Refund","Normal") -> Normal | R126: Kredit - Mandiri Tunas | S126: Lunas | T126: Online - Website | U126: =COUNTIF($A$2:$A$342,A126) -> 1
A127: TRX-1039 | B127: 14 Juli 2026 | C127: =SUBSTITUTE(SUBSTITUTE(SUBSTITUTE(SUBSTITUTE(SUBSTITUTE(SUBSTITUTE(SUBSTITUTE(SUBSTITUTE(SUBSTITUTE(SUBSTITUTE(SUBSTITUTE(SUBSTITUTE(B127," Januari ","/01/")," Februari ","/02/")," Maret ","/03/")," April ","/04/")," Mei ","/05/")," Juni ","/06/")," Juli ","/07/")," Agustus ","/08/")," September ","/09/")," Oktober ","/10/")," November ","/11/")," Desember ","/12/") -> 14/07/2026 | D127: =IFERROR(DATE(VALUE(LEFT(C127,4)),VALUE(MID(C127,6,2)),VALUE(RIGHT(C127,2))),DATE(VALUE(RIGHT(C127,4)),VALUE(MID(C127,4,2)),VALUE(LEFT(C127,2)))) -> 46217 | E127: Bekasi | F127: =PROPER(TRIM(SUBSTITUTE(SUBSTITUTE(E127,"Jaksel","Jakarta Selatan"),"Tangerang Kota","Tangerang"))) -> Bekasi | G127: Puji Lestari | H127: =IF(G127="","Unknown",G127) -> Puji Lestari | I127: Tono Firmansyah | J127: =IF(I127="","Unknown",I127) -> Tono Firmansyah | K127: P002 | L127: Aerox | M127: 1 | N127: 29800000 | O127: 596000 | P127: 29204000 | Q127: =IF(P127=0,"Batal/Refund","Normal") -> Normal | R127: Cash | S127: Lunas | T127: Pameran | U127: =COUNTIF($A$2:$A$342,A127) -> 1
A128: TRX-1239 | B128: 2026-07-17 | C128: =SUBSTITUTE(SUBSTITUTE(SUBSTITUTE(SUBSTITUTE(SUBSTITUTE(SUBSTITUTE(SUBSTITUTE(SUBSTITUTE(SUBSTITUTE(SUBSTITUTE(SUBSTITUTE(SUBSTITUTE(B128," Januari ","/01/")," Februari ","/02/")," Maret ","/03/")," April ","/04/")," Mei ","/05/")," Juni ","/06/")," Juli ","/07/")," Agustus ","/08/")," September ","/09/")," Oktober ","/10/")," November ","/11/")," Desember ","/12/") -> 2026-07-17 | D128: =IFERROR(DATE(VALUE(LEFT(C128,4)),VALUE(MID(C128,6,2)),VALUE(RIGHT(C128,2))),DATE(VALUE(RIGHT(C128,4)),VALUE(MID(C128,4,2)),VALUE(LEFT(C128,2)))) -> 46220 | E128: Sukabumi | F128: =PROPER(TRIM(SUBSTITUTE(SUBSTITUTE(E128,"Jaksel","Jakarta Selatan"),"Tangerang Kota","Tangerang"))) -> Sukabumi | G128: Lukman Hakim | H128: =IF(G128="","Unknown",G128) -> Lukman Hakim | I128: Dewi Wijaya | J128: =IF(I128="","Unknown",I128) -> Dewi Wijaya | K128: P003 | L128: Lexi | M128: 1 | N128: 27400000 | O128: 0 | P128: 27400000 | Q128: =IF(P128=0,"Batal/Refund","Normal") -> Normal | R128: Cash | S128: DP | T128: Showroom | U128: =COUNTIF($A$2:$A$342,A128) -> 1
A129: TRX-1292 | B129: 18 Juli 2026 | C129: =SUBSTITUTE(SUBSTITUTE(SUBSTITUTE(SUBSTITUTE(SUBSTITUTE(SUBSTITUTE(SUBSTITUTE(SUBSTITUTE(SUBSTITUTE(SUBSTITUTE(SUBSTITUTE(SUBSTITUTE(B129," Januari ","/01/")," Februari ","/02/")," Maret ","/03/")," April ","/04/")," Mei ","/05/")," Juni ","/06/")," Juli ","/07/")," Agustus ","/08/")," September ","/09/")," Oktober ","/10/")," November ","/11/")," Desember ","/12/") -> 18/07/2026 | D129: =IFERROR(DATE(VALUE(LEFT(C129,4)),VALUE(MID(C129,6,2)),VALUE(RIGHT(C129,2))),DATE(VALUE(RIGHT(C129,4)),VALUE(MID(C129,4,2)),VALUE(LEFT(C129,2)))) -> 46221 | E129: Sukabumi | F129: =PROPER(TRIM(SUBSTITUTE(SUBSTITUTE(E129,"Jaksel","Jakarta Selatan"),"Tangerang Kota","Tangerang"))) -> Sukabumi | H129: =IF(G129="","Unknown",G129) -> Unknown | I129: Oscar Kusuma | J129: =IF(I129="","Unknown",I129) -> Oscar Kusuma | K129: P003 | L129: Lexi | M129: 1 | N129: 27400000 | O129: 0 | P129: 27400000 | Q129: =IF(P129=0,"Batal/Refund","Normal") -> Normal | R129: Cash | S129: DP | T129: Referral | U129: =COUNTIF($A$2:$A$342,A129) -> 1
A130: TRX-1243 | B130: 2026-07-18 | C130: =SUBSTITUTE(SUBSTITUTE(SUBSTITUTE(SUBSTITUTE(SUBSTITUTE(SUBSTITUTE(SUBSTITUTE(SUBSTITUTE(SUBSTITUTE(SUBSTITUTE(SUBSTITUTE(SUBSTITUTE(B130," Januari ","/01/")," Februari ","/02/")," Maret ","/03/")," April ","/04/")," Mei ","/05/")," Juni ","/06/")," Juli ","/07/")," Agustus ","/08/")," September ","/09/")," Oktober ","/10/")," November ","/11/")," Desember ","/12/") -> 2026-07-18 | D130: =IFERROR(DATE(VALUE(LEFT(C130,4)),VALUE(MID(C130,6,2)),VALUE(RIGHT(C130,2))),DATE(VALUE(RIGHT(C130,4)),VALUE(MID(C130,4,2)),VALUE(LEFT(C130,2)))) -> 46221 | E130: BEKASI | F130: =PROPER(TRIM(SUBSTITUTE(SUBSTITUTE(E130,"Jaksel","Jakarta Selatan"),"Tangerang Kota","Tangerang"))) -> Bekasi | G130: Joko Widodo S. | H130: =IF(G130="","Unknown",G130) -> Joko Widodo S. | I130: Irfan Maharani | J130: =IF(I130="","Unknown",I130) -> Irfan Maharani | K130: P002 | L130: Aerox | M130: 1 | N130: 29800000 | O130: 298000 | P130: 29502000 | Q130: =IF(P130=0,"Batal/Refund","Normal") -> Normal | R130: Debit/Transfer | S130: Lunas | T130: Pameran | U130: =COUNTIF($A$2:$A$342,A130) -> 1
A131: TRX-1101 | B131: 2026-07-15 | C131: =SUBSTITUTE(SUBSTITUTE(SUBSTITUTE(SUBSTITUTE(SUBSTITUTE(SUBSTITUTE(SUBSTITUTE(SUBSTITUTE(SUBSTITUTE(SUBSTITUTE(SUBSTITUTE(SUBSTITUTE(B131," Januari ","/01/")," Februari ","/02/")," Maret ","/03/")," April ","/04/")," Mei ","/05/")," Juni ","/06/")," Juli ","/07/")," Agustus ","/08/")," September ","/09/")," Oktober ","/10/")," November ","/11/")," Desember ","/12/") -> 2026-07-15 | D131: =IFERROR(DATE(VALUE(LEFT(C131,4)),VALUE(MID(C131,6,2)),VALUE(RIGHT(C131,2))),DATE(VALUE(RIGHT(C131,4)),VALUE(MID(C131,4,2)),VALUE(LEFT(C131,2)))) -> 46218 | E131: Bekasi | F131: =PROPER(TRIM(SUBSTITUTE(SUBSTITUTE(E131,"Jaksel","Jakarta Selatan"),"Tangerang Kota","Tangerang"))) -> Bekasi | G131: Rangga Saputra | H131: =IF(G131="","Unknown",G131) -> Rangga Saputra | I131: Budi Anggraini | J131: =IF(I131="","Unknown",I131) -> Budi Anggraini | K131: P009 | L131: Grand Filano | M131: 1 | N131: 26900000 | O131: 0 | P131: 26900000 | Q131: =IF(P131=0,"Batal/Refund","Normal") -> Normal | R131: Cash | S131: DP | T131: Online - Website | U131: =COUNTIF($A$2:$A$342,A131) -> 1
A132: TRX-1035 | B132: 14/07/2026 | C132: =SUBSTITUTE(SUBSTITUTE(SUBSTITUTE(SUBSTITUTE(SUBSTITUTE(SUBSTITUTE(SUBSTITUTE(SUBSTITUTE(SUBSTITUTE(SUBSTITUTE(SUBSTITUTE(SUBSTITUTE(B132," Januari ","/01/")," Februari ","/02/")," Maret ","/03/")," April ","/04/")," Mei ","/05/")," Juni ","/06/")," Juli ","/07/")," Agustus ","/08/")," September ","/09/")," Oktober ","/10/")," November ","/11/")," Desember ","/12/") -> 14/07/2026 | D132: =IFERROR(DATE(VALUE(LEFT(C132,4)),VALUE(MID(C132,6,2)),VALUE(RIGHT(C132,2))),DATE(VALUE(RIGHT(C132,4)),VALUE(MID(C132,4,2)),VALUE(LEFT(C132,2)))) -> 46217 | E132: Tangerang | F132: =PROPER(TRIM(SUBSTITUTE(SUBSTITUTE(E132,"Jaksel","Jakarta Selatan"),"Tangerang Kota","Tangerang"))) -> Tangerang | G132: Sari Dewi | H132: =IF(G132="","Unknown",G132) -> Sari Dewi | I132: Rendi Anggraini | J132: =IF(I132="","Unknown",I132) -> Rendi Anggraini | K132: P010 | L132: Freego | M132: 1 | N132: 22300000 | O132: 669000 | P132: 21631000 | Q132: =IF(P132=0,"Batal/Refund","Normal") -> Normal | R132: Kredit - Adira | S132: Lunas | T132: Referral | U132: =COUNTIF($A$2:$A$342,A132) -> 1
A133: TRX-1111 | B133: 2026-07-15 | C133: =SUBSTITUTE(SUBSTITUTE(SUBSTITUTE(SUBSTITUTE(SUBSTITUTE(SUBSTITUTE(SUBSTITUTE(SUBSTITUTE(SUBSTITUTE(SUBSTITUTE(SUBSTITUTE(SUBSTITUTE(B133," Januari ","/01/")," Februari ","/02/")," Maret ","/03/")," April ","/04/")," Mei ","/05/")," Juni ","/06/")," Juli ","/07/")," Agustus ","/08/")," September ","/09/")," Oktober ","/10/")," November ","/11/")," Desember ","/12/") -> 2026-07-15 | D133: =IFERROR(DATE(VALUE(LEFT(C133,4)),VALUE(MID(C133,6,2)),VALUE(RIGHT(C133,2))),DATE(VALUE(RIGHT(C133,4)),VALUE(MID(C133,4,2)),VALUE(LEFT(C133,2)))) -> 46218 | E133: Depok | F133: =PROPER(TRIM(SUBSTITUTE(SUBSTITUTE(E133,"Jaksel","Jakarta Selatan"),"Tangerang Kota","Tangerang"))) -> Depok | G133: Rangga Saputra | H133: =IF(G133="","Unknown",G133) -> Rangga Saputra | I133: Ahmad Wijaya | J133: =IF(I133="","Unknown",I133) -> Ahmad Wijaya | K133: P002 | L133: Aerox | M133: 1 | N133: 29800000 | O133: 1490000 | P133: 28310000 | Q133: =IF(P133=0,"Batal/Refund","Normal") -> Normal | R133: Debit/Transfer | S133: Lunas | T133: Pameran | U133: =COUNTIF($A$2:$A$342,A133) -> 1
A134: TRX-1187 | B134: 2026-07-16 | C134: =SUBSTITUTE(SUBSTITUTE(SUBSTITUTE(SUBSTITUTE(SUBSTITUTE(SUBSTITUTE(SUBSTITUTE(SUBSTITUTE(SUBSTITUTE(SUBSTITUTE(SUBSTITUTE(SUBSTITUTE(B134," Januari ","/01/")," Februari ","/02/")," Maret ","/03/")," April ","/04/")," Mei ","/05/")," Juni ","/06/")," Juli ","/07/")," Agustus ","/08/")," September ","/09/")," Oktober ","/10/")," November ","/11/")," Desember ","/12/") -> 2026-07-16 | D134: =IFERROR(DATE(VALUE(LEFT(C134,4)),VALUE(MID(C134,6,2)),VALUE(RIGHT(C134,2))),DATE(VALUE(RIGHT(C134,4)),VALUE(MID(C134,4,2)),VALUE(LEFT(C134,2)))) -> 46219 | E134: Karawang | F134: =PROPER(TRIM(SUBSTITUTE(SUBSTITUTE(E134,"Jaksel","Jakarta Selatan"),"Tangerang Kota","Tangerang"))) -> Karawang | G134: Mira Anjani | H134: =IF(G134="","Unknown",G134) -> Mira Anjani | I134: Oscar Anggraini | J134: =IF(I134="","Unknown",I134) -> Oscar Anggraini | K134: P002 | L134: Aerox | M134: 1 | N134: 29800000 | O134: 0 | P134: 29800000 | Q134: =IF(P134=0,"Batal/Refund","Normal") -> Normal | R134: Cash | S134: Lunas | T134: Referral | U134: =COUNTIF($A$2:$A$342,A134) -> 1
A135: TRX-1327 | B135: 2026-07-19 | C135: =SUBSTITUTE(SUBSTITUTE(SUBSTITUTE(SUBSTITUTE(SUBSTITUTE(SUBSTITUTE(SUBSTITUTE(SUBSTITUTE(SUBSTITUTE(SUBSTITUTE(SUBSTITUTE(SUBSTITUTE(B135," Januari ","/01/")," Februari ","/02/")," Maret ","/03/")," April ","/04/")," Mei ","/05/")," Juni ","/06/")," Juli ","/07/")," Agustus ","/08/")," September ","/09/")," Oktober ","/10/")," November ","/11/")," Desember ","/12/") -> 2026-07-19 | D135: =IFERROR(DATE(VALUE(LEFT(C135,4)),VALUE(MID(C135,6,2)),VALUE(RIGHT(C135,2))),DATE(VALUE(RIGHT(C135,4)),VALUE(MID(C135,4,2)),VALUE(LEFT(C135,2)))) -> 46222 | E135: Jakarta Selatan | F135: =PROPER(TRIM(SUBSTITUTE(SUBSTITUTE(E135,"Jaksel","Jakarta Selatan"),"Tangerang Kota","Tangerang"))) -> Jakarta Selatan | G135: Puji Lestari | H135: =IF(G135="","Unknown",G135) -> Puji Lestari | I135: Siska Saputra | J135: =IF(I135="","Unknown",I135) -> Siska Saputra | K135: P010 | L135: Freego | M135: 1 | N135: 22300000 | O135: 669000 | P135: 21631000 | Q135: =IF(P135=0,"Batal/Refund","Normal") -> Normal | R135: Debit/Transfer | S135: Lunas | T135: Referral | U135: =COUNTIF($A$2:$A$342,A135) -> 1
A136: TRX-1020 | B136: 2026-07-13 | C136: =SUBSTITUTE(SUBSTITUTE(SUBSTITUTE(SUBSTITUTE(SUBSTITUTE(SUBSTITUTE(SUBSTITUTE(SUBSTITUTE(SUBSTITUTE(SUBSTITUTE(SUBSTITUTE(SUBSTITUTE(B136," Januari ","/01/")," Februari ","/02/")," Maret ","/03/")," April ","/04/")," Mei ","/05/")," Juni ","/06/")," Juli ","/07/")," Agustus ","/08/")," September ","/09/")," Oktober ","/10/")," November ","/11/")," Desember ","/12/") -> 2026-07-13 | D136: =IFERROR(DATE(VALUE(LEFT(C136,4)),VALUE(MID(C136,6,2)),VALUE(RIGHT(C136,2))),DATE(VALUE(RIGHT(C136,4)),VALUE(MID(C136,4,2)),VALUE(LEFT(C136,2)))) -> 46216 | E136: Jakarta Selatan | F136: =PROPER(TRIM(SUBSTITUTE(SUBSTITUTE(E136,"Jaksel","Jakarta Selatan"),"Tangerang Kota","Tangerang"))) -> Jakarta Selatan | G136: Vino Bastian G. | H136: =IF(G136="","Unknown",G136) -> Vino Bastian G. | I136: Dewi Wijaya | J136: =IF(I136="","Unknown",I136) -> Dewi Wijaya | K136: P003 | L136: Lexi | M136: 1 | N136: 27400000 | O136: 0 | P136: 0 | Q136: =IF(P136=0,"Batal/Refund","Normal") -> Batal/Refund | R136: Cash | S136: Lunas | T136: Online - Website | U136: =COUNTIF($A$2:$A$342,A136) -> 1
A137: TRX-1218 | B137: 2026-07-17 | C137: =SUBSTITUTE(SUBSTITUTE(SUBSTITUTE(SUBSTITUTE(SUBSTITUTE(SUBSTITUTE(SUBSTITUTE(SUBSTITUTE(SUBSTITUTE(SUBSTITUTE(SUBSTITUTE(SUBSTITUTE(B137," Januari ","/01/")," Februari ","/02/")," Maret ","/03/")," April ","/04/")," Mei ","/05/")," Juni ","/06/")," Juli ","/07/")," Agustus ","/08/")," September ","/09/")," Oktober ","/10/")," November ","/11/")," Desember ","/12/") -> 2026-07-17 | D137: =IFERROR(DATE(VALUE(LEFT(C137,4)),VALUE(MID(C137,6,2)),VALUE(RIGHT(C137,2))),DATE(VALUE(RIGHT(C137,4)),VALUE(MID(C137,4,2)),VALUE(LEFT(C137,2)))) -> 46220 | E137: Bandung | F137: =PROPER(TRIM(SUBSTITUTE(SUBSTITUTE(E137,"Jaksel","Jakarta Selatan"),"Tangerang Kota","Tangerang"))) -> Bandung | G137: Hadi Santoso | H137: =IF(G137="","Unknown",G137) -> Hadi Santoso | I137: Rendi Pratama | J137: =IF(I137="","Unknown",I137) -> Rendi Pratama | K137: P003 | L137: Lexi | M137: 1 | N137: 27400000 | O137: 548000 | P137: 26852000 | Q137: =IF(P137=0,"Batal/Refund","Normal") -> Normal | R137: Kredit - Adira | S137: DP | T137: Referral | U137: =COUNTIF($A$2:$A$342,A137) -> 1
A138: TRX-1045 | B138: 2026-07-14 | C138: =SUBSTITUTE(SUBSTITUTE(SUBSTITUTE(SUBSTITUTE(SUBSTITUTE(SUBSTITUTE(SUBSTITUTE(SUBSTITUTE(SUBSTITUTE(SUBSTITUTE(SUBSTITUTE(SUBSTITUTE(B138," Januari ","/01/")," Februari ","/02/")," Maret ","/03/")," April ","/04/")," Mei ","/05/")," Juni ","/06/")," Juli ","/07/")," Agustus ","/08/")," September ","/09/")," Oktober ","/10/")," November ","/11/")," Desember ","/12/") -> 2026-07-14 | D138: =IFERROR(DATE(VALUE(LEFT(C138,4)),VALUE(MID(C138,6,2)),VALUE(RIGHT(C138,2))),DATE(VALUE(RIGHT(C138,4)),VALUE(MID(C138,4,2)),VALUE(LEFT(C138,2)))) -> 46217 | E138: Depok | F138: =PROPER(TRIM(SUBSTITUTE(SUBSTITUTE(E138,"Jaksel","Jakarta Selatan"),"Tangerang Kota","Tangerang"))) -> Depok | G138: Taufik Hidayat | H138: =IF(G138="","Unknown",G138) -> Taufik Hidayat | I138: Oscar Ramadhan | J138: =IF(I138="","Unknown",I138) -> Oscar Ramadhan | K138: P001 | L138: NMAX | M138: 1 | N138: 33500000 | O138: 1675000 | P138: 31825000 | Q138: =IF(P138=0,"Batal/Refund","Normal") -> Normal | R138: Kredit - Adira | S138: Lunas | T138: Showroom | U138: =COUNTIF($A$2:$A$342,A138) -> 1
A139: TRX-1214 | B139: 2026-07-17 | C139: =SUBSTITUTE(SUBSTITUTE(SUBSTITUTE(SUBSTITUTE(SUBSTITUTE(SUBSTITUTE(SUBSTITUTE(SUBSTITUTE(SUBSTITUTE(SUBSTITUTE(SUBSTITUTE(SUBSTITUTE(B139," Januari ","/01/")," Februari ","/02/")," Maret ","/03/")," April ","/04/")," Mei ","/05/")," Juni ","/06/")," Juli ","/07/")," Agustus ","/08/")," September ","/09/")," Oktober ","/10/")," November ","/11/")," Desember ","/12/") -> 2026-07-17 | D139: =IFERROR(DATE(VALUE(LEFT(C139,4)),VALUE(MID(C139,6,2)),VALUE(RIGHT(C139,2))),DATE(VALUE(RIGHT(C139,4)),VALUE(MID(C139,4,2)),VALUE(LEFT(C139,2)))) -> 46220 | E139: Depok | F139: =PROPER(TRIM(SUBSTITUTE(SUBSTITUTE(E139,"Jaksel","Jakarta Selatan"),"Tangerang Kota","Tangerang"))) -> Depok | G139: Umi Kalsum | H139: =IF(G139="","Unknown",G139) -> Umi Kalsum | I139: Fitri Lestari | J139: =IF(I139="","Unknown",I139) -> Fitri Lestari | K139: P004 | L139: Mio | M139: 1 | N139: 18900000 | O139: 0 | P139: 18900000 | Q139: =IF(P139=0,"Batal/Refund","Normal") -> Normal | R139: Kredit - Adira | S139: DP | T139: Showroom | U139: =COUNTIF($A$2:$A$342,A139) -> 1
A140: TRX-1189 | B140: 2026-07-16 | C140: =SUBSTITUTE(SUBSTITUTE(SUBSTITUTE(SUBSTITUTE(SUBSTITUTE(SUBSTITUTE(SUBSTITUTE(SUBSTITUTE(SUBSTITUTE(SUBSTITUTE(SUBSTITUTE(SUBSTITUTE(B140," Januari ","/01/")," Februari ","/02/")," Maret ","/03/")," April ","/04/")," Mei ","/05/")," Juni ","/06/")," Juli ","/07/")," Agustus ","/08/")," September ","/09/")," Oktober ","/10/")," November ","/11/")," Desember ","/12/") -> 2026-07-16 | D140: =IFERROR(DATE(VALUE(LEFT(C140,4)),VALUE(MID(C140,6,2)),VALUE(RIGHT(C140,2))),DATE(VALUE(RIGHT(C140,4)),VALUE(MID(C140,4,2)),VALUE(LEFT(C140,2)))) -> 46219 | E140: Cibubur | F140: =PROPER(TRIM(SUBSTITUTE(SUBSTITUTE(E140,"Jaksel","Jakarta Selatan"),"Tangerang Kota","Tangerang"))) -> Cibubur | G140: Oki Setiawan | H140: =IF(G140="","Unknown",G140) -> Oki Setiawan | I140: Galih Pratama | J140: =IF(I140="","Unknown",I140) -> Galih Pratama | K140: P003 | L140: Lexi | M140: 1 | N140: 27400000 | O140: 0 | P140: 27400000 | Q140: =IF(P140=0,"Batal/Refund","Normal") -> Normal | R140: Debit/Transfer | S140: Lunas | T140: Showroom | U140: =COUNTIF($A$2:$A$342,A140) -> 1
A141: TRX-1109 | B141: 2026-07-15 | C141: =SUBSTITUTE(SUBSTITUTE(SUBSTITUTE(SUBSTITUTE(SUBSTITUTE(SUBSTITUTE(SUBSTITUTE(SUBSTITUTE(SUBSTITUTE(SUBSTITUTE(SUBSTITUTE(SUBSTITUTE(B141," Januari ","/01/")," Februari ","/02/")," Maret ","/03/")," April ","/04/")," Mei ","/05/")," Juni ","/06/")," Juli ","/07/")," Agustus ","/08/")," September ","/09/")," Oktober ","/10/")," November ","/11/")," Desember ","/12/") -> 2026-07-15 | D141: =IFERROR(DATE(VALUE(LEFT(C141,4)),VALUE(MID(C141,6,2)),VALUE(RIGHT(C141,2))),DATE(VALUE(RIGHT(C141,4)),VALUE(MID(C141,4,2)),VALUE(LEFT(C141,2)))) -> 46218 | E141: Depok | F141: =PROPER(TRIM(SUBSTITUTE(SUBSTITUTE(E141,"Jaksel","Jakarta Selatan"),"Tangerang Kota","Tangerang"))) -> Depok | G141: Fajar Nugraha | H141: =IF(G141="","Unknown",G141) -> Fajar Nugraha | I141: Citra Pratama | J141: =IF(I141="","Unknown",I141) -> Citra Pratama | K141: P001 | L141: NMAX | M141: 1 | N141: 33500000 | O141: 670000 | P141: 32830000 | Q141: =IF(P141=0,"Batal/Refund","Normal") -> Normal | R141: Kredit - Mandiri Tunas | S141: DP | T141: Showroom | U141: =COUNTIF($A$2:$A$342,A141) -> 1
... A151: TRX-1279 | B151: 18 Juli 2026 | C151: =SUBSTITUTE(SUBSTITUTE(SUBSTITUTE(SUBSTITUTE(SUBSTITUTE(SUBSTITUTE(SUBSTITUTE(SUBSTITUTE(SUBSTITUTE(SUBSTITUTE(SUBSTITUTE(SUBSTITUTE(B151," Januari ","/01/")," Februari ","/02/")," Maret ","/03/")," April ","/04/")," Mei ","/05/")," Juni ","/06/")," Juli ","/07/")," Agustus ","/08/")," September ","/09/")," Oktober ","/10/")," November ","/11/")," Desember ","/12/") -> 18/07/2026 | D151: =IFERROR(DATE(VALUE(LEFT(C151,4)),VALUE(MID(C151,6,2)),VALUE(RIGHT(C151,2))),DATE(VALUE(RIGHT(C151,4)),VALUE(MID(C151,4,2)),VALUE(LEFT(C151,2)))) -> 46221 | E151: Jakarta Selatan | F151: =PROPER(TRIM(SUBSTITUTE(SUBSTITUTE(E151,"Jaksel","Jakarta Selatan"),"Tangerang Kota","Tangerang"))) -> Jakarta Selatan | G151: Puji Lestari | H151: =IF(G151="","Unknown",G151) -> Puji Lestari | I151: Putra Saputra | J151: =IF(I151="","Unknown",I151) -> Putra Saputra | K151: P003 | L151: Lexi | M151: 1 | N151: 27400000 | O151: 0 | P151: 27400000 | Q151: =IF(P151=0,"Batal/Refund","Normal") -> Normal | R151: Cash | S151: Lunas | T151: Referral | U151: =COUNTIF($A$2:$A$342,A151) -> 1
A152: TRX-1029 | B152: 2026-07-13 | C152: =SUBSTITUTE(SUBSTITUTE(SUBSTITUTE(SUBSTITUTE(SUBSTITUTE(SUBSTITUTE(SUBSTITUTE(SUBSTITUTE(SUBSTITUTE(SUBSTITUTE(SUBSTITUTE(SUBSTITUTE(B152," Januari ","/01/")," Februari ","/02/")," Maret ","/03/")," April ","/04/")," Mei ","/05/")," Juni ","/06/")," Juli ","/07/")," Agustus ","/08/")," September ","/09/")," Oktober ","/10/")," November ","/11/")," Desember ","/12/") -> 2026-07-13 | D152: =IFERROR(DATE(VALUE(LEFT(C152,4)),VALUE(MID(C152,6,2)),VALUE(RIGHT(C152,2))),DATE(VALUE(RIGHT(C152,4)),VALUE(MID(C152,4,2)),VALUE(LEFT(C152,2)))) -> 46216 | E152: Cibubur | F152: =PROPER(TRIM(SUBSTITUTE(SUBSTITUTE(E152,"Jaksel","Jakarta Selatan"),"Tangerang Kota","Tangerang"))) -> Cibubur | H152: =IF(G152="","Unknown",G152) -> Unknown | I152: Rendi Pratama | J152: =IF(I152="","Unknown",I152) -> Rendi Pratama | K152: P003 | L152: Lexi | M152: 1 | N152: 27400000 | O152: 274000 | P152: 27126000 | Q152: =IF(P152=0,"Batal/Refund","Normal") -> Normal | R152: Debit/Transfer | S152: Lunas | T152: Referral | U152: =COUNTIF($A$2:$A$342,A152) -> 1
A153: TRX-1032 | B153: 2026-07-13 | C153: =SUBSTITUTE(SUBSTITUTE(SUBSTITUTE(SUBSTITUTE(SUBSTITUTE(SUBSTITUTE(SUBSTITUTE(SUBSTITUTE(SUBSTITUTE(SUBSTITUTE(SUBSTITUTE(SUBSTITUTE(B153," Januari ","/01/")," Februari ","/02/")," Maret ","/03/")," April ","/04/")," Mei ","/05/")," Juni ","/06/")," Juli ","/07/")," Agustus ","/08/")," September ","/09/")," Oktober ","/10/")," November ","/11/")," Desember ","/12/") -> 2026-07-13 | D153: =IFERROR(DATE(VALUE(LEFT(C153,4)),VALUE(MID(C153,6,2)),VALUE(RIGHT(C153,2))),DATE(VALUE(RIGHT(C153,4)),VALUE(MID(C153,4,2)),VALUE(LEFT(C153,2)))) -> 46216 | E153: Sukabumi | F153: =PROPER(TRIM(SUBSTITUTE(SUBSTITUTE(E153,"Jaksel","Jakarta Selatan"),"Tangerang Kota","Tangerang"))) -> Sukabumi | G153: Doni Saputra | H153: =IF(G153="","Unknown",G153) -> Doni Saputra | I153: Tono Hidayat | J153: =IF(I153="","Unknown",I153) -> Tono Hidayat | K153: P007 | L153: XSR 155 | M153: 2 | N153: 41000000 | O153: 4100000 | P153: 77900000 | Q153: =IF(P153=0,"Batal/Refund","Normal") -> Normal | R153: Kredit - FIF | S153: Proses Kredit | T153: Online - Website | U153: =COUNTIF($A$2:$A$342,A153) -> 1
A154: TRX-1056 | B154: 14 Juli 2026 | C154: =SUBSTITUTE(SUBSTITUTE(SUBSTITUTE(SUBSTITUTE(SUBSTITUTE(SUBSTITUTE(SUBSTITUTE(SUBSTITUTE(SUBSTITUTE(SUBSTITUTE(SUBSTITUTE(SUBSTITUTE(B154," Januari ","/01/")," Februari ","/02/")," Maret ","/03/")," April ","/04/")," Mei ","/05/")," Juni ","/06/")," Juli ","/07/")," Agustus ","/08/")," September ","/09/")," Oktober ","/10/")," November ","/11/")," Desember ","/12/") -> 14/07/2026 | D154: =IFERROR(DATE(VALUE(LEFT(C154,4)),VALUE(MID(C154,6,2)),VALUE(RIGHT(C154,2))),DATE(VALUE(RIGHT(C154,4)),VALUE(MID(C154,4,2)),VALUE(LEFT(C154,2)))) -> 46217 | E154: Bogor | F154: =PROPER(TRIM(SUBSTITUTE(SUBSTITUTE(E154,"Jaksel","Jakarta Selatan"),"Tangerang Kota","Tangerang"))) -> Bogor | G154: Joko Widodo S. | H154: =IF(G154="","Unknown",G154) -> Joko Widodo S. | I154: Citra Saputra | J154: =IF(I154="","Unknown",I154) -> Citra Saputra | K154: P003 | L154: Lexi | M154: 1 | N154: 27400000 | O154: 1370000 | P154: 26030000 | Q154: =IF(P154=0,"Batal/Refund","Normal") -> Normal | R154: Kredit - FIF | S154: Lunas | T154: Pameran | U154: =COUNTIF($A$2:$A$342,A154) -> 1
A155: TRX-1173 | B155: 2026-07-16 | C155: =SUBSTITUTE(SUBSTITUTE(SUBSTITUTE(SUBSTITUTE(SUBSTITUTE(SUBSTITUTE(SUBSTITUTE(SUBSTITUTE(SUBSTITUTE(SUBSTITUTE(SUBSTITUTE(SUBSTITUTE(B155," Januari ","/01/")," Februari ","/02/")," Maret ","/03/")," April ","/04/")," Mei ","/05/")," Juni ","/06/")," Juli ","/07/")," Agustus ","/08/")," September ","/09/")," Oktober ","/10/")," November ","/11/")," Desember ","/12/") -> 2026-07-16 | D155: =IFERROR(DATE(VALUE(LEFT(C155,4)),VALUE(MID(C155,6,2)),VALUE(RIGHT(C155,2))),DATE(VALUE(RIGHT(C155,4)),VALUE(MID(C155,4,2)),VALUE(LEFT(C155,2)))) -> 46219 | E155: Serang | F155: =PROPER(TRIM(SUBSTITUTE(SUBSTITUTE(E155,"Jaksel","Jakarta Selatan"),"Tangerang Kota","Tangerang"))) -> Serang | G155: Umi Kalsum | H155: =IF(G155="","Unknown",G155) -> Umi Kalsum | I155: Fitri Hidayat | J155: =IF(I155="","Unknown",I155) -> Fitri Hidayat | K155: P001 | L155: NMAX | M155: 1 | N155: 33500000 | O155: 335000 | P155: 33165000 | Q155: =IF(P155=0,"Batal/Refund","Normal") -> Normal | R155: Kredit - Mandiri Tunas | S155: Lunas | T155: Showroom | U155: =COUNTIF($A$2:$A$342,A155) -> 1
A156: TRX-1033 | B156: 2026-07-13 | C156: =SUBSTITUTE(SUBSTITUTE(SUBSTITUTE(SUBSTITUTE(SUBSTITUTE(SUBSTITUTE(SUBSTITUTE(SUBSTITUTE(SUBSTITUTE(SUBSTITUTE(SUBSTITUTE(SUBSTITUTE(B156," Januari ","/01/")," Februari ","/02/")," Maret ","/03/")," April ","/04/")," Mei ","/05/")," Juni ","/06/")," Juli ","/07/")," Agustus ","/08/")," September ","/09/")," Oktober ","/10/")," November ","/11/")," Desember ","/12/") -> 2026-07-13 | D156: =IFERROR(DATE(VALUE(LEFT(C156,4)),VALUE(MID(C156,6,2)),VALUE(RIGHT(C156,2))),DATE(VALUE(RIGHT(C156,4)),VALUE(MID(C156,4,2)),VALUE(LEFT(C156,2)))) -> 46216 | E156: Sukabumi | F156: =PROPER(TRIM(SUBSTITUTE(SUBSTITUTE(E156,"Jaksel","Jakarta Selatan"),"Tangerang Kota","Tangerang"))) -> Sukabumi | G156: Rangga Saputra | H156: =IF(G156="","Unknown",G156) -> Rangga Saputra | I156: Citra Anggraini | J156: =IF(I156="","Unknown",I156) -> Citra Anggraini | K156: P008 | L156: MX King | M156: 1 | N156: 24600000 | O156: 0 | P156: 24600000 | Q156: =IF(P156=0,"Batal/Refund","Normal") -> Normal | R156: Kredit - Mandiri Tunas | S156: Lunas | T156: Pameran | U156: =COUNTIF($A$2:$A$342,A156) -> 1
A157: TRX-1219 | B157: 2026-07-17 | C157: =SUBSTITUTE(SUBSTITUTE(SUBSTITUTE(SUBSTITUTE(SUBSTITUTE(SUBSTITUTE(SUBSTITUTE(SUBSTITUTE(SUBSTITUTE(SUBSTITUTE(SUBSTITUTE(SUBSTITUTE(B157," Januari ","/01/")," Februari ","/02/")," Maret ","/03/")," April ","/04/")," Mei ","/05/")," Juni ","/06/")," Juli ","/07/")," Agustus ","/08/")," September ","/09/")," Oktober ","/10/")," November ","/11/")," Desember ","/12/") -> 2026-07-17 | D157: =IFERROR(DATE(VALUE(LEFT(C157,4)),VALUE(MID(C157,6,2)),VALUE(RIGHT(C157,2))),DATE(VALUE(RIGHT(C157,4)),VALUE(MID(C157,4,2)),VALUE(LEFT(C157,2)))) -> 46220 | E157: Bogor | F157: =PROPER(TRIM(SUBSTITUTE(SUBSTITUTE(E157,"Jaksel","Jakarta Selatan"),"Tangerang Kota","Tangerang"))) -> Bogor | G157: Hadi Santoso | H157: =IF(G157="","Unknown",G157) -> Hadi Santoso | I157: Hana Ramadhan | J157: =IF(I157="","Unknown",I157) -> Hana Ramadhan | K157: P005 | L157: Fazzio | M157: 1 | N157: 21500000 | O157: 1075000 | P157: 20425000 | Q157: =IF(P157=0,"Batal/Refund","Normal") -> Normal | R157: Kredit - FIF | S157: Lunas | T157: Showroom | U157: =COUNTIF($A$2:$A$342,A157) -> 1
A158: TRX-1049 | B158: 2026-07-14 | C158: =SUBSTITUTE(SUBSTITUTE(SUBSTITUTE(SUBSTITUTE(SUBSTITUTE(SUBSTITUTE(SUBSTITUTE(SUBSTITUTE(SUBSTITUTE(SUBSTITUTE(SUBSTITUTE(SUBSTITUTE(B158," Januari ","/01/")," Februari ","/02/")," Maret ","/03/")," April ","/04/")," Mei ","/05/")," Juni ","/06/")," Juli ","/07/")," Agustus ","/08/")," September ","/09/")," Oktober ","/10/")," November ","/11/")," Desember ","/12/") -> 2026-07-14 | D158: =IFERROR(DATE(VALUE(LEFT(C158,4)),VALUE(MID(C158,6,2)),VALUE(RIGHT(C158,2))),DATE(VALUE(RIGHT(C158,4)),VALUE(MID(C158,4,2)),VALUE(LEFT(C158,2)))) -> 46217 | E158: Depok | F158: =PROPER(TRIM(SUBSTITUTE(SUBSTITUTE(E158,"Jaksel","Jakarta Selatan"),"Tangerang Kota","Tangerang"))) -> Depok | G158: Eka Putri | H158: =IF(G158="","Unknown",G158) -> Eka Putri | I158: Kevin Wijaya | J158: =IF(I158="","Unknown",I158) -> Kevin Wijaya | K158: P002 | L158: Aerox | M158: 1 | N158: 29800000 | O158: 298000 | P158: 29502000 | Q158: =IF(P158=0,"Batal/Refund","Normal") -> Normal | R158: Kredit - Adira | S158: Proses Kredit | T158: Online - Website | U158: =COUNTIF($A$2:$A$342,A158) -> 1
A159: TRX-1288 | B159: 2026-07-18 | C159: =SUBSTITUTE(SUBSTITUTE(SUBSTITUTE(SUBSTITUTE(SUBSTITUTE(SUBSTITUTE(SUBSTITUTE(SUBSTITUTE(SUBSTITUTE(SUBSTITUTE(SUBSTITUTE(SUBSTITUTE(B159," Januari ","/01/")," Februari ","/02/")," Maret ","/03/")," April ","/04/")," Mei ","/05/")," Juni ","/06/")," Juli ","/07/")," Agustus ","/08/")," September ","/09/")," Oktober ","/10/")," November ","/11/")," Desember ","/12/") -> 2026-07-18 | D159: =IFERROR(DATE(VALUE(LEFT(C159,4)),VALUE(MID(C159,6,2)),VALUE(RIGHT(C159,2))),DATE(VALUE(RIGHT(C159,4)),VALUE(MID(C159,4,2)),VALUE(LEFT(C159,2)))) -> 46221 | E159: Cibubur | F159: =PROPER(TRIM(SUBSTITUTE(SUBSTITUTE(E159,"Jaksel","Jakarta Selatan"),"Tangerang Kota","Tangerang"))) -> Cibubur | G159: Joko Widodo S. | H159: =IF(G159="","Unknown",G159) -> Joko Widodo S. | I159: Budi Lestari | J159: =IF(I159="","Unknown",I159) -> Budi Lestari | K159: P001 | L159: NMAX | M159: 1 | N159: 33500000 | O159: 0 | P159: 33500000 | Q159: =IF(P159=0,"Batal/Refund","Normal") -> Normal | R159: Kredit - Mandiri Tunas | S159: Lunas | T159: Showroom | U159: =COUNTIF($A$2:$A$342,A159) -> 1
A160: TRX-1232 | B160: 2026-07-17 | C160: =SUBSTITUTE(SUBSTITUTE(SUBSTITUTE(SUBSTITUTE(SUBSTITUTE(SUBSTITUTE(SUBSTITUTE(SUBSTITUTE(SUBSTITUTE(SUBSTITUTE(SUBSTITUTE(SUBSTITUTE(B160," Januari ","/01/")," Februari ","/02/")," Maret ","/03/")," April ","/04/")," Mei ","/05/")," Juni ","/06/")," Juli ","/07/")," Agustus ","/08/")," September ","/09/")," Oktober ","/10/")," November ","/11/")," Desember ","/12/") -> 2026-07-17 | D160: =IFERROR(DATE(VALUE(LEFT(C160,4)),VALUE(MID(C160,6,2)),VALUE(RIGHT(C160,2))),DATE(VALUE(RIGHT(C160,4)),VALUE(MID(C160,4,2)),VALUE(LEFT(C160,2)))) -> 46220 | E160: Karawang | F160: =PROPER(TRIM(SUBSTITUTE(SUBSTITUTE(E160,"Jaksel","Jakarta Selatan"),"Tangerang Kota","Tangerang"))) -> Karawang | H160: =IF(G160="","Unknown",G160) -> Unknown | I160: Putra Saputra | J160: =IF(I160="","Unknown",I160) -> Putra Saputra | K160: P001 | L160: NMAX | M160: 1 | N160: 33500000 | O160: 0 | P160: 33500000 | Q160: =IF(P160=0,"Batal/Refund","Normal") -> Normal | R160: Kredit - FIF | S160: Lunas | T160: Online - Website | U160: =COUNTIF($A$2:$A$342,A160) -> 1
A161: TRX-1034 | B161: 2026-07-14 | C161: =SUBSTITUTE(SUBSTITUTE(SUBSTITUTE(SUBSTITUTE(SUBSTITUTE(SUBSTITUTE(SUBSTITUTE(SUBSTITUTE(SUBSTITUTE(SUBSTITUTE(SUBSTITUTE(SUBSTITUTE(B161," Januari ","/01/")," Februari ","/02/")," Maret ","/03/")," April ","/04/")," Mei ","/05/")," Juni ","/06/")," Juli ","/07/")," Agustus ","/08/")," September ","/09/")," Oktober ","/10/")," November ","/11/")," Desember ","/12/") -> 2026-07-14 | D161: =IFERROR(DATE(VALUE(LEFT(C161,4)),VALUE(MID(C161,6,2)),VALUE(RIGHT(C161,2))),DATE(VALUE(RIGHT(C161,4)),VALUE(MID(C161,4,2)),VALUE(LEFT(C161,2)))) -> 46217 | E161: Tangerang | F161: =PROPER(TRIM(SUBSTITUTE(SUBSTITUTE(E161,"Jaksel","Jakarta Selatan"),"Tangerang Kota","Tangerang"))) -> Tangerang | G161: Indah Permata | H161: =IF(G161="","Unknown",G161) -> Indah Permata | I161: Qori Anggraini | J161: =IF(I161="","Unknown",I161) -> Qori Anggraini | K161: P001 | L161: NMAX | M161: 1 | N161: 33500000 | O161: 0 | P161: 33500000 | Q161: =IF(P161=0,"Batal/Refund","Normal") -> Normal | R161: Kredit - Mandiri Tunas | S161: Lunas | T161: Referral | U161: =COUNTIF($A$2:$A$342,A161) -> 1
A162: TRX-1036 | B162: 14 Juli 2026 | C162: =SUBSTITUTE(SUBSTITUTE(SUBSTITUTE(SUBSTITUTE(SUBSTITUTE(SUBSTITUTE(SUBSTITUTE(SUBSTITUTE(SUBSTITUTE(SUBSTITUTE(SUBSTITUTE(SUBSTITUTE(B162," Januari ","/01/")," Februari ","/02/")," Maret ","/03/")," April ","/04/")," Mei ","/05/")," Juni ","/06/")," Juli ","/07/")," Agustus ","/08/")," September ","/09/")," Oktober ","/10/")," November ","/11/")," Desember ","/12/") -> 14/07/2026 | D162: =IFERROR(DATE(VALUE(LEFT(C162,4)),VALUE(MID(C162,6,2)),VALUE(RIGHT(C162,2))),DATE(VALUE(RIGHT(C162,4)),VALUE(MID(C162,4,2)),VALUE(LEFT(C162,2)))) -> 46217 | E162: TANGERANG | F162: =PROPER(TRIM(SUBSTITUTE(SUBSTITUTE(E162,"Jaksel","Jakarta Selatan"),"Tangerang Kota","Tangerang"))) -> Tangerang | G162: Puji Lestari | H162: =IF(G162="","Unknown",G162) -> Puji Lestari | I162: Jihan Pratama | J162: =IF(I162="","Unknown",I162) -> Jihan Pratama | K162: P007 | L162: XSR 155 | M162: 1 | N162: 41000000 | O162: 2050000 | P162: 38950000 | Q162: =IF(P162=0,"Batal/Refund","Normal") -> Normal | R162: Kredit - Adira | S162: Lunas | T162: Pameran | U162: =COUNTIF($A$2:$A$342,A162) -> 1
A163: TRX-1272 | B163: 18/07/2026 | C163: =SUBSTITUTE(SUBSTITUTE(SUBSTITUTE(SUBSTITUTE(SUBSTITUTE(SUBSTITUTE(SUBSTITUTE(SUBSTITUTE(SUBSTITUTE(SUBSTITUTE(SUBSTITUTE(SUBSTITUTE(B163," Januari ","/01/")," Februari ","/02/")," Maret ","/03/")," April ","/04/")," Mei ","/05/")," Juni ","/06/")," Juli ","/07/")," Agustus ","/08/")," September ","/09/")," Oktober ","/10/")," November ","/11/")," Desember ","/12/") -> 18/07/2026 | D163: =IFERROR(DATE(VALUE(LEFT(C163,4)),VALUE(MID(C163,6,2)),VALUE(RIGHT(C163,2))),DATE(VALUE(RIGHT(C163,4)),VALUE(MID(C163,4,2)),VALUE(LEFT(C163,2)))) -> 46221 | E163: Jakarta Timur | F163: =PROPER(TRIM(SUBSTITUTE(SUBSTITUTE(E163,"Jaksel","Jakarta Selatan"),"Tangerang Kota","Tangerang"))) -> Jakarta Timur | G163: Eka Putri | H163: =IF(G163="","Unknown",G163) -> Eka Putri | I163: Hana Anggraini | J163: =IF(I163="","Unknown",I163) -> Hana Anggraini | K163: P001 | L163: NMAX | M163: 1 | N163: 33500000 | O163: 1005000 | P163: 32495000 | Q163: =IF(P163=0,"Batal/Refund","Normal") -> Normal | R163: Cash | S163: Lunas | T163: Referral | U163: =COUNTIF($A$2:$A$342,A163) -> 1
A164: TRX-1064 | B164: 2026-07-14 | C164: =SUBSTITUTE(SUBSTITUTE(SUBSTITUTE(SUBSTITUTE(SUBSTITUTE(SUBSTITUTE(SUBSTITUTE(SUBSTITUTE(SUBSTITUTE(SUBSTITUTE(SUBSTITUTE(SUBSTITUTE(B164," Januari ","/01/")," Februari ","/02/")," Maret ","/03/")," April ","/04/")," Mei ","/05/")," Juni ","/06/")," Juli ","/07/")," Agustus ","/08/")," September ","/09/")," Oktober ","/10/")," November ","/11/")," Desember ","/12/") -> 2026-07-14 | D164: =IFERROR(DATE(VALUE(LEFT(C164,4)),VALUE(MID(C164,6,2)),VALUE(RIGHT(C164,2))),DATE(VALUE(RIGHT(C164,4)),VALUE(MID(C164,4,2)),VALUE(LEFT(C164,2)))) -> 46217 | E164: Serang | F164: =PROPER(TRIM(SUBSTITUTE(SUBSTITUTE(E164,"Jaksel","Jakarta Selatan"),"Tangerang Kota","Tangerang"))) -> Serang | G164: Oki Setiawan | H164: =IF(G164="","Unknown",G164) -> Oki Setiawan | I164: Qori Lestari | J164: =IF(I164="","Unknown",I164) -> Qori Lestari | K164: P006 | L164: Gear | M164: 1 | N164: 17800000 | O164: 0 | P164: 17800000 | Q164: =IF(P164=0,"Batal/Refund","Normal") -> Normal | R164: Debit/Transfer | S164: Lunas | T164: Pameran | U164: =COUNTIF($A$2:$A$342,A164) -> 1
A165: TRX-1158 | B165: 2026-07-16 | C165: =SUBSTITUTE(SUBSTITUTE(SUBSTITUTE(SUBSTITUTE(SUBSTITUTE(SUBSTITUTE(SUBSTITUTE(SUBSTITUTE(SUBSTITUTE(SUBSTITUTE(SUBSTITUTE(SUBSTITUTE(B165," Januari ","/01/")," Februari ","/02/")," Maret ","/03/")," April ","/04/")," Mei ","/05/")," Juni ","/06/")," Juli ","/07/")," Agustus ","/08/")," September ","/09/")," Oktober ","/10/")," November ","/11/")," Desember ","/12/") -> 2026-07-16 | D165: =IFERROR(DATE(VALUE(LEFT(C165,4)),VALUE(MID(C165,6,2)),VALUE(RIGHT(C165,2))),DATE(VALUE(RIGHT(C165,4)),VALUE(MID(C165,4,2)),VALUE(LEFT(C165,2)))) -> 46219 | E165: Bandung | F165: =PROPER(TRIM(SUBSTITUTE(SUBSTITUTE(E165,"Jaksel","Jakarta Selatan"),"Tangerang Kota","Tangerang"))) -> Bandung | G165: Lina Marlina | H165: =IF(G165="","Unknown",G165) -> Lina Marlina | I165: Budi Ramadhan | J165: =IF(I165="","Unknown",I165) -> Budi Ramadhan | K165: P001 | L165: NMAX | M165: 1 | N165: 33500000 | O165: 670000 | P165: 32830000 | Q165: =IF(P165=0,"Batal/Refund","Normal") -> Normal | R165: Kredit - Adira | S165: Lunas | T165: Referral | U165: =COUNTIF($A$2:$A$342,A165) -> 1
A166: TRX-1129 | B166: 2026-07-15 | C166: =SUBSTITUTE(SUBSTITUTE(SUBSTITUTE(SUBSTITUTE(SUBSTITUTE(SUBSTITUTE(SUBSTITUTE(SUBSTITUTE(SUBSTITUTE(SUBSTITUTE(SUBSTITUTE(SUBSTITUTE(B166," Januari ","/01/")," Februari ","/02/")," Maret ","/03/")," April ","/04/")," Mei ","/05/")," Juni ","/06/")," Juli ","/07/")," Agustus ","/08/")," September ","/09/")," Oktober ","/10/")," November ","/11/")," Desember ","/12/") -> 2026-07-15 | D166: =IFERROR(DATE(VALUE(LEFT(C166,4)),VALUE(MID(C166,6,2)),VALUE(RIGHT(C166,2))),DATE(VALUE(RIGHT(C166,4)),VALUE(MID(C166,4,2)),VALUE(LEFT(C166,2)))) -> 46218 | E166: Karawang | F166: =PROPER(TRIM(SUBSTITUTE(SUBSTITUTE(E166,"Jaksel","Jakarta Selatan"),"Tangerang Kota","Tangerang"))) -> Karawang | G166: Kiki Amelia | H166: =IF(G166="","Unknown",G166) -> Kiki Amelia | I166: Made Lestari | J166: =IF(I166="","Unknown",I166) -> Made Lestari | K166: P005 | L166: Fazzio | M166: 1 | N166: 21500000 | O166: 1075000 | P166: 20425000 | Q166: =IF(P166=0,"Batal/Refund","Normal") -> Normal | R166: Kredit - Mandiri Tunas | S166: Lunas | T166: Pameran | U166: =COUNTIF($A$2:$A$342,A166) -> 1
A167: TRX-1047 | B167: 2026-07-14 | C167: =SUBSTITUTE(SUBSTITUTE(SUBSTITUTE(SUBSTITUTE(SUBSTITUTE(SUBSTITUTE(SUBSTITUTE(SUBSTITUTE(SUBSTITUTE(SUBSTITUTE(SUBSTITUTE(SUBSTITUTE(B167," Januari ","/01/")," Februari ","/02/")," Maret ","/03/")," April ","/04/")," Mei ","/05/")," Juni ","/06/")," Juli ","/07/")," Agustus ","/08/")," September ","/09/")," Oktober ","/10/")," November ","/11/")," Desember ","/12/") -> 2026-07-14 | D167: =IFERROR(DATE(VALUE(LEFT(C167,4)),VALUE(MID(C167,6,2)),VALUE(RIGHT(C167,2))),DATE(VALUE(RIGHT(C167,4)),VALUE(MID(C167,4,2)),VALUE(LEFT(C167,2)))) -> 46217 | E167: Depok | F167: =PROPER(TRIM(SUBSTITUTE(SUBSTITUTE(E167,"Jaksel","Jakarta Selatan"),"Tangerang Kota","Tangerang"))) -> Depok | G167: Sari Dewi | H167: =IF(G167="","Unknown",G167) -> Sari Dewi | I167: Citra Pratama | J167: =IF(I167="","Unknown",I167) -> Citra Pratama | K167: P009 | L167: Grand Filano | M167: 1 | N167: 26900000 | O167: 269000 | P167: 26631000 | Q167: =IF(P167=0,"Batal/Refund","Normal") -> Normal | R167: Kredit - Mandiri Tunas | S167: Lunas | T167: Pameran | U167: =COUNTIF($A$2:$A$342,A167) -> 1
A168: TRX-1067 | B168: 2026-07-14 | C168: =SUBSTITUTE(SUBSTITUTE(SUBSTITUTE(SUBSTITUTE(SUBSTITUTE(SUBSTITUTE(SUBSTITUTE(SUBSTITUTE(SUBSTITUTE(SUBSTITUTE(SUBSTITUTE(SUBSTITUTE(B168," Januari ","/01/")," Februari ","/02/")," Maret ","/03/")," April ","/04/")," Mei ","/05/")," Juni ","/06/")," Juli ","/07/")," Agustus ","/08/")," September ","/09/")," Oktober ","/10/")," November ","/11/")," Desember ","/12/") -> 2026-07-14 | D168: =IFERROR(DATE(VALUE(LEFT(C168,4)),VALUE(MID(C168,6,2)),VALUE(RIGHT(C168,2))),DATE(VALUE(RIGHT(C168,4)),VALUE(MID(C168,4,2)),VALUE(LEFT(C168,2)))) -> 46217 | E168: Serang | F168: =PROPER(TRIM(SUBSTITUTE(SUBSTITUTE(E168,"Jaksel","Jakarta Selatan"),"Tangerang Kota","Tangerang"))) -> Serang | G168: Puji Lestari | H168: =IF(G168="","Unknown",G168) -> Puji Lestari | I168: Oscar Saputra | J168: =IF(I168="","Unknown",I168) -> Oscar Saputra | K168: P001 | L168: NMAX | M168: 2 | N168: 33500000 | O168: 670000 | P168: 66330000 | Q168: =IF(P168=0,"Batal/Refund","Normal") -> Normal | R168: Cash | S168: Lunas | T168: Pameran | U168: =COUNTIF($A$2:$A$342,A168) -> 1
A169: TRX-1222 | B169: 2026-07-17 | C169: =SUBSTITUTE(SUBSTITUTE(SUBSTITUTE(SUBSTITUTE(SUBSTITUTE(SUBSTITUTE(SUBSTITUTE(SUBSTITUTE(SUBSTITUTE(SUBSTITUTE(SUBSTITUTE(SUBSTITUTE(B169," Januari ","/01/")," Februari ","/02/")," Maret ","/03/")," April ","/04/")," Mei ","/05/")," Juni ","/06/")," Juli ","/07/")," Agustus ","/08/")," September ","/09/")," Oktober ","/10/")," November ","/11/")," Desember ","/12/") -> 2026-07-17 | D169: =IFERROR(DATE(VALUE(LEFT(C169,4)),VALUE(MID(C169,6,2)),VALUE(RIGHT(C169,2))),DATE(VALUE(RIGHT(C169,4)),VALUE(MID(C169,4,2)),VALUE(LEFT(C169,2)))) -> 46220 | E169: Cikarang | F169: =PROPER(TRIM(SUBSTITUTE(SUBSTITUTE(E169,"Jaksel","Jakarta Selatan"),"Tangerang Kota","Tangerang"))) -> Cikarang | G169: Puji Lestari | H169: =IF(G169="","Unknown",G169) -> Puji Lestari | I169: Nia Wijaya | J169: =IF(I169="","Unknown",I169) -> Nia Wijaya | K169: P007 | L169: XSR 155 | M169: 1 | N169: 41000000 | O169: 0 | P169: 41000000 | Q169: =IF(P169=0,"Batal/Refund","Normal") -> Normal | R169: Kredit - Mandiri Tunas | S169: Proses Kredit | T169: Referral | U169: =COUNTIF($A$2:$A$342,A169) -> 1
A170: TRX-1176 | B170: 2026-07-16 | C170: =SUBSTITUTE(SUBSTITUTE(SUBSTITUTE(SUBSTITUTE(SUBSTITUTE(SUBSTITUTE(SUBSTITUTE(SUBSTITUTE(SUBSTITUTE(SUBSTITUTE(SUBSTITUTE(SUBSTITUTE(B170," Januari ","/01/")," Februari ","/02/")," Maret ","/03/")," April ","/04/")," Mei ","/05/")," Juni ","/06/")," Juli ","/07/")," Agustus ","/08/")," September ","/09/")," Oktober ","/10/")," November ","/11/")," Desember ","/12/") -> 2026-07-16 | D170: =IFERROR(DATE(VALUE(LEFT(C170,4)),VALUE(MID(C170,6,2)),VALUE(RIGHT(C170,2))),DATE(VALUE(RIGHT(C170,4)),VALUE(MID(C170,4,2)),VALUE(LEFT(C170,2)))) -> 46219 | E170: Jakarta Timur | F170: =PROPER(TRIM(SUBSTITUTE(SUBSTITUTE(E170,"Jaksel","Jakarta Selatan"),"Tangerang Kota","Tangerang"))) -> Jakarta Timur | G170: Nanda Pratama | H170: =IF(G170="","Unknown",G170) -> Nanda Pratama | I170: Tono Lestari | J170: =IF(I170="","Unknown",I170) -> Tono Lestari | K170: P004 | L170: Mio | M170: 1 | N170: 18900000 | O170: 0 | P170: 18900000 | Q170: =IF(P170=0,"Batal/Refund","Normal") -> Normal | R170: Kredit - Mandiri Tunas | S170: Lunas | T170: Online - Website | U170: =COUNTIF($A$2:$A$342,A170) -> 1
A171: TRX-1332 | B171: 2026-07-19 | C171: =SUBSTITUTE(SUBSTITUTE(SUBSTITUTE(SUBSTITUTE(SUBSTITUTE(SUBSTITUTE(SUBSTITUTE(SUBSTITUTE(SUBSTITUTE(SUBSTITUTE(SUBSTITUTE(SUBSTITUTE(B171," Januari ","/01/")," Februari ","/02/")," Maret ","/03/")," April ","/04/")," Mei ","/05/")," Juni ","/06/")," Juli ","/07/")," Agustus ","/08/")," September ","/09/")," Oktober ","/10/")," November ","/11/")," Desember ","/12/") -> 2026-07-19 | D171: =IFERROR(DATE(VALUE(LEFT(C171,4)),VALUE(MID(C171,6,2)),VALUE(RIGHT(C171,2))),DATE(VALUE(RIGHT(C171,4)),VALUE(MID(C171,4,2)),VALUE(LEFT(C171,2)))) -> 46222 | E171: Jakarta Selatan | F171: =PROPER(TRIM(SUBSTITUTE(SUBSTITUTE(E171,"Jaksel","Jakarta Selatan"),"Tangerang Kota","Tangerang"))) -> Jakarta Selatan | G171: Rangga Saputra | H171: =IF(G171="","Unknown",G171) -> Rangga Saputra | I171: Rendi Saputra | J171: =IF(I171="","Unknown",I171) -> Rendi Saputra | K171: P001 | L171: NMAX | M171: 1 | N171: 33500000 | O171: 0 | P171: 33500000 | Q171: =IF(P171=0,"Batal/Refund","Normal") -> Normal | R171: Debit/Transfer | S171: Lunas | T171: Referral | U171: =COUNTIF($A$2:$A$342,A171) -> 1
A172: TRX-1341 | B172: 2026-07-19 | C172: =SUBSTITUTE(SUBSTITUTE(SUBSTITUTE(SUBSTITUTE(SUBSTITUTE(SUBSTITUTE(SUBSTITUTE(SUBSTITUTE(SUBSTITUTE(SUBSTITUTE(SUBSTITUTE(SUBSTITUTE(B172," Januari ","/01/")," Februari ","/02/")," Maret ","/03/")," April ","/04/")," Mei ","/05/")," Juni ","/06/")," Juli ","/07/")," Agustus ","/08/")," September ","/09/")," Oktober ","/10/")," November ","/11/")," Desember ","/12/") -> 2026-07-19 | D172: =IFERROR(DATE(VALUE(LEFT(C172,4)),VALUE(MID(C172,6,2)),VALUE(RIGHT(C172,2))),DATE(VALUE(RIGHT(C172,4)),VALUE(MID(C172,4,2)),VALUE(LEFT(C172,2)))) -> 46222 | E172: Sukabumi | F172: =PROPER(TRIM(SUBSTITUTE(SUBSTITUTE(E172,"Jaksel","Jakarta Selatan"),"Tangerang Kota","Tangerang"))) -> Sukabumi | G172: Kiki Amelia | H172: =IF(G172="","Unknown",G172) -> Kiki Amelia | I172: Tono Ramadhan | J172: =IF(I172="","Unknown",I172) -> Tono Ramadhan | K172: P001 | L172: NMAX | M172: 1 | N172: 33500000 | O172: 335000 | P172: 33165000 | Q172: =IF(P172=0,"Batal/Refund","Normal") -> Normal | R172: Debit/Transfer | S172: Lunas | T172: Pameran | U172: =COUNTIF($A$2:$A$342,A172) -> 1
... A174: TRX-1046 | B174: 2026-07-14 | C174: =SUBSTITUTE(SUBSTITUTE(SUBSTITUTE(SUBSTITUTE(SUBSTITUTE(SUBSTITUTE(SUBSTITUTE(SUBSTITUTE(SUBSTITUTE(SUBSTITUTE(SUBSTITUTE(SUBSTITUTE(B174," Januari ","/01/")," Februari ","/02/")," Maret ","/03/")," April ","/04/")," Mei ","/05/")," Juni ","/06/")," Juli ","/07/")," Agustus ","/08/")," September ","/09/")," Oktober ","/10/")," November ","/11/")," Desember ","/12/") -> 2026-07-14 | D174: =IFERROR(DATE(VALUE(LEFT(C174,4)),VALUE(MID(C174,6,2)),VALUE(RIGHT(C174,2))),DATE(VALUE(RIGHT(C174,4)),VALUE(MID(C174,4,2)),VALUE(LEFT(C174,2)))) -> 46217 | E174: Depok | F174: =PROPER(TRIM(SUBSTITUTE(SUBSTITUTE(E174,"Jaksel","Jakarta Selatan"),"Tangerang Kota","Tangerang"))) -> Depok | G174: Nanda Pratama | H174: =IF(G174="","Unknown",G174) -> Nanda Pratama | I174: Putra Hidayat | J174: =IF(I174="","Unknown",I174) -> Putra Hidayat | K174: P002 | L174: Aerox | M174: 1 | N174: 29800000 | O174: 596000 | P174: 29204000 | Q174: =IF(P174=0,"Batal/Refund","Normal") -> Normal | R174: Kredit - FIF | S174: Lunas | T174: Referral | U174: =COUNTIF($A$2:$A$342,A174) -> 1
...

Sheet Clean Sales Transaction
A1: Transaction ID | B1: Date | C1: Branch | D1: Sales Rep | E1: Custumer Name | F1: Product Code | G1: Product Name | H1: Qty | I1: Unit Price | J1: Discount | K1: Total Sales | L1: Status Transaksi | M1: Payment Method | N1: Payment Status | O1: Channel
A2: TRX-1086 | B2: 46217 | C2: Cibubur | D2: Taufik Hidayat | E2: Galih Ramadhan | F2: P001 | G2: NMAX | H2: 1 | I2: 33500000 | J2: 1675000 | K2: 31825000 | L2: Normal | M2: Kredit - Mandiri Tunas | N2: Lunas | O2: Pameran
A3: TRX-1192 | B3: 46219 | C3: Sukabumi | D3: Vino Bastian G. | E3: Made Ramadhan | F3: P001 | G3: NMAX | H3: 1 | I3: 33500000 | J3: 1005000 | K3: 32495000 | L3: Normal | M3: Debit/Transfer | N3: Lunas | O3: Online - Website
A4: TRX-1108 | B4: 46218 | C4: Depok | D4: Joko Widodo S. | E4: Putra Hidayat | F4: P010 | G4: Freego | H4: 1 | I4: 22300000 | J4: 669000 | K4: 21631000 | L4: Normal | M4: Cash | N4: Lunas | O4: Referral
A5: TRX-1106 | B5: 46218 | C5: Depok | D5: Lina Marlina | E5: Hana Anggraini | F5: P008 | G5: MX King | H5: 1 | I5: 24600000 | J5: 0 | K5: 24600000 | L5: Normal | M5: Kredit - Adira | N5: Lunas | O5: Online - Website
A6: TRX-1124 | B6: 46218 | C6: Jakarta Selatan | D6: Fajar Nugraha | E6: Putra Saputra | F6: P007 | G6: XSR 155 | H6: 1 | I6: 41000000 | J6: 0 | K6: 41000000 | L6: Normal | M6: Debit/Transfer | N6: Lunas | O6: Online - Website
A7: TRX-1094 | B7: 46217 | C7: Sukabumi | D7: Hadi Santoso | E7: Galih Kusuma | F7: P001 | G7: NMAX | H7: 1 | I7: 33500000 | J7: 1005000 | K7: 32495000 | L7: Normal | M7: Cash | N7: Lunas | O7: Pameran
A8: TRX-1115 | B8: 46218 | C8: Bogor | D8: Lukman Hakim | E8: Lala Firmansyah | F8: P006 | G8: Gear | H8: 1 | I8: 17800000 | J8: 534000 | K8: 17266000 | L8: Normal | M8: Kredit - Mandiri Tunas | N8: Lunas | O8: Online - Website
A9: TRX-1012 | B9: 46216 | C9: Bandung | D9: Puji Lestari | E9: Oscar Wijaya | F9: P006 | G9: Gear | H9: 1 | I9: 17800000 | J9: 890000 | K9: 16910000 | L9: Normal | M9: Debit/Transfer | N9: Lunas | O9: Online - Website
A10: TRX-1148 | B10: 46219 | C10: Bekasi | D10: Sari Dewi | E10: Made Wijaya | F10: P001 | G10: NMAX | H10: 1 | I10: 33500000 | J10: 670000 | K10: 32830000 | L10: Normal | M10: Cash | N10: Lunas | O10: Referral
A11: TRX-1213 | B11: 46220 | C11: Depok | D11: Eka Putri | E11: Ahmad Hidayat | F11: P001 | G11: NMAX | H11: 1 | I11: 33500000 | J11: 335000 | K11: 33165000 | L11: Normal | M11: Kredit - FIF | N11: Lunas | O11: Showroom
A12: TRX-1340 | B12: 46222 | C12: Cibubur | D12: Kiki Amelia | E12: Eko Kusuma | F12: P007 | G12: XSR 155 | H12: 1 | I12: 41000000 | J12: 0 | K12: 41000000 | L12: Normal | M12: Debit/Transfer | N12: DP | O12: Pameran
A13: TRX-1132 | B13: 46218 | C13: Karawang | D13: Kiki Amelia | E13: Citra Ramadhan | F13: P001 | G13: NMAX | H13: 1 | I13: 33500000 | J13: 1005000 | K13: 32495000 | L13: Normal | M13: Debit/Transfer | N13: Proses Kredit | O13: Referral
... A342: TRX-1038 | B342: 46217 | C342: Bekasi | D342: Oki Setiawan | E342: Rendi Maharani | F342: P001 | G342: NMAX | H342: 1 | I342: 33500000 | J342: 670000 | K342: 32830000 | L342: Normal | M342: Cash | N342: Lunas | O342: Pameran

Sheet Target vs Actual
A1: Status Transaksi | B1: Normal
D2: Actual Sales per Cabang
A3: Row Labels | B3: Sum of Total Sales | D3: Target Revenue | E3: Achievement % | G3: Row Labels | H3: Sum of Total Sales | J3: Target Revenue | K3: Achievement %
A4: Bandung | B4: 906597000 | D4: =SUMIFS('Target Sales'!D:D,'Target Sales'!A:A,A4) -> 520000000 | E4: =B4/D4 -> 1.7434558 | G4: Bandung | H4: 906597000 | J4: 520000000 | K4: 1.7434558
A5: Bekasi | B5: 923721000 | D5: =SUMIFS('Target Sales'!D:D,'Target Sales'!A:A,A5) -> 260000000 | E5: =B5/D5 -> 3.5527731 | G5: Bekasi | H5: 923721000 | J5: 260000000 | K5: 3.5527731
A6: Bogor | B6: 598845000 | D6: =SUMIFS('Target Sales'!D:D,'Target Sales'!A:A,A6) -> 208000000 | E6: =B6/D6 -> 2.8790625 | G6: Bogor | H6: 598845000 | J6: 208000000 | K6: 2.8790625
A7: Cibubur | B7: 800267000 | D7: =SUMIFS('Target Sales'!D:D,'Target Sales'!A:A,A7) -> 468000000 | E7: =B7/D7 -> 1.7099722 | G7: Cibubur | H7: 800267000 | J7: 468000000 | K7: 1.7099722
A8: Cikarang | B8: 760218000 | D8: =SUMIFS('Target Sales'!D:D,'Target Sales'!A:A,A8) -> 260000000 | E8: =B8/D8 -> 2.9239154 | G8: Cikarang | H8: 760218000 | J8: 260000000 | K8: 2.9239154
A9: Depok | B9: 768832000 | D9: =SUMIFS('Target Sales'!D:D,'Target Sales'!A:A,A9) -> 260000000 | E9: =B9/D9 -> 2.9570462 | G9: Depok | H9: 768832000 | J9: 260000000 | K9: 2.9570462
A10: Jakarta Selatan | B10: 918489000 | D10: =SUMIFS('Target Sales'!D:D,'Target Sales'!A:A,A10) -> 468000000 | E10: =B10/D10 -> 1.9625833 | G10: Jakarta Selatan | H10: 918489000 | J10: 468000000 | K10: 1.9625833
A11: Jakarta Timur | B11: 532139000 | D11: =SUMIFS('Target Sales'!D:D,'Target Sales'!A:A,A11) -> 260000000 | E11: =B11/D11 -> 2.0466885 | G11: Jakarta Timur | H11: 532139000 | J11: 260000000 | K11: 2.0466885
A12: Karawang | B12: 862042000 | D12: =SUMIFS('Target Sales'!D:D,'Target Sales'!A:A,A12) -> 312000000 | E12: =B12/D12 -> 2.7629551 | G12: Karawang | H12: 862042000 | J12: 312000000 | K12: 2.7629551
A13: Serang | B13: 650659000 | D13: =SUMIFS('Target Sales'!D:D,'Target Sales'!A:A,A13) -> 468000000 | E13: =B13/D13 -> 1.390297 | G13: Serang | H13: 650659000 | J13: 468000000 | K13: 1.390297
A14: Sukabumi | B14: 924626000 | D14: =SUMIFS('Target Sales'!D:D,'Target Sales'!A:A,A14) -> 468000000 | E14: =B14/D14 -> 1.9756966 | G14: Sukabumi | H14: 924626000 | J14: 468000000 | K14: 1.9756966
A15: Tangerang | B15: 787054000 | D15: =SUMIFS('Target Sales'!D:D,'Target Sales'!A:A,A15) -> 364000000 | E15: =B15/D15 -> 2.1622363 | G15: Tangerang | H15: 787054000 | J15: 364000000 | K15: 2.1622363
A16: Grand Total | B16: 9433489000 | G16: Grand Total | H16: 9433489000

Sheet Product Performance
A1: Status Transaksi | B1: Normal
A3: Row Labels | B3: Sum of Total Sales | C3: Sum of Qty | E3: Row Labels | F3: Sum of Total Sales | G3: Sum of Qty
A4: NMAX | B4: 2631760000 | C4: 80 | E4: NMAX | F4: 2631760000 | G4: 80
A5: Aerox | B5: 1811542000 | C5: 62 | E5: Aerox | F5: 1811542000 | G5: 62
A6: Lexi | B6: 1025034000 | C6: 38 | E6: Lexi | F6: 1025034000 | G6: 38
A7: Fazzio | B7: 691225000 | C7: 33 | E7: Fazzio | F7: 691225000 | G7: 33
A8: XSR 155 | B8: 683880000 | C8: 17 | E8: XSR 155 | F8: 683880000 | G8: 17
A9: MX King | B9: 652638000 | C9: 27 | E9: MX King | F9: 652638000 | G9: 27
A10: Mio | B10: 574938000 | C10: 31 | E10: Mio | F10: 574938000 | G10: 31
A11: Grand Filano | B11: 475323000 | C11: 18 | E11: Grand Filano | F11: 475323000 | G11: 18
A12: Gear | B12: 471700000 | C12: 27 | E12: Gear | F12: 471700000 | G12: 27
A13: Freego | B13: 415449000 | C13: 19 | E13: Freego | F13: 415449000 | G13: 19
A14: Grand Total | B14: 9433489000 | C14: 352

Sheet Sales Rep Performance
A1: Status Transaksi | B1: Normal
A3: Row Labels | B3: Count of Transaction ID | C3: Sum of Total Sales | D3: Sum of Qty | F3: Row Labels | G3: Count of Transaction ID | H3: Sum of Total Sales | I3: Sum of Qty
A4: Lukman Hakim | B4: 27 | C4: 668561000 | D4: 30 | F4: Lukman Hakim | G4: 27 | H4: 668561000 | I4: 30
A5: Kiki Amelia | B5: 20 | C5: 566792000 | D5: 20 | F5: Kiki Amelia | G5: 20 | H5: 566792000 | I5: 20
A6: Rangga Saputra | B6: 20 | C6: 554821000 | D6: 21 | F6: Rangga Saputra | G6: 20 | H6: 554821000 | I6: 21
A7: Sari Dewi | B7: 19 | C7: 538697000 | D7: 20 | F7: Sari Dewi | G7: 19 | H7: 538697000 | I7: 20
A8: Taufik Hidayat | B8: 19 | C8: 524072000 | D8: 19 | F8: Taufik Hidayat | G8: 19 | H8: 524072000 | I8: 19
A9: Puji Lestari | B9: 17 | C9: 522417000 | D9: 18 | F9: Puji Lestari | G9: 17 | H9: 522417000 | I9: 18
A10: Umi Kalsum | B10: 19 | C10: 507562000 | D10: 20 | F10: Umi Kalsum | G10: 19 | H10: 507562000 | I10: 20
A11: Joko Widodo S. | B11: 17 | C11: 490679000 | D11: 18 | F11: Joko Widodo S. | G11: 17 | H11: 490679000 | I11: 18
A12: Indah Permata | B12: 17 | C12: 478850000 | D12: 19 | F12: Indah Permata | G12: 17 | H12: 478850000 | I12: 19
A13: Hadi Santoso | B13: 18 | C13: 466106000 | D13: 18 | F13: Hadi Santoso | G13: 18 | H13: 466106000 | I13: 18
A14: Fajar Nugraha | B14: 15 | C14: 453537000 | D14: 16 | F14: Fajar Nugraha | G14: 15 | H14: 453537000 | I14: 16
A15: Vino Bastian G. | B15: 17 | C15: 451581000 | D15: 17 | F15: Vino Bastian G. | G15: 17 | H15: 451581000 | I15: 17
... A24: Rudi Hartono | B24: 9 | C24: 261338000 | D24: 10 | F24: Rudi Hartono | G24: 9 | H24: 261338000 | I24: 10
A25: Grand Total | B25: 336 | C25: 9433489000 | D25: 352

Sheet Dashboard
G2: SALES PERFORMANCE REPORT — MINGGU 29 (13-19 JULI 2026)
E4: TOTAL REVENUE | J4: TOTAL UNIT TERJUAL | N4: AVG ACHIEVEMENT %
E5: =SUM('Clean Sales Transaction'!K:K) -> 9433489000 | J5: =SUMIFS('Clean Sales Transaction'!H:H,'Clean Sales Transaction'!L:L,"Normal") -> 352 | N5: =AVERAGE('Target vs Actual'!E4:E15) -> 2.3388902

Sheet Target Sales
A1: Branch | B1: Week | C1: Target Unit | D1: Target Revenue
A2: Tangerang | B2: 2026-W29 (13-19 Jul 2026) | C2: 14 | D2: 364000000
A3: Bekasi | B3: 2026-W29 (13-19 Jul 2026) | C3: 10 | D3: 260000000
A4: Depok | B4: 2026-W29 (13-19 Jul 2026) | C4: 10 | D4: 260000000
A5: Bandung | B5: 2026-W29 (13-19 Jul 2026) | C5: 20 | D5: 520000000
A6: Bogor | B6: 2026-W29 (13-19 Jul 2026) | C6: 8 | D6: 208000000
A7: Cikarang | B7: 2026-W29 (13-19 Jul 2026) | C7: 10 | D7: 260000000
A8: Serang | B8: 2026-W29 (13-19 Jul 2026) | C8: 18 | D8: 468000000
A9: Jakarta Timur | B9: 2026-W29 (13-19 Jul 2026) | C9: 10 | D9: 260000000
A10: Jakarta Selatan | B10: 2026-W29 (13-19 Jul 2026) | C10: 18 | D10: 468000000
A11: Karawang | B11: 2026-W29 (13-19 Jul 2026) | C11: 12 | D11: 312000000
A12: Cibubur | B12: 2026-W29 (13-19 Jul 2026) | C12: 18 | D12: 468000000
A13: Sukabumi | B13: 2026-W29 (13-19 Jul 2026) | C13: 18 | D13: 468000000

Sheet Branch Master
A1: Branch Code | B1: Branch Name | C1: City | D1: Region | E1: Branch Manager
A2: BR01 | B2: Tangerang | C2: Tangerang | D2: Banten | E2: Andi Wijaya
A3: BR02 | B3: Bekasi | C3: Bekasi | D3: Jawa Barat | E3: Siti Nuraini
A4: BR03 | B4: Depok | C4: Depok | D4: Jawa Barat | E4: Budi Santoso
A5: BR04 | B5: Bandung | C5: Bandung | D5: Jawa Barat | E5: Rina Marlina
A6: BR05 | B6: Bogor | C6: Bogor | D6: Jawa Barat | E6: Dedi Kurniawan
A7: BR06 | B7: Cikarang | C7: Cikarang | D7: Jawa Barat | E7: Yusuf Hakim
A8: BR07 | B8: Serang | C8: Serang | D8: Banten | E8: Maya Sari
A9: BR08 | B9: Jakarta Timur | C9: Jakarta | D9: DKI Jakarta | E9: Fajar Ramadhan
A10: BR09 | B10: Jakarta Selatan | C10: Jakarta | D10: DKI Jakarta | E10: Wulan Dari
A11: BR10 | B11: Karawang | C11: Karawang | D11: Jawa Barat | E11: Hendra Gunawan
A12: BR11 | B12: Cibubur | C12: Jakarta Timur | D12: DKI Jakarta | E12: Putri Ayu
A13: BR12 | B13: Sukabumi | C13: Sukabumi | D13: Jawa Barat | E13: Agus Salim

Sheet Product Master
A1: Product Code | B1: Product Name | C1: Category | D1: Unit Price
A2: P001 | B2: NMAX | C2: Skutik Premium | D2: 33500000
A3: P002 | B3: Aerox | C3: Skutik Sport | D3: 29800000
A4: P003 | B4: Lexi | C4: Skutik Premium | D4: 27400000
A5: P004 | B5: Mio | C5: Skutik Entry | D5: 18900000
A6: P005 | B6: Fazzio | C6: Skutik Entry | D6: 21500000
A7: P006 | B7: Gear | C7: Skutik Entry | D7: 17800000
A8: P007 | B8: XSR 155 | C8: Sport | D8: 41000000
A9: P008 | B9: MX King | C9: Bebek Sport | D9: 24600000
A10: P009 | B10: Grand Filano | C10: Skutik Premium | D10: 26900000
A11: P010 | B11: Freego | C11: Skutik Entry | D11: 22300000

Sheet Data Profiling
A1: DATA PROFILING - SALES PERFORMANCE REPORT
A2: Periode: 13-19 Juli 2026
A4: Total Baris (Sales Transaction) | B4: =COUNTA('Cleaning Sales Transaction'!A:A)-1 -> 341
A5: Missing - Sales Rep | B5: =COUNTBLANK('Cleaning Sales Transaction'!G2:K342) -> 14
A6: Missing - Customer Name | B6: =COUNTBLANK('Cleaning Sales Transaction'!I2:I342) -> 2
A7: Duplicate Records | B7: =COUNTIF('Cleaning Sales Transaction'!U2:U342,">1") -> 0
A8: Transaksi Total Sales = 0 | B8: =COUNTIF('Cleaning Sales Transaction'!P2:P342,0) -> 5
